Workbook

Sheet Instructions
A1: Diagnostic de restauration
A2: Version 2.0 - Mise à jour en 2026
B4: Informations générales | H4: Comment fonctionne le diagnostic ? | N4: Autres considérations
B5: Bienvenue dans l'outil de diagnostic de restauration de WRI ! Un outil d'évaluation rapide permettant d'évaluer l'état de préparation d'une zone géographique ou d'une échelle donnée pour la restauration et de concevoir des actions stratégiques garantissant le succès à long terme. Un outil autonome développé dans le cadre de ROAM (méthodologie d'évaluation des opportunités de restauration) https://iucn.org/resources/grey-literature/guide-restoration-opportunities-assessment-methodology-roam | H5: Le diagnostic suit un processus en trois étapes ; il est vivement recommandé de lire la section précédente avant de commencer. De plus, une étape préparatoire est suggérée. Consultez l'onglet « Avant de commencer ». Chaque étape correspond à une section de l'outil et est expliquée dans un onglet distinct de ce document : Étape 1. Définir le périmètre ; Étape 2. Évaluer les facteurs clés pour la restauration ; Étape 3. Proposer des stratégies pour remédier aux lacunes L'onglet « Tableau récapitulatif » génère un tableau récapitulatif à partir des données saisies aux étapes 1, 2 et 3. | N5: Calendrier proposé pour la mise en œuvre du diagnostic Étape 1. Définir le champ d'application 2 à 3 jours Étape 2. Évaluer les facteurs clés pour la restauration 2 à 4 semaines Étape 3. Choisir des mesures pour remédier aux lacunes. 2 à 3 semaines Le calendrier proposé donne une estimation indicative du temps nécessaire à la réalisation du diagnostic. La durée effective peut varier en fonction du contexte, de e champ d'application de l'évaluation, de la disponibilité des informations, des processus de participation des parties prenantes et du temps alloué par l'équipe chargée de la mise en œuvre. Dans certains cas, les étapes peuvent se prolonger s'il est nécessaire de mener des consultations supplémentaires, de collecter des données ou de mener à bien des processus de validation. Au contraire, le processus peut avancer plus rapidement lorsque les informations et les parties prenantes sont facilement accessibles.
B10: Qu'est-ce que l'outil de diagnostic de restauration ? Le diagnostic de restauration vous aide à déterminer si les facteurs clés culturels, financiers, politiques, institutionnels et écologiques nécessaires à la réussite de la restauration des écosystèmes sont réunis. En identifiant les lacunes et les défis, vous pouvrez passer d'une planification générale à une action concrète et efficace.
B14: En quoi cet outil est-il utile ? Un diagnostic permet d'identifier les facteurs clés qui influencent la réussite de la restauration et de planifier et d'agir de manière plus stratégique.
B17: Suis-je la personne qu'il faut pour utiliser cet outil ? Vous devriez utiliser cet outil si vous êtes chargé de planifier ou de coordonner des politiques, des actions et des mesures de restauration au niveau national ou régional et que vous souhaitez connaître les conditions actuelles nécessaires à la réussite d'une restauration.
N19: Quel est le résultat final de ce diagnostic ? Le diagnostic permet de parvenir à un consensus sur les facteurs clés qui influencent la réussite de la restauration et de définir un ensemble de mesures prioritaires visant à renforcer ces facteurs et à rendre possible la restauration dans la zone ou à l'échelle prévues.
H21: La rubrique « Conseils supplémentaires » fournit davantage de détails sur chaque facteur clé afin de vous aider à formuler vos réponses à l'étape 2.
B22: Remarque concernant la participation : Même si une seule personne peut se charger de la saisie des données, cet outil s'avère plus efficace lorsqu'il est utilisé de manière participative, recueillant les points de vue de diverses parties prenantes et d'experts.
B27: Quels sont les facteurs clés ? Les facteurs clés sont les conditions et les éléments qui influencent la réussite et la viabilité à long terme des initiatives de restauration. Parmi ces facteurs figurent, par exemple, les avantages liés à la restauration, les connaissances disponibles en la matière, les conditions du marché et les politiques relatives à la restauration, entre autres. À titre de référence, l'étape 2 comprend une liste complète des conditions favorables et des facteurs clés.
N29: Documents à rassembler au préalable (liste non exhaustive) +Plans, stratégies ou programmes nationaux de restauration +Engagements en matière de restauration dans le cadre de la CCNUCC et de la CDB +Lois ou politiques relatives à la restauration des écosystèmes forestiers, agricoles ou autres écosystèmes pertinents +Documentation infranationale sur les actions de restauration +Plans de développement municipal dans les paysages cibles
H30: Si vous souhaitez en savoir plus sur la manière dont cet outil a été élaboré, vous pouvez consulter une explication détaillée du diagnostic en ligne à l'adresse suivante : XXXX
B35: Utilisation des données : Vos données seront utilisées conformément à la politique de confidentialité de WRI, disponible via le lien suivant : https://www.wri.org/about/privacy-policy. Nous tenons à souligner que vous pouvez interagir avec WRI en ligne par le biais de divers sites web, applications, outils de diagnostic, outils numériques, enquêtes, courriels, pages sur les réseaux sociaux et autres services en ligne grâce auxquels nous menons des recherches, des activités programmatiques, des actions de communication ou des initiatives de participation (collectivement, les « Services »).

Sheet Avant de commencer
B1: Avant de commencer
B3: Avant de commencer
B4: Pourquoi passer cette étape ? Cette phase de préparation contribue à garantir que le diagnostic se déroule sans encombre et aboutisse à des résultats auxquels les parties prenantes peuvent se fier et sur lesquels elles peuvent s'appuyer pour agir. Cela permet de garantir : Composition : Les rôles et les responsabilités sont clairement définis. Inclusion : Les parties prenantes concernées sont associées au processus. Efficacité : Les informations et les documents essentiels sont déjà prêts.
B6: Comment mener à bien cette étape
B7: 1. Désigner un responsable du processus Désigner une personne chargée de coordonner le diagnostic et de compiler les résultats. 2. Définir la participation des parties prenantes Choisissez la manière dont les parties prenantes contribueront : Ateliers consacrés aux discussions de groupe et aux échanges rapides Entretiens sur des thèmes spécifiques Contributions à distance d'experts techniques intervenant à distance 3. Rassembler les éléments clés Rassembler les documents et les données pertinents à l'appui de l'évaluation
B9: Conception de la participation des parties prenantes
B10: Commencez par analyser le contexte social du secteur de la restauration : qui sont les clients, qui est concerné et qui a de l'influence. Identifiez les besoins, les motivations et les relations entre les parties prenantes afin de comprendre où peuvent surgir des frictions ou des points de convergence. Tirez parti de ces informations pour concevoir des points de contact — ateliers, entretiens, processus de retour d'information — qui soient inclusifs, itératifs et adaptés au contexte. Considérez les parties prenantes comme des co-concepteurs, et non pas simplement comme des sources de données, afin d'améliorer la convivialité, la pertinence et l'acceptation de l'outil. Outil recommandé pour cartographier les paysages sociaux : https://www.wri.org/research/mapping-social-landscapes-guide-identifying-networks-priorities-and-values-restoration
B17: Documents qu'il est recommandé de rassembler (liste non exhaustive)
B18: □ A. Contexte réglementaire et juridique [ ] Stratégies ou programmes nationaux de restauration. [ ] Lois et règlements (sylviculture, agriculture, aménagement du territoire, ressources en eau). [ ] Engagements internationaux (CCNUCC, CDB, CNULD). [ ] Plans nationaux de développement et contributions déterminées au niveau national (CDN). □ B. Mise en œuvre et planification [ ] Plans d'action de restauration au niveau infranational ou régional. [ ] Plans d'aménagement communal pour les paysages concernés. [ ] Documentation relative aux programmes financés par des bailleurs de fonds. [ ] Budgets institutionnels et organigrammes existants. □ C. Données biophysiques et socio-économiques [ ] Évaluations de la couverture du sol et de la dégradation des sols. [ ] Cartes des opportunités de restauration (par exemple, résultats du projet ROAM). [ ] Données socio-économiques (régime foncier, dépendance vis-à-vis des moyens de subsistance, analyse de marché). □ D. Suivi et valeurs de référence [ ] Données issues de systèmes de surveillance du paysage (par exemple, Global Forest Watch). [ ] Indicateurs de restauration existants et rapports d'avancement antérieurs.
B20: Garantir l'inclusion et l'équité
B21: Il se peut que certains participants hésitent à prendre la parole lors des discussions de groupe, et les dynamiques sociales et de genre locales peuvent exclure certains groupes. L'équipe de coordination devrait adapter les méthodes de participation afin de garantir la prise en compte de différents points de vue. Voici comment procéder : • organisez des groupes de discussion distincts pour les femmes et/ou les communautés autochtones • utilisez les langues locales • faites appel à des intermédiaires de confiance • proposez une aide au transport ou une compensation financière si nécessaire • concluez des accords pour garantir un espace sûr • permettez une participation anonyme par écrit pour les questions sensibles

Sheet Étape 1. Définir le champ d'app
B1: Étape 1. Définir le champ d'application
B3: Pourquoi cette étape est-elle importante ?
B4: À cette étape, vous pouvez prendre le temps de définir clairement la portée de l'évaluation. Cela implique notamment de déterminer le lieu où le diagnostic sera réalisé, le délai prévu et les objectifs de la restauration du paysage. Prendre ces décisions dès le début permet de s'assurer que le diagnostic porte sur les aspects, les parties prenantes et les possibilités de redressement pertinents.
B7: Sélectionnez la zone géographique et les types d'écosystèmes
B8: Définissez le contexte géographique, l'échelle ou le paysage dans lequel le diagnostic sera réalisé. Il est important de choisir la zone géographique appropriée, car celle-ci détermine les écosystèmes à évaluer, les parties prenantes à associer et les options de restauration pertinentes. Cela peut inclure : National Sous-national (c'est-à-dire commune, province, district) Paysage (ou paysage marin, le cas échéant) Zone de restauration Transfrontalier (c'est-à-dire deux pays ou plus)
B14: Types d'écosystèmes de pêche
B15: La liste suivante des écosystèmes est donnée à titre indicatif.
B16: Référence : Classification mondiale des écosystèmes de l'UICN 2.0
B17: https://portals.iucn.org/library/sites/library/files/documents/2020-037-En.pdf, https://global-ecosystems.org/
B18: Terrestre | F18: Eau douce | I18: Marine
B19: Forêts tropicales et subtropicales | F19: Tourbières | I19: Plates-formes maritimes
B20: Forêts et zones boisées tempérées et boréales | F20: Zones humides | I20: Mangroves et écosystèmes côtiers
B21: Broussailles et forêts arbustives | F21: Écosystèmes riverains | I21: Les grands fonds marins
B22: Savanes et prairies | F22: Bassins versants
B23: Déserts et semi-déserts | F23: Eaux douces artificielles
B24: Polaire-alpin
B25: Systèmes de production et agricoles
B26: Paysages urbains
B28: Définir l'horizon temporel
B29: Déterminez jusqu'où le projet de restauration devrait aller à l'avenir. La restauration est un processus de longue haleine. Même si certains avantages peuvent se manifester rapidement, de nombreux résultats écologiques et sociaux mettent des années à se concrétiser. Fixer un délai précis permet de définir des attentes réalistes et garantit que les initiatives de restauration s'inscrivent dans le cadre des politiques et des cycles de planification existants. Misez sur une vision à long terme, même si les mesures sont mises en œuvre à court terme. Dans la mesure du possible, il convient d'aligner le calendrier sur les cadres de planification nationaux ou régionaux.
B31: Définir les objectifs de restauration
B32: Précisez ce que vous souhaitez obtenir grâce à la restauration du paysage. Les objectifs de restauration peuvent porter sur un seul écosystème (comme les forêts ou les mangroves) ou sur une combinaison d'écosystèmes et d'utilisations des sols, y compris les systèmes agricoles ou agroforestiers. Les objectifs peuvent être décrits aussi bien avant qu'après la réalisation du diagnostic, selon le contexte et la manière dont ce diagnostic est effectué. Parmi les objectifs habituels de la restauration, on peut citer (liste non exhaustive): - Préservation de la biodiversité - Atténuation du changement climatique ou adaptation à celui-ci - Amélioration des moyens de subsistance - Sécurité de l'approvisionnement en eau - Production alimentaire Des objectifs clairement définis permettent de déterminer quelles options de restauration sont prises en compte et aident les parties prenantes à s'accorder sur la manière dont le succès sera évalué.
B34: Valider la portée avec les parties prenantes
B35: Avant de poursuivre, veuillez confirmer la portée du projet avec les parties prenantes concernées. Une validation précoce contribue à instaurer la confiance, à établir une compréhension commune et à susciter un sentiment d'implication dans le processus de diagnostic. De plus, cela permet de garantir que l'évaluation reflète les priorités et les réalités locales.

Sheet Étape 2. Évaluer les facteurs
A1: Étape 2. Évaluez les facteurs clés de la restauration en choisissant une réponse pour chacune des questions suivantes. Une définition est proposée, ainsi qu'une série de questions complémentaires permettant d'obtenir davantage d'informations.
B3: Objectif L'étape 2 consiste à évaluer si les facteurs clés de la réussite de la restauration des écosystèmes sont actuellement : • En service • Partiellement en service • Hors service L'objectif n'est pas de procéder à une analyse exhaustive de chaque aspect du processus de restauration, mais d'identifier rapidement les points forts, les points faibles et les obstacles potentiels à une restauration réussie. Structure de l'évaluation L'évaluation s'articule autour de trois thèmes généraux : 1. Motiver : facteurs qui inspirent ou motivent afin de stimuler les processus menant à la restauration 2. Facteurs favorables : éléments créant un contexte propice à la restauration 3. Mise en œuvre : facteurs liés aux capacités et aux ressources nécessaires pour mener à bien la mise en œuvre des mesures de restauration sur le terrain | K3: Le code couleur a la signification suivante :
K4: Vert = EN PLACE
K5: Jaune = PARTIELLEMENT EN PLACE
K6: Rouge = PAS EN PLACE
K7: Blanc : N'APPLIQUE PAS
B12: Condition habilitante | C12: Facteur clé | D12: Question | E12: Réponse | F12: National | G12: Régional | H12: Local | I12: Definition | J12: Orientation | K12: Question(s) de suivi | L12: Réponses complémentaires, justification et pièces justificatives
A13: Motiver | B13: a. Avantages | C13: 1. La restauration génère des avantages économiques | D13: • La restauration de la zone ciblée devrait-elle générer des avantages économiques se traduisant par un impact financier ou économique net positif au niveau de l'ensemble de l'économie par rapport à l'utilisation actuelle des terres ? | I13: La restauration de la zone ciblée devrait générer des avantages économiques (par exemple, diversification économique, dommages évités, nouveaux produits commercialisables) qui créeront un impact financier net positif (avantages privés) et/ou un impact net positif sur l'ensemble de l'économie (avantages publics) par rapport à l'utilisation actuelle des terres. Remarque : « Les impacts économiques qui font référence aux avantages environnementaux qui fonctionnent comme des biens publics, ou aux impacts économiques à l’échelle de l’économie qui rendent compte des effets indirects liés à la restauration sur les chaînes de valeur et l’économie en général, y compris la croissance du PIB et l’emploi. » Ces impacts découlent souvent d'avantages économiques tels que la diversification, les dommages évités et les nouveaux produits commercialisés rendus possibles par la restauration. | J13: • Les avantages économiques de la restauration correspondent aux résultats positifs globaux en termes de revenus ou de finances qui découlent de la mise en œuvre d'activités de restauration par rapport à un scénario inchangé. • Parmi les exemples de bénéfices économiques, on peut citer une augmentation des revenus, de meilleures opportunités commerciales, une production accrue de produits de base essentiels ou de nouvelles opportunités d'emploi résultant des efforts de restauration. Une liste plus complète des bénéfices potentiels figure dans cet outil, dans le tableau « Bénéfices de la restauration ». • Le cadre temporel de cette réponse doit tenir compte du calendrier des activités de restauration prévues, en reconnaissant que les processus de restauration et leurs avantages s’inscrivent dans le long terme. • Dans la mesure du possible, distinguez les avantages à court, moyen et long terme, y compris les résultats attendus une fois la restauration pleinement mise en œuvre. • Notez quelles personnes ou quels groupes sont susceptibles de bénéficier de ces avantages. • Certains propriétaires fonciers peuvent craindre que la « restauration » ne signifie la perte de leurs terres, de leurs droits d’usage ou de leurs revenus par rapport au statu quo. Par conséquent, la réponse à cette question peut être étayée par des documents montrant que les avantages nets l’emportent sur les coûts. Remarque : la formalisation des droits fonciers pourrait constituer un avantage connexe positif du projet de restauration. Dans certains cas, la mise en œuvre du projet et le déblocage de fonds pour soutenir les activités de restauration peuvent nécessiter une définition claire des droits fonciers. Par conséquent, cela pourrait accélérer les processus de délimitation et permettre aux communautés locales d’obtenir des titres légaux sur leurs terres. | K13: • Si la réponse est « oui », quels sont les avantages économiques attendus ? • Si la réponse est « oui », qui en bénéficie ? • Si la réponse est « non », quelle est l’ampleur du déficit financier ou économique anticipé ?
C14: 2. La restauration génère des avantages sociaux | D14: • La restauration de la zone ciblée devrait-elle générer des avantages sociaux, culturels ou politiques pour les personnes qui y vivent, notamment les groupes des femmes, des jeunes et des peuples autochtones ? | I14: La restauration de la zone ciblée devrait améliorer les conditions de vie, rehausser le statut social ou politique des populations, sauvegarder ou restaurer les sites du patrimoine culturel naturel ou l'utilisation de pratiques culturellement importantes, ou produire d'autres avantages sociaux, culturels et/ou politiques pour la population locale. | J14: • Consultez la liste des avantages sociaux potentiels dans le tableau « Avantages de la restauration », qui figure dans les documents d'accompagnement de cet outil. Par exemple, les activités de restauration peuvent apporter des avantages d'ordre social, culturel ou politique, tels qu'une meilleure mise en valeur des valeurs culturelles, la reconnaissance des savoirs écologiques traditionnels, la réalisation d'objectifs politiques, l'augmentation des possibilités de loisirs ou l'amélioration de l'égalité entre les sexes. La restauration peut également permettre aux gouvernements d’être perçus comme des leaders sur la scène mondiale et de respecter les engagements pris dans le cadre d’accords internationaux (par exemple, la CCNUCC, la CNULD, la CNUDB, REDD+, les ODD). En outre, la restauration peut être bénéfique pour les pays ou les communautés ayant un lien culturel historique avec les forêts ou d’autres écosystèmes (par exemple, traditions et folklore liés aux forêts, moyens de subsistance et emplois liés aux écosystèmes). • Vérifiez si les avantages énumérés dans le tableau sont reconnus ou pris en compte dans les plans, programmes ou activités de restauration au sein du paysage cible. • Dans la mesure du possible, distinguez les avantages sociaux à court, moyen et long terme, y compris les résultats attendus une fois la restauration pleinement mise en œuvre. • Notez quelles personnes ou quels groupes sont susceptibles de bénéficier de ces avantages. | K14: • Si la réponse est « oui », quels sont les avantages sociaux attendus ? | L14: ·
C15: 3. La restauration génère des avantages environnementaux | D15: • La restauration de la zone ciblée devrait-elle générer des bénéfices environnementaux ? | I15: La restauration de la zone ciblée devrait générer des avantages environnementaux substantiels et durables, notamment la conservation et le rétablissement de la biodiversité, une meilleure atténuation et une meilleure adaptation aux changements climatiques, une réduction de la dégradation des terres et de la désertification, ainsi que la restauration de services écosystémiques essentiels tels que la régulation de l'eau, la fertilité des sols et la séquestration du carbone. Ces améliorations contribueront à accroître la résilience écologique et à assurer des moyens de subsistance durables au fil du temps. | J15: • Parmi les exemples de bénéfices environnementaux, on peut citer, entre autres, une plus grande biodiversité, une meilleure sécurité des bassins versants, une meilleure atténuation et adaptation au changement climatique, ainsi qu'une meilleure fertilité des sols. Une description plus complète des bénéfices environnementaux attendus est fournie dans les documents d'accompagnement de ce diagnostic. Tableau « Bénéfices de la restauration ». • Dans la mesure du possible, distinguez les avantages environnementaux à court, moyen et long terme, y compris les résultats attendus une fois la restauration entièrement mise en œuvre. | K15: • Quels avantages pourraient en découler ? • Comment la communication avec les principales parties prenantes a-t-elle été spécifiquement orientée ou intégrée ? | L15: ·
B16: b. Conscience | C16: 4. Les avantages de la restauration sont communiqués publiquement | D16: • Les avantages de la restauration de la zone ciblée sont-ils communiqués à toutes les parties prenantes, y compris tous les groupes de la population, et les canaux de communication sont-ils conçus pour atteindre ces diverses parties prenantes ? | I16: Les avantages de la restauration de la zone ciblée ont été clairement communiqués aux gestionnaires fonciers, aux groupes vulnérables et aux autres parties prenantes. | J16: • La communication peut se faire par divers canaux, notamment des articles, la presse, les médias sociaux, la radio et la télévision, des visites de démonstration, du théâtre de rue ou d'autres moyens destinés aux parties prenantes et aux décideurs concernés. • La communication entre pairs sur les avantages de la restauration peut être un moyen efficace de sensibiliser et de motiver l'action. • Déterminez si cette communication s’inscrit dans une stratégie plus large de mobilisation des parties prenantes. • Une liste plus complète des avantages est incluse dans les documents d’aide au diagnostic, dans le tableau « Avantages de la restauration ». | K16: • What benefits might arise? • How has the communication specifically targeted or included key stakeholders? | L16: ·
C17: 5. Les possibilités de restauration sont identifiées | D17: • Les zones susceptibles d'être restaurées ont été identifiées et quantifiées ? | I17: Les zones propices à la restauration ont été identifiées et quantifiées. | J17: • Les zones cibles de restauration sont les endroits où les efforts de restauration devraient être entrepris en fonction d'une combinaison de considérations environnementales, sociales et économiques, y compris sa contribution au climat mondial, à la biodiversité et à d'autres objectifs environnementaux. • Les informations relatives à ces possibilités peuvent être présentées dans des cartes nationales ou infranationales et/ou des stratégies de restauration, et doivent être cohérentes avec les zones que les organismes gouvernementaux utilisent lorsqu'ils allouent des fonds, des programmes et des ressources de planification pour la restauration. • Vérifier si les parties prenantes reconnaissent et font référence aux mêmes niveaux de priorité. | K17: • Si la réponse est « oui », quelles sont les zones candidates ? • Si la réponse est « oui », quelles sont les chances de restauration ? | L17: ·
B18: c. Événements de crise | C18: 6. Les événements de crise sont exploités | D18: • La zone cible est-elle confrontée à une situation de crise, ou risque-t-elle d'en connaître une à l'avenir, qui justifierait une restauration du paysage cible, et comment ces événements pourraient-ils affecter les différents groupes de population (ruraux et paysans, urbains, autochtones, femmes, jeunes, etc.) et être anticipés ? | I18: Le gouvernement et/ou la société civile utilisent le risque ou l'occasion que représentent les événements de crise, y compris en envisageant des scénarios futurs (notamment climatiques), pour obtenir le soutien politique et public nécessaire à la restauration des écosystèmes. | J18: • Les événements de crise peuvent inclure des inondations, des glissements de terrain, des sécheresses, des incendies, des tempêtes de sable, une pénurie de bois, une baisse des rendements agricoles, le chômage ou d’autres perturbations qui affectent les écosystèmes et les moyens de subsistance. • Les crises peuvent créer des opportunités pour catalyser la restauration (par exemple, générer une dynamique politique après une catastrophe), mais elles peuvent également interrompre, retarder ou stopper les efforts de restauration (par exemple, dommages aux infrastructures, détournement de fonds, instabilité sociale). • Prenez en compte ces deux dimensions : (i) la capacité à tirer parti des crises pour stimuler la restauration, et (ii) la résilience des efforts de restauration pour résister aux crises et s'en remettre. • Évaluez comment les différents groupes peuvent être affectés par les événements de crise et les réponses de relèvement, y compris les impacts disproportionnés potentiels sur les populations vulnérables. • Vérifiez si les priorités de restauration sont alignées sur les risques climatiques actuels et futurs, et si les investissements sont évalués en fonction de leur viabilité climatique à long terme (au-delà des décisions de conception technique). • Dans le contexte du changement climatique, tenez compte à la fois des événements passés et des scénarios futurs, y compris l'augmentation de la fréquence et de l'intensité des chocs climatiques. Des outils tels que SPARCLE peuvent être utilisés pour visualiser rapidement les impacts du changement climatique. • Le cas échéant, identifiez des mesures visant à atténuer les risques liés à la mise en œuvre de la restauration (par exemple, planification adaptative, financement diversifié, préparation de la communauté). Bien que les crises ne soient pas souhaitables, lorsqu'elles surviennent, elles peuvent offrir des opportunités de mobiliser le soutien politique et communautaire en faveur de la reprise. | K18: • Quels types de crises se sont produites par le passé dans le paysage ciblé ? • Quels types de crises pourraient survenir à l'avenir ? | L18: ·
B19: d. Exigences légales | C19: 7. Il existe des lois et des politiques qui exigent une restauration | D19: • Existe-t-il des lois ou des politiques qui obligent les propriétaires fonciers ou les gestionnaires à replanter ou à restaurer les écosystèmes dans les zones qui ont été exploitées (par exemple, les forêts, les pâturages, les zones humides) ? | I19: Le gouvernement dispose de lois et de politiques qui obligent les gestionnaires fonciers à permettre le rétablissement de la végétation naturelle ou à replanter des arbres dans les écosystèmes naturels qui ont été défrichés dans lla zone ciblée. | J19: • Examiner si la législation exige spécifiquement des mesures de restauration, telles que des exigences de reboisement, des obligations de réhabilitation des terres ou des réglementations relatives à la restauration des activités extractives. Ces lois et politiques précisent-elles qui est tenu de procéder aux réparations, dans quelles situations et pour quelles périodes ? Ce cadre juridique s'applique-t-il à toutes les limites de la zone ciblée ? (Autrement dit, ces exigences sont-elles applicables à l'échelle nationale ?) • Les exigences en matière de restauration visent généralement davantage les entités impliquées dans l’exploitation forestière commerciale, l’exploitation minière ou d’autres activités extractives que les activités de subsistance. | K19: • Si oui, quelles sont les modalités et conditions spécifiques prévues par la loi (par exemple, que faut-il restaurer, quand et comment) ? | L19: ·
C20: 8. Les lois et les politiques sont comprises | D20: • La loi ou la politique exigeant la restauration ou la réhabilitation de l'écosystème est-elle appliquée de manière visible, crédible et équitable, et est-elle largement comprise par tous les acteurs concernés, y compris tous les groupes ? | I20: Les lois et les politiques qui exigent la restauration ou la réhabilitation des écosystèmes (y compris les activités visant à rétablir les fonctions des écosystèmes, à réduire leur dégradation ou à favoriser leur régénération naturelle) dans le paysage concerné sont comprises par les acteurs concernés et mises en œuvre de manière visible, crédible et équitable. | J20: • Il ne suffit pas qu'il existe une loi ou une politique exigeant la restauration ou la réhabilitation ; il faut qu'elle soit appliquée de manière équitable, que les entités concernées la comprennent et que les autorités la mettent en œuvre pour qu'elle serve de moteur à l'action. • Vérifiez si les exigences légales en matière de restauration ou de réhabilitation du paysage sont communiquées aux principales parties prenantes et si elles sont complétées par des mesures telles que des campagnes de communication, des sanctions coercitives (par exemple, des amendes) en cas d’infraction, ainsi que la garantie de ressources humaines et financières suffisantes pour assurer leur respect. • Les mandats gouvernementaux en matière de restauration ou de réhabilitation peuvent susciter des réticences quant à l’implication du gouvernement dans des décisions d’aménagement du territoire qui, autrement, relèveraient de la compétence des communautés traditionnelles ou des propriétaires privés. Par conséquent, la manière dont les exigences légales sont communiquées et complétées par d’autres politiques, incitations et pratiques peut être déterminante pour leur efficacité. | K20: • Il ne suffit pas d’avoir une loi qui exige la remise en état ; il est nécessaire que les entités concernées la comprennent et que les autorités l’appliquent pour inciter à la remise en état. | L20: ·
B21: Condition habilitante | C21: Facteur clé | D21: Question | E21: Réponse | F21: National | G21: Régional | H21: Local | I21: Definition | J21: Orientation | K21: Question(s) de suivi | L21: Réponses complémentaires, justification et pièces justificatives
A22: Activer | B22: e. Conditions écologiques | C22: 9. Les conditions du sol, de l'eau, du climat et du feu sont adéquates pour la restauration | D22: • Les conditions du sol, les précipitations, la température, le feu et la gestion du paysage ciblé sont-ils adaptés pour permettre la croissance et la survie de la végétation plantée ou à régénération naturelle ? | I22: Les conditions du sol, des précipitations et de la température de la zone ciblée sont propices à la repousse de la végétation naturelle, et le régime des feux n'entrave pas le rétablissement des écosystèmes naturels. | J22: • Ce facteur clé combine de multiples conditions écologiques qui affectent la restauration des écosystèmes. Chaque condition (sol, précipitations, température, incendies) doit être évaluée séparément, mais la réponse peut refléter la somme des quatre. | K22: • Si la réponse est « non », quelles sont les carences en matière de condition physique ? Les efforts déployés pour surmonter ces limitations sont-ils viables ? | L22: ·
C23: 10. Les plantes et les animaux susceptibles d'entraver la restauration sont réduits au minimum | D23: • Est-il possible d’éliminer ou de contrôler efficacement les plantes et les animaux envahissants indésirables qui entravent le rétablissement des écosystèmes dans les lieux ciblés pour la restauration ? | I23: Les espèces envahissantes persistantes dans la zone ciblée peuvent être gérées ou contrôlées afin d'éviter qu'elles n'interfèrent avec la végétation replantée ou en régénération naturelle. Les sites de restauration peuvent être protégés du pâturage du bétail qui entrave la restauration des écosystèmes. | J23: • Examiner s’il existe des mesures de surveillance ou de contrôle (clôtures, gestion des mauvaises herbes, élimination) pour gérer les espèces problématiques ou envahissantes qui peuvent concurrencer ou exclure les espèces utilisées pour la restauration. • Les paysages peuvent être exempts de plantes et/ou d'animaux indésirables, soit parce qu'ils n'y ont jamais existé naturellement dans l'écosystème, soit parce qu'ils ont été minimisés avec succès grâce à une gestion appropriée. • Parmi les espèces susceptibles d’entraver les efforts de restauration, on peut citer Brachiaria spp. au Brésil, Imperata cylindrica en Indonésie, Pueraria montana (kudzu) dans le sud des États-Unis et le pâturage incontrôlé d’animaux (bovins, moutons, chèvres) dans de nombreux endroits. | K23: • If “no”, then what are the persistent plant and/or animal species? | L23: ·
C24: 11. Les semences indigènes, des pantules ou des populations sources sont facilement disponibles | D24: • La zone ciblée possède-t-il des populations sources, des banques de propagules du sol (telles que des systèmes racinaires souterrains et des banques de semences) ou des sources peu coûteuses de semences et de jeunes plantules indigènes pouvant servir de base à la restauration de l'écosystème ? | I24: Le paysage ciblé possède des ressources naturelles qui favorisent la régénération, telles que des zones naturelles avoisinantes, la repousse des racines souterraines, les graines dispersées par les animaux et un accès facile à des semences et des plantules indigènes à faible coût qui soutiennent le rétablissement de l'écosystème. | J24: • Des populations sources viables ou des banques de propagules dans le sol de plantes indigènes sont essentielles à la restauration passive. • Ce facteur clé de succès s’applique à l’ensemble de la chaîne d’approvisionnement des semences et des plantules indigènes, y compris la production, la collecte et le traitement des semences, ainsi que les pépinières de pantules. | K24: • Si la réponse est « non », où se situe la lacune (par exemple, semences, collecteurs de semences, pépinières, populations sources, banques de propagules du sol) ? | L24: ·
B25: f. Conditions économiques | C25: 12. Gestion d'autres activités qui entrent en conflit avec la restauration | D25: • Les pressions économiques liées à la production agricole, à l'élevage, à la production de bois de chauffage et/ou de biocarburants sur les terres dégradées et les écosystèmes naturels de la zone cible sont-elles en train de diminuer, et/ou existe-t-il des mécanismes permettant de gérer les pressions économiques contradictoires sur les terres qui favorisent leur dégradation ? | I25: Les pressions économiques liées à la production agricole, à l'élevage, à la production de bois de chauffage et/ou de biocarburants sur les terres dégradées et les écosystèmes naturels de la zone cible diminuent et/ou sont activement gérées par le biais de politiques, d'incitations, d'une planification de l'utilisation des terres ou d'améliorations de la productivité, réduisant ainsi les pressions qui favorisent la dégradation des terres et « libèrent » des opportunités de restauration. | J25: • Les pressions sur l'utilisation des sols qui entrent en conflit avec la restauration peuvent provenir de l'expansion agricole, du développement des infrastructures, du pâturage du bétail, de l'exploitation du bois de chauffage et de l'urbanisation. • Vérifiez s’il existe des mécanismes permettant de gérer ces pressions qui entrent en conflit avec la restauration, tels que l’aménagement du territoire, le zonage, l’intensification agricole sur les terres existantes, les interventions dans la chaîne d’approvisionnement, les incitations à la production durable ou les restrictions à l’expansion dans les écosystèmes naturels. • Ce facteur clé de succès est sans doute l’un des plus importants compte tenu de la demande mondiale croissante en terres pour la production de cultures, de bétail et de biocarburants (Searchinger et al. 2013) • Ce facteur clé ne s’appliquerait pas lorsque les terres sont restaurées en systèmes agroforestiers ou sylvopastoraux, qui continuent respectivement à produire des récoltes et du bétail. | K25: • Quelles sont les principales utilisations alternatives concurrentes des terres pour les zones candidates à la restauration ? | L25: ·
C26: 13. Il existe des chaînes de valeur et/ou des marchés pour les produits de base (bois, produits agricoles) et les produits environnementaux (carbone, eau, biodiversité) issus des zones restaurées | D26: • Existe-t-il des chaînes de valeur, des droits fonciers et des politiques permettant aux produits ou services issus de terres restaurées d'atteindre les consommateurs finaux ? | I26: Dans la mesure où la restauration des forêts dans le paysage ciblé génère des produits et services commercialisables, des chaînes de valeur seront mises en place qui permettront à ces produits d'atteindre le consommateur final depuis la forêt restaurée. | J26: • Ce facteur clé de succès concerne à la fois l'accès au marché et la demande du marché pour les produits et services issus de paysages forestiers restaurés. Une « chaîne de valeur » décrit les multiples étapes impliquées dans l'offre d'un produit ou d'un service, telles que la récolte, la cueillette, la transformation, le transport et la distribution. Une chaîne de valeur issue de la restauration suggère que les individus ou les groupes de la zone cible peuvent tirer des moyens de subsistance et des activités économiques locales dans le cadre de la restauration des écosystèmes. De plus, les chaînes de valeur des produits environnementaux comprennent la production/fourniture du service, l'émission de crédits carbone ou de crédits nature, l'achat de crédits, etc. • Vérifier s’il existe des initiatives, des coopératives ou des entreprises dans les zones cibles qui vendent des produits ou des services issus des activités de restauration. Les producteurs de ces lieux peuvent-ils différencier leurs produits et services grâce à des labels, des certifications ou un accès à des marchés préférentiels ? Existe-t-il des infrastructures pour transformer et valoriser les produits et services offerts par les écosystèmes ? Existe-t-il des promoteurs ou des développeurs de projets qui soutiennent la génération de crédits carbone ou de nature ? Quelles sont les politiques en vigueur qui facilitent les marchés du carbone et de la nature ? • Les services écosystémiques restaurés pourraient inclure les loisirs, le tourisme et l'approvisionnement en eau. | K26: • Si la réponse est « non », où se situent les lacunes de cette chaîne de valeur ? • Si la réponse est « oui », quelle est la chaîne de valeur, y compris les producteurs, les intermédiaires, les consommateurs finaux, etc. ? | L26: ·
B27: g. Conditions de la politique | C27: 14. Les usagers, les propriétaires ou les communautés foncières disposent de droits fonciers garantis sur la terre et ses ressources naturelles | D27: • Les gestionnaires de la zone concernée disposent-elles de droits clairs et garantis pour utiliser les terres, récolter les produits de manière durable et percevoir les avantages financiers qui résulteraient de la restauration ? Ces droits sont-ils accessibles à toutes les parties prenantes, y compris aux femmes et aux groupes vulnérables ? | I27: Les populations et les communautés qui gèrent la zone ciblée disposent de droits clairs et garantis (par exemple, sous la forme de droits de propriété foncière ou de droits de gestion des ressources naturelles) sur les avantages qui résulteraient de la restauration. | J27: • L’absence (ou l’insécurité) de titres fonciers et de droits sur les ressources naturelles dans la zone ciblée peut décourager les restaurations impliquant une intervention humaine. Les gens n'investiront pas dans la plantation d'arbres et de végétation indigènes ni ne permettront la régénération naturelle des terres qu'ils gèrent s'ils ne sont pas susceptibles de bénéficier de l'état restauré. • Les droits fonciers et les droits sur les ressources naturelles peuvent prendre la forme de la propriété foncière privée, de terres communautaires, d'accords coutumiers, de certificats de droits d'usage, etc. • Il convient également d'examiner si les droits fonciers existants chevauchent ou entrent en conflit avec les droits coutumiers. | K27: • Si la réponse est « non », quels droits manquent et pour qui ? | L27: ·
C28: 15. Les politiques relatives à la restauration sont harmonisées et rationalisées | D28: • Les politiques susceptibles d’avoir un impact sur la restauration de la zone ciblée sont-elles alignées et optimisées dans un contexte mondial, national, infranational et local ? | I28: Les politiques publiques pertinentes sont harmonisées, cohérentes et optimisées pour soutenir efficacement les efforts de restauration dans la zone ciblée. Ces politiques se renforcent mutuellement, minimisent les obstacles administratifs inutiles et créent un environnement propice à leur mise en œuvre. Les politiques qui promeuvent l'égalité des sexes et l'inclusion sociale sont également considérées comme essentielles pour soutenir des résultats de restauration inclusifs et durables. | J28: • Les politiques nationales relatives au climat, à la biodiversité et à la dégradation des terres présenteront probablement des points de convergence en matière de restauration, qui pourront être examinés par le biais des comités nationaux existants. • Parmi les autres politiques à prendre en compte figurent celles relatives à l'agriculture, aux industries extractives, à l'eau, à l'aménagement du territoire, aux infrastructures et aux ressources naturelles. • Dans certains cas, les politiques de conservation de la nature ou d’autres secteurs peuvent entraver la restauration (par exemple, les lois qui interdisent le prélèvement de semences indigènes dans les zones protégées, les lois qui interdisent la récolte d’espèces d’arbres indigènes, les subventions qui incitent aux facteurs de dégradation). | K28: • Si la réponse est « non », quelles politiques ne sont pas harmonisées ou simplifiées ? | L28: ·
C29: 16. L’exploitation forestière est soumise à des restrictions dans les écosystèmes naturels restants (forêts, pâturages, zones humides, etc.) | D29: • La zone ciblée est-elle soumise à des lois qui limitent l’exploitation forestière ou le défrichement des écosystèmes naturels restants ? | I29: La zone ciblée est soumise à des lois qui limitent le défrichement ou l'exploitation forestière des écosystèmes naturels restants. | J29: • Les restrictions imposées à l'abattage des forêts et des écosystèmes naturels restants peuvent empêcher une nouvelle expansion des zones dégradées ou déboisées. Ces restrictions incitent également à restaurer la productivité des zones déjà déboisées, car elles limitent les possibilités d'exploitation de la lisière forestière. • Les restrictions peuvent également prendre la forme d’un vaste réseau de parcs nationaux et de forêts nationales, d’un vaste réseau de territoires autochtones boisés, de normes de protection des écosystèmes sur les terres communales, de normes de « zéro perte nette », de pourcentages spécifiques de terres devant rester boisées (par exemple, le Code forestier brésilien), etc. • Un élément important de ce facteur clé de succès est que les « forêts et écosystèmes naturels » aient été clairement définis par l’autorité qui impose la restriction (par exemple, le gouvernement national). Cette définition doit inclure les forêts primaires, les forêts secondaires et les forêts dégradées, ainsi que d’autres écosystèmes présentant un potentiel de restauration. Remarque : les effets potentiels de déplacement ou de fuite (par exemple, le déplacement du déboisement vers d'autres zones) sont abordés dans une section distincte de cette évaluation et doivent être pris en compte conjointement avec cette question. | K29: • Si oui, quelles sont ces lois ? | L29: ·
C30: 17. Les restrictions s'appliquent à l'exploitation des écosystèmes naturels restants (par exemple, les forêts, les pâturages, les zones humides) | D30: • Ces restrictions en matière de nettoyage ou d'élagage sont-elles correctement appliquées ? | I30: Les lois qui limitent l'exploitation forestière des écosystèmes naturels restants sont correctement appliquées. | J30: • Il ne suffit pas d’avoir des réglementations limitant l’exploitation des écosystèmes naturels restants ; il est nécessaire que les autorités compétentes fassent respecter ces restrictions. • En particulier dans les zones reculées, l’application de la loi dépend des capacités des organismes chargés de l’application de la loi et des incitations qu’ils ont à mener à bien leurs activités. | K30: • Si la réponse est « non », pourquoi pas ? | L30: ·
B31: h. Conditions sociales et culturelles | C31: 18. Les femmes, les jeunes et les peuples autochtones participent à la prise de décision concernant la restauration | D31: • Les femmes, les jeunes et les peuples autochtones vivant dans et autour de la zone ciblée, ainsi que les systèmes culturels, les structures de gouvernance traditionnelles et les systèmes de connaissances qu’ils représentent, sont-ils réellement impliqués dans la prise de décision en matière de restauration (par exemple, la conception du programme, la définition des objectifs, la gestion, le suivi et la sélection des indicateurs) ? | I31: Les femmes, les jeunes et les peuples autochtones sont explicitement reconnus et soutenus en tant qu'acteurs clés dans la planification et la mise en œuvre de la restauration à toutes les échelles. Leurs systèmes culturels, leurs structures de gouvernance traditionnelles et leurs connaissances sont respectés et intégrés aux instances décisionnelles, aux accords de gouvernance et aux processus de suivi, garantissant ainsi des résultats de restauration inclusifs, représentatifs et culturellement adaptés. | J31: • Les décisions relatives aux différents domaines (y compris la planification, la conception, la gestion et le suivi) doivent être inclusives et adaptées au contexte culturel. Lorsque la participation est limitée ou extractive, les efforts de restauration risquent de se fragmenter, d'affaiblir l'appropriation locale et de répartir inégalement les bénéfices, en particulier pour les femmes, les jeunes et les peuples autochtones. • Le renforcement des institutions locales existantes et des processus ancrés dans la culture (par exemple, les coopératives forestières villageoises, les groupes de femmes, les organisations de peuples autochtones, les associations de jeunes et les systèmes de gouvernance traditionnels) peut soutenir les accords de cogestion, améliorer la participation locale et accroître l’adoption à long terme des initiatives de restauration. • La planification et la mise en œuvre de la restauration doivent reconnaître et respecter les systèmes culturels en général (y compris les valeurs, les connaissances et les pratiques des divers groupes de parties prenantes) et intégrer ces perspectives dans les processus de prise de décision, de gestion et de suivi. • Une participation efficace et inclusive exige de la transparence et de la responsabilité dans la prise de décision, le respect du consentement libre, préalable et éclairé (CLPE) lorsque cela est approprié, et des mécanismes de réclamation et de rétroaction accessibles et fiables qui permettent aux parties prenantes de soulever des préoccupations et de permettre une correction du cap lorsque les processus ou les résultats échouent. | K31: • Si la réponse est « non », quels groupes sont mal représentés ? • Si la réponse est « non », de quels aspects de la restauration les groupes vulnérables sont-ils exclus ? | L31: ·
C32: 19. La population locale bénéficie de la restauration | D32: • Les populations vivant dans et autour de la zone ciblée peuvent-elles bénéficier des avantages générés par la restauration, tels que l’amélioration de leurs moyens de subsistance ou des services écosystémiques ? | I32: Les communautés vivant dans ou autour des zones cibles voient leurs besoins satisfaits grâce aux efforts de restauration et bénéficient d'avantages environnementaux (par exemple, une meilleure qualité de l'eau, un approvisionnement accru en produits forestiers) ou économiques (par exemple, des sources de revenus alternatives, des moyens de subsistance améliorés) grâce à la restauration. | J32: • La documentation de planification et la conception technique de toute initiative de restauration doivent inclure des cadres et des mécanismes visant à garantir que les personnes vivant dans ou à proximité des zones restaurées soient les principaux bénéficiaires des résultats positifs de la restauration. Vous trouverez ici des exemples des bienfaits que peut apporter la restauration. • Les planificateurs ou les responsables de la mise en œuvre des restaurations devraient se poser en permanence les questions suivantes : Parmi les avantages sociaux, culturels, politiques, environnementaux et économiques recensés, les plans de restauration précisent-ils quelles populations ou quels groupes locaux sont censés bénéficier des activités de restauration ? Ces avantages correspondent-ils aux besoins locaux ? Les avantages perçus par la population locale sont-ils raisonnables, équitables et fiables ? • Si la population locale ne perçoit pas les avantages, elle sera peu incitée à modifier ses comportements afin de permettre la restauration ou de préserver le paysage restauré à long terme. | K32: • Si la réponse est « non », quels obstacles ou limitations empêchent les communautés locales d’accéder aux avantages de la restauration ? | L32: ·
B33: i. Conditions institutionnelles | C33: 20. Les rôles et les responsabilités en matière de restauration sont clairement définis | D33: • Les rôles et responsabilités en matière de restauration des écosystèmes dans la zone cible sont-ils clairement définis, compris par les acteurs concernés et accompagnés d'une autorité, et, si nécessaire, existe-t-il des mécanismes de résolution des conflits ? | I33: Les rôles et responsabilités en matière de restauration dans la zone cible sont clairement définis, compris par les acteurs concernés (par exemple, le gouvernement, la société civile, le secteur privé et d'autres parties prenantes pertinentes) et accompagnés d'une autorité. Des mécanismes de résolution des conflits existent et sont mis en œuvre. | J33: • Déterminer s'il existe des agences, des institutions ou des groupes désignés ayant le pouvoir de mettre en œuvre la restauration des écosystèmes. • En l'absence de clarté sur les rôles et les responsabilités, l'inaction peut survenir en raison de l'absence de personnes occupant des postes importants, de l'incertitude quant à la répartition des tâches ou du chevauchement des responsabilités et des droits revendiqués par les institutions et les groupes. • Pour répondre de manière adéquate à cette question, les utilisateurs peuvent avoir besoin de cartographier les mandats existants en matière de planification, de coordination, de mise en œuvre et de suivi de la restauration parmi les entités publiques, les groupes et organisations privés, les propriétaires fonciers, les utilisateurs des terres et les autres parties prenantes clés. Les rôles, les responsabilités et les droits peuvent également être définis dans des lois, des politiques ou des pratiques coutumières. • Les mécanismes de résolution des conflits pour la restauration des écosystèmes sont des systèmes structurés et collaboratifs conçus pour gérer les différends entre les parties prenantes concernant la gestion, l'accès et l'utilisation des ressources naturelles ou d'autres activités pendant les projets de restauration. | K33: • Si la réponse est « non », qu’est-ce qui manque en termes de clarté des rôles et des responsabilités ? | L33: ·
C34: 21. Une coordination institutionnelle efficace est maintenue | D34: • Les parties prenantes concernées issues du gouvernement, de la société civile et du secteur privé se coordonnent-elles efficacement – par exemple au sein d'un groupe de travail ou dans le cadre d'un processus multilatéral – pour concevoir, mettre en œuvre et superviser la restauration de l'écosystème dans la zone candidate, tout en veillant à ce que ces efforts incluent les groupes vulnérables ? | I34: Les acteurs concernés issus du gouvernement, de la société civile et/ou du secteur privé sont suffisamment coordonnés pour concevoir, mettre en œuvre et suivre la restauration dans la zone ciblée. | J34: • Examiner si les institutions publiques et privées se sont engagées à établir un leadership et des mandats clairs en matière de restauration. Existe-t-il une action conjointe concrète sous la forme de mécanismes de coordination, de comités, de groupes de travail ou d'alliances qui se réunissent régulièrement et prennent des décisions concernant la restauration ? Ces efforts de coordination comprennent-ils le partage de plans, de données, d'apports techniques et de mécanismes de suivi, notamment aux niveaux de gouvernance local, régional et national ? | K34: • Si la réponse est « non », que manque-t-il en termes de coordination ? | L34: ·
B35: Condition habilitante | C35: Facteur clé | D35: Question | E35: Réponse | F35: National | G35: Régional | H35: Local | I35: Definition | J35: Orientation | K35: Question(s) de suivi | L35: Réponses complémentaires, justification et pièces justificatives
A36: Mettre en œuvre | B36: j. Direction | C36: 22. Il existe des leaders nationaux et/ou locaux de la restauration | D36: • Existe-t-il un défenseur charismatique et engagé de la restauration dans la zone ciblée ? Représentent-ils tous les acteurs de la société, y compris les femmes, les jeunes et les peuples autochtones ? | I36: Il existe des personnalités charismatiques (ou des institutions influentes) capables d'inciter efficacement les décideurs à s'engager en faveur de la restauration, à mobiliser des soutiens et à maintenir la dynamique au fil du temps dans la zone candidate | J36: • Les leaders locaux de la restauration peuvent être des individus ou des groupes engagés dans la restauration de la zone et capables d’agir en conséquence. Dans certains paysages ou écosystèmes, il peut être nécessaire de cultiver les espèces championnes et de leur donner une visibilité accrue. • Historiquement, les projets de restauration réussis bénéficiaient d'un promoteur ou d'un soutien gouvernemental important. Rares étaient ceux qui ne possédaient ni l'un ni l'autre. | K36: • Qui est le leader local de la restauration ?
C37: 23. Il existe un engagement politique soutenu | D37: • Existe-t-il un engagement clair et durable à long terme de la part des institutions gouvernementales et non gouvernementales pour soutenir les efforts de restauration dans la zone cible, y compris en termes de budgets alloués ? | I37: L'engagement des autorités gouvernementales (à tous les niveaux pertinents, le cas échéant) et des institutions non gouvernementales en faveur de la restauration dans la zone cible est clairement établi et reconnu comme un engagement durable et à long terme, assorti d'un budget alloué. | J37: • Il peut être difficile de prévoir l’engagement à long terme d’un gouvernement ou d’une organisation. Dans de telles situations, il convient d'examiner si l'engagement transcende les partis politiques et si la restauration produira des avantages récurrents pour les principaux acteurs concernés. | K37: • Si oui, quelle est la preuve de cet engagement exprès et de qui vient-elle ?
B38: k. Connaissance | C38: 24. Il existe une « expertise technique » pertinente en matière de restauration pour la zone candidate | D38: • Existe-t-il des connaissances locales diversifiées (y compris des connaissances autochtones, des connaissances écologiques traditionnelles et des connaissances tenant compte des questions de genre) sur la manière de mettre en œuvre la restauration à grande échelle dans la zone ciblée ? | I38: Les experts locaux connaissent les techniques de restauration (par exemple, la régénération naturelle et assistée, les connaissances traditionnelles) adaptées à la zone concernée, ou mènent des recherches sur le sujet. | J38: • L’expertise locale peut provenir des connaissances traditionnelles des communautés vivant dans ou autour du paysage, des experts des universités et des services de vulgarisation rurale, et des organisations non gouvernementales actives dans ce domaine. • Les connaissances peuvent être produites localement ou importées d'ailleurs, mais elles doivent être communiquées ou transmises par des professionnels locaux. Des conseils sur les « meilleures pratiques » en matière de restauration peuvent être obtenus auprès des universités, des organisations non gouvernementales ou des agences de vulgarisation, ainsi qu'auprès de personnes ou de groupes locaux ayant une expérience en matière de restauration à long terme. | K38: • Si la réponse est « non », quelles sont les lacunes les plus importantes en matière de connaissances ?
C39: 25. Le « savoir-faire » en matière de restauration est transféré par l'intermédiaire de partenaires ou de services de vulgarisation. | D39: • Existe-t-il des services de vulgarisation, des visites entre agriculteurs, des groupes de femmes, des réseaux locaux et/ou d'autres moyens de sensibilisation et de renforcement des capacités en matière de restauration, et disposent-ils de ressources adéquates dans la zone ciblée ou au niveau national ? | I39: L’assistance technique et la vulgarisation rurale (« services de vulgarisation »), les visites d’agriculteur à agriculteur, les groupes de femmes, les réseaux locaux et/ou d’autres moyens de sensibilisation et de renforcement des capacités en matière de restauration sont disponibles, et des ressources adéquates sont disponibles dans la zone candidate. | J39: • Le partage des connaissances peut être documenté dans le cadre de services de vulgarisation formels, tels que les visites de terrain, les programmes de formation, les écoles de terrain, les documents imprimés et les sites de démonstration. • Examiner si des groupes d’apprentissage informels sur la restauration partagent des informations ou coordonnent des activités, notamment des groupes de femmes, des associations de producteurs ou des échanges de connaissances entre les peuples autochtones. Cette communication «d'agriculteur à agriculteur» ou «de gestionnaire foncier à gestionnaire foncier» peut être l'un des moyens les plus efficaces d'éducation et de formation. • Les réseaux ou associations locaux de renforcement des capacités en matière de restauration des écosystèmes, d’agroforesterie ou de reboisement peuvent être mentionnés dans les documents nationaux ou les rapports des organisations non gouvernementales. | K39: • Dans le paysage des candidats, quelles entités sont les mieux placées pour fournir des services d'extension ?
B40: l.Conception technique | C40: 26. Le projet de restauration repose sur des bases techniques et adaptées au changement climatique | D40: • Le plan de restauration de la zone ciblée est-il fondé sur les meilleures pratiques, intégrant les meilleures connaissances scientifiques disponibles, les savoirs écologiques traditionnels et les approches résilientes face au climat ? | I40: Le plan de restauration est basé sur les meilleures pratiques en matière de conception, de mise en œuvre et d'entretien des activités de restauration. Le plan de restauration intègre les meilleures connaissances scientifiques disponibles et des approches résilientes au climat qui garantissent que l'intervention, y compris des aspects tels que la sélection des espèces et les techniques de restauration, est appropriée au contexte local et aux objectifs de l'intervention, et réduit la vulnérabilité de l'intervention de restauration aux impacts climatiques tels que les sécheresses, les inondations, les feux de forêt et les températures extrêmes. | J40: • Examiner si les approches de restauration des écosystèmes sont étayées par la recherche scientifique, les connaissances locales ou les pratiques autochtones pour restaurer les écosystèmes naturels et réduire la vulnérabilité aux impacts climatiques. • La conception technique doit aborder des aspects tels que la préparation du site, la pente, le choix des espèces, l'espacement et l'entretien des arbres, ou comment éliminer les pressions qui empêchent la végétation naturelle de repousser (par exemple, le bétail, les incendies). • Pour être résilients face au changement climatique, les plans de restauration doivent tenir compte des impacts climatiques prévus. | K40: • Si la réponse est « non », que manque-t-il au plan ?
C41: 27. Les limites de restauration «fuites» | D41: • Le processus de restauration comporte-t-il des dispositions établies (par exemple, des politiques, des pratiques, des incitations, des améliorations du rendement) qui limitent les fuites ou est-il en cours d’élaboration de manière à les réduire ? Les activités de restauration empêchent-elles les utilisateurs des terres d'être déplacés vers d'autres zones où ils n'ont d'autre choix que de transformer/nettoyer les écosystèmes naturels pour l'utilisation des terres agricoles ? | I41: La restauration des écosystèmes dans la zone candidate empêche le transfert des activités de défrichement vers d'autres endroits (« fuite »), ce qui entraîne une augmentation nette de la superficie restaurée. | J41: • Il existe un risque que la restauration des écosystèmes dans la zone ciblée entraîne le déplacement vers un autre paysage des activités qui causaient la dégradation des terres. • Bien que de telles « fuites » puissent entraîner une augmentation de la superficie restaurée dans le paysage ciblé, elles entraîneraient également une augmentation des terres dégradées ou déboisées ailleurs. • Les moyens de limiter les fuites liées aux activités de restauration pourraient inclure : Combiner la restauration avec des usages productifs (par exemple, l'agroforesterie), proposer des moyens de subsistance locaux alternatifs qui ne nécessitent pas la conversion des terres en terres agricoles, accroître l'efficacité agricole afin que la production ne se déplace pas vers de nouvelles zones, planifier la restauration à l'échelle du paysage pour gérer les changements d'activités et s'attaquer aux causes profondes de la dégradation. • Pour plus d’informations sur le reboisement d’un pays qui déplace la déforestation vers un autre, voir : Meyfroidt et Lambin (2011). | K41: • Si la réponse est « non », quelles mesures manquent au processus de restauration pour empêcher le déplacement de la dégradation des terres vers d’autres zones ?
B42: m. Financement et incitations | C42: 28. Les incitations positives et les fonds de restauration l'emportent sur les incitations négatives | D42: • Du point de vue des parties prenantes concernées, les incitations financières et les mécanismes de financement disponibles encouragent-ils suffisamment la restauration dans la zone cible, par rapport aux incitations qui pourraient décourager ou entraver la restauration de l'écosystème ? | I42: Du point de vue des parties prenantes concernées, les incitations financières et les mécanismes de financement destinés à soutenir la restauration dans la zone candidate sont disponibles, accessibles et suffisamment attractifs pour encourager les investissements dans les activités de restauration. Ces incitations sont conçues pour compenser les coûts d'opportunité et les risques financiers associés à la restauration, et pour l'emporter sur les incitations concurrentes qui favorisent les utilisations ou les pratiques foncières qui entravent ou retardent la restauration des écosystèmes. Le cadre global d'incitations soutient un engagement durable en faveur de la restauration à long terme. | J42: • La restauration peut avoir lieu lorsque les incitations globales l'emportent à la fois sur les coûts de la restauration et sur les avantages continus procurés par le paysage dégradé. • Les incitations « positives » (par exemple, les subventions, les prêts, les allégements fiscaux, les aides, les paiements pour les services écosystémiques, les biens et services privés) encouragent la restauration, tandis que les incitations « négatives » (par exemple, les subventions pour l'élevage, l'agriculture ou les industries extractives) la découragent. • Si les incitations positives sont éclipsées par les incitations négatives, une restauration à grande échelle est peu probable ; le montant et le calendrier des incitations sont également importants. • Les incitations et le financement font partie de la mise en œuvre, car ils influencent directement les décisions des gestionnaires fonciers en matière de restauration. • Les engagements des entreprises peuvent également être analysés pour la zone proposée. Ils font référence aux promesses faites par les entreprises de restaurer les écosystèmes ou d'atteindre des objectifs en matière de climat et de biodiversité. Lors de l'examen, vérifiez si ces engagements sont spécifiques, mesurables et liés à des actions concrètes ou à un financement pour la restauration. | K42: • Quels sont les principaux facteurs incitatifs, positifs et négatifs, qui influencent les décisions en matière de restauration et d'utilisation des terres dans le paysage ciblé ? • Du point de vue des parties prenantes concernées, quelle est l’ampleur ou la portée de ces incitations (par exemple, la valeur financière par hectare ou des mesures comparables) ?
C43: 29. Les fonds sont disponibles pour les projets de restauration | D43: • Les incitations financières et les mécanismes de financement visant à promouvoir la restauration dans la zone cible sont-ils accessibles, inclusifs et utilisables par un large éventail de parties prenantes, y compris les communautés locales, tout en garantissant la durabilité à long terme ? | I43: Les mécanismes financiers et les incitations ont été soigneusement conçus, sélectionnés et mis en œuvre afin de soutenir efficacement les politiques, les actions et les mesures de restauration à l'échelle du paysage et des communautés. Ces mécanismes sont accessibles à un large éventail de parties prenantes, favorisent une participation équitable et mobilisent les financements du secteur privé, le cas échéant, afin d'améliorer et de pérenniser les résultats de la restauration. Le financement à long terme désigne les ressources financières engagées pour soutenir des activités sur une longue période, garantissant ainsi la continuité et la stabilité. | J43: • Les incitations et les fonds comprennent les subventions, les prêts, les allégements fiscaux sur les intrants, les extrants ou le financement de la restauration, les dépenses publiques directes telles que les subventions ou les politiques d'approvisionnement, les paiements pour les services écosystémiques ou les marchés privés de biens et services qui encouragent les efforts de restauration des écosystèmes. • Déterminez si des particuliers, des communautés ou des groupes dans la ou les zones de restauration ont demandé et obtenu un soutien financier pour des activités de restauration. Incluez les commentaires des particuliers ou des groupes qui ont tenté d'accéder à ces incitations ou fonds, mais qui n'ont pas réussi. • Le financement à long terme et les mécanismes de marché font référence à un soutien financier durable pour des activités sur la durée, y compris des sources de financement dédiées ou des systèmes qui génèrent une demande continue, tels que les marchés de crédits environnementaux. Lors de l'examen, vérifiez s'il existe des engagements de financement pluriannuels ou des instruments basés sur le marché qui peuvent soutenir de manière fiable la mise en œuvre. | K43: • Si la réponse est « non », quels sont les obstacles à l’accès ?
B44: n. Retour | C44: 30. Un système de suivi efficace est mis en place | D44: • Existe-t-il un système de suivi permettant de contrôler et d'évaluer les progrès de la restauration à l'échelle du paysage ou au niveau national, et est-il aligné sur les systèmes de suivi nationaux et mondiaux ? | I44: Un système est en place pour suivre les progrès et évaluer l'impact de la restauration sur la zone candidate. | J44: • Les informations nécessaires au suivi et à l’évaluation doivent être collectées de manière planifiée et continue afin de fournir des connaissances et un retour d’information sur la mise en œuvre des activités de restauration. Les aspects à surveiller peuvent inclure les hectares restaurés, les taux de survie des espèces plantées, les avantages économiques et sociaux quantifiés et les flux de services écosystémiques. • Les systèmes de suivi et d’évaluation peuvent employer des approches telles que la télédétection, la surveillance sur le terrain avec participation collective (par exemple, en utilisant des technologies communautaires, des bénévoles et des moyens de communication) et des enquêtes auprès des habitants de la zone ciblée. | K44: • Si la réponse est « oui », des données de référence sont-elles déjà collectées ? • Si la réponse est « non », quels aspects d’un système de surveillance des performances sont manquants ?
C45: 31. Les succès précoces et continus sont signalés | D45: • Les succès de la restauration sont-ils communiqués et le public cible est-il identifié ? | I45: Les principaux succès obtenus dans la restauration de la zone candidate sont rapidement partagés avec les parties prenantes, ce qui permet de les tenir informées des progrès réalisés et de favoriser un sentiment de partenariat et d'engagement. | J45: • La communication peut prendre la forme de documentation et de reportages dans des campagnes médiatiques et sur les réseaux sociaux, mais elle peut également inclure l'observation directe par le biais de visites d'agriculteurs, de gestionnaires fonciers et de décideurs sur les sites de restauration. • La réalisation et la communication publique des succès, y compris des « premiers succès », peuvent contribuer à maintenir la dynamique, à attirer davantage de participants, à générer des réplications dans d’autres régions, à renforcer le soutien politique et à pérenniser le financement externe. | K45: • Si la réponse est « oui », comment les succès sont-ils communiqués (par exemple, par quels moyens) ? • Si la réponse est « non », quels moyens sont disponibles et pourraient être utilisés ?
B12568: X
B12569: N'applique pas
B12571: En place
B12572: Partiellement en place
B12573: Pas en place
B12574: N'applique pas

Sheet Étape 3. Proposer des stratégie
A1: Étape 3. Sélectionner des mesures stratégiques visant à remédier aux lacunes dans des domaines clés
B3: Objectif L'étape 3 vous aidera à élaborer des stratégies pour traiter les facteurs clés qui font défaut ou qui n'ont été que partiellement mis en œuvre. L'objectif est d'identifier les mesures susceptibles d'augmenter les chances de réussite de la restauration dans la zone concernée. Stratégies d'identification Les utilisateurs procèdent à un brainstorming et notent des propositions à partir des catégories d'exemple indiquées ci-dessous, susceptibles de contribuer à améliorer les facteurs de réussite manquants ou insuffisants : • Politiques • Mesures incitatives • Réformes institutionnelles • Mesures de renforcement des capacités • Interventions intersectorielles (par exemple, agriculture, finances, régime foncier) Considérations clés : • Une stratégie peut remédier à plusieurs lacunes • Les stratégies doivent clairement préciser : • Qui interviendra • Quelles actions seront menées • Pourquoi • Dans quels délais • Comment, y compris comment ces actions seront financées L'outil propose des exemples de stratégies, mais ceux-ci sont purement illustratifs et non normatifs. Le contexte local et le jugement personnel sont essentiels.
B5: Condition habilitante | C5: Facteur clé | D5: Réponse | E5: Stratégies visant à combler les lacunes en matière de conditions habilitants | F5: National | G5: Régional | H5: Local | I5: Exemples de stratégies pour combler l'écart en matière de facteurs clés
A6: Motiver | B6: a. Avantages | C6: 1. La restauration génère des avantages économiques | D6: =IF(ISBLANK('Étape 2. Évaluer les facteurs'!E13),"",'Étape 2. Évaluer les facteurs'!E13) | I6: • Réaliser une analyse coûts-avantages en comparant (a) les avantages probables générés par la zone restaurée, (b) les coûts probables de la restauration du paysage visé, et (c) les coûts et avantages probables de l'utilisation actuelle de l'écosystème. • Explorer les méthodologies de comptabilité des écosystèmes permettant d'évaluer les avantages économiques des services écosystémiques (par exemple, l'UNSEEA) et la capacité des bureaux nationaux de statistique à mener à bien ces évaluations.
C7: 2. La restauration génère des avantages sociaux | D7: =IF(ISBLANK('Étape 2. Évaluer les facteurs'!E14),"",'Étape 2. Évaluer les facteurs'!E14) | I7: • Impliquer les communautés vivant dans et autour de la zone ciblée afin d'identifier leurs objectifs et priorités sociaux, politiques ou culturels. Cela pourrait se faire par le biais d'enquêtes ou d'ateliers en présentiel. À partir de cet exercice, élaborez conjointement une carte des interventions de restauration qui pourraient contribuer à atteindre ces objectifs. • Valider auprès des communautés locales, y compris des représentants des populations vulnérables, les plans de restauration, les instruments de financement, les systèmes de suivi et les indicateurs existants, afin de garantir que ces plans répondent aux besoins de la communauté.
C8: 3. La restauration génère des avantages environnementaux | D8: =IF(ISBLANK('Étape 2. Évaluer les facteurs'!E15),"",'Étape 2. Évaluer les facteurs'!E15) | I8: • Faire appel à des scientifiques (par exemple, des biologistes, des écologues, des hydrologues, des pédologues) pour identifier les bénéfices environnementaux qui pourraient être générés par les efforts de restauration.
B9: b. Conscience | C9: 4. Les avantages de la restauration sont communiqués publiquement | D9: =IF(ISBLANK('Étape 2. Évaluer les facteurs'!E16),"",'Étape 2. Évaluer les facteurs'!E16) | I9: • Élaborer des supports et des campagnes de sensibilisation par le biais des journaux, de la radio, de la télévision, d'Internet ou de visites sur site, en fonction du public cible. • Mettre en place ou tirer parti des activités nationales de restauration existantes, telles que les programmes publics ou scolaires de plantation d’arbres.
C10: 5. Les possibilités de restauration sont identifiées | D10: =IF(ISBLANK('Étape 2. Évaluer les facteurs'!E17),"",'Étape 2. Évaluer les facteurs'!E17) | I10: • Réaliser une activité de planification sur la « Méthodologie d’évaluation des possibilités de restauration ». Il s'agit d'une ressource complète pour la planification de la restauration, disponible en ligne à l'adresse suivante : https://iucn.org/resources/grey-literature/guide-restoration-opportunities-assessment-methodology-roam
B11: c. Événements de crise | C11: 6. Les événements de crise sont exploités | D11: =IF(ISBLANK('Étape 2. Évaluer les facteurs'!E18),"",'Étape 2. Évaluer les facteurs'!E18) | I11: • Mener et communiquer des recherches qui quantifient et visualisent dans quelle mesure les écosystèmes restaurés peuvent prévenir ou atténuer les catastrophes humanitaires naturelles et permettre de réaliser des économies sur les efforts d’atténuation lorsque des mes • En cas de catastrophe, communiquez immédiatement et publiquement sur les avantages de la restauration.
B12: d. Exigences légales | C12: 7. Il existe des lois et des politiques qui exigent une restauration | D12: =IF(ISBLANK('Étape 2. Évaluer les facteurs'!E19),"",'Étape 2. Évaluer les facteurs'!E19) | I12: • Établir une loi gouvernementale (ou une politique industrielle) obligeant les gestionnaires fonciers à permettre à la végétation de se rétablir ou d'être replantée dans les zones qui ont été défrichées en raison de leur propre activité commerciale (par exemple, l'exploitation forestière, l'exploitation minière, etc.).
C13: 8. Les lois et les politiques sont comprises | D13: =IF(ISBLANK('Étape 2. Évaluer les facteurs'!E20),"",'Étape 2. Évaluer les facteurs'!E20) | I13: • Mener une campagne de communication pour sensibiliser les parties prenantes concernées aux exigences de restauration. • Adopter des mesures coercitives (par exemple, amendes, refus d’accès au crédit, emprisonnement) en cas de violation des exigences de rétablissement. • Veiller à ce que les ressources humaines et financières allouées aux forces de l’ordre soient adéquates.
B14: Condition habilitante | C14: Facteur clé | D14: Réponse | E14: Stratégies visant à combler les lacunes en matière de conditions habilitants | F14: National | G14: Régional | H14: Local | I14: Exemples de stratégies pour combler l'écart en matière de facteurs clés
A15: Activer | B15: e. Conditions écologiques | C15: 9. Les conditions du sol, de l'eau, du climat et du feu sont adéquates pour la restauration | D15: =IF(ISBLANK('Étape 2. Évaluer les facteurs'!E22),"",'Étape 2. Évaluer les facteurs'!E22) | I15: • Adapter ou modifier le plan de restauration (par exemple, le mélange d’espèces) en fonction du régime hydrique et climatique du paysage. • Mettre en œuvre un programme de prévention des incendies indésirables ou introduire des brûlages dirigés. • Mettre en œuvre un programme visant à améliorer la qualité des sols (par exemple, en plantant des espèces fixatrices d’azote). • Créer des digues ou des structures en forme de croissant pour stocker l'eau après les pluies.
C16: 10. Les plantes et les animaux susceptibles d'entraver la restauration sont réduits au minimum | D16: =IF(ISBLANK('Étape 2. Évaluer les facteurs'!E23),"",'Étape 2. Évaluer les facteurs'!E23) | I16: • Mettre en œuvre un programme visant à éliminer les plantes envahissantes (par exemple, utiliser des arbres indigènes à croissance rapide pour ombrager les plantes envahissantes, utiliser des chèvres, utiliser le feu de manière appropriée). • Mettre en œuvre un programme visant à exclure le bétail errant indésirable (par exemple, des incitations et une formation à la pose de barrières).
C17: 11. Les semences indigènes, des pantules ou des populations sources sont facilement disponibles | D17: =IF(ISBLANK('Étape 2. Évaluer les facteurs'!E24),"",'Étape 2. Évaluer les facteurs'!E24) | I17: • Établir des lois qui protègent les zones restantes de végétation indigène dans la zone candidate. • Créer des incitations financières et des programmes de renforcement des capacités visant à consolider et à améliorer le nombre et la qualité des pépinières de plantules et des réseaux de collecteurs de semences.
B18: f. Conditions économiques | C18: 12. Gestion d'autres activités qui entrent en conflit avec la restauration. | D18: =IF(ISBLANK('Étape 2. Évaluer les facteurs'!E25),"",'Étape 2. Évaluer les facteurs'!E25) | I18: • Mettre en œuvre des mesures techniques et financières visant à accroître la productivité (rendements à l'hectare) des cultures et de l'élevage sur les terres agricoles existantes non marginales. • Mettre en œuvre des mesures techniques et financières visant à accroître l'approvisionnement en bois, en produits agricoles et en énergie renouvelable non issue de la biomasse provenant de paysages restaurés. • Éviter de fixer des objectifs en matière de bioénergie susceptibles d'entraîner la conversion de terres dégradées ou d'anciennes terres forestières en plantations de biomasse. • Les mesures financières comprennent-elles des incitations politiques ? Une stratégie clé pour faire face à cette pression économique consiste à réorienter les incitations vers les activités d'utilisation des terres nuisibles et vers des pratiques agricoles régénératrices. • Utilisez des évaluations des flux de financement public vers des secteurs clés, tels que l'agriculture ou la sylviculture, pour identifier les domaines où des impacts indésirables et préjudiciables à l'environnement pourraient se produire. Les flux de financement peuvent inclure, entre autres, des subventions ou des incitations.
C19: 13. Il existe des chaînes de valeur et/ou des marchés pour les produits de base (bois, produits agricoles) et les produits environnementaux (carbone, eau, biodiversité) issus des zones restaurées. | D19: =IF(ISBLANK('Étape 2. Évaluer les facteurs'!E26),"",'Étape 2. Évaluer les facteurs'!E26) | I19: • Promouvoir la croissance des marchés (offre et demande) des produits de base (bois, produits agricoles) et des produits environnementaux (carbone, eau, biodiversité) issus des paysages restaurés. • Proposer des financements à faible taux d’intérêt aux entreprises directement impliquées dans la « chaîne de valeur de la restauration ».
B20: g. Conditions de la politique | C20: 14. Les usagers, les propriétaires ou les communautés foncières disposent de droits fonciers garantis sur la terre et ses ressources naturelles | D20: =IF(ISBLANK('Étape 2. Évaluer les facteurs'!E27),"",'Étape 2. Évaluer les facteurs'!E27) | I20: • Réformer les politiques afin de garantir que les gestionnaires fonciers disposent de droits clairs et sûrs sur les terres et les ressources naturelles (par exemple, les arbres) présentes sur leurs terres.
C21: 15. Les politiques relatives à la restauration sont harmonisées et rationalisées | D21: =IF(ISBLANK('Étape 2. Évaluer les facteurs'!E28),"",'Étape 2. Évaluer les facteurs'!E28) | I21: • Conduct an assessment to identify existing policies that might impact the efficacy and efficiency of ecosystem restoration, determine whether or not each is mutually supportive, and recommend policy reforms to achieve greater alignment.
C22: 16. L’exploitation forestière est soumise à des restrictions dans les écosystèmes naturels restants (forêts, pâturages, zones humides, etc.) | D22: =IF(ISBLANK('Étape 2. Évaluer les facteurs'!E29),"",'Étape 2. Évaluer les facteurs'!E29) | I22: • Établir des lois qui limitent l’exploitation forestière ou le défrichement des écosystèmes naturels restants. Établir, renforcer et appliquer des cadres juridiques et réglementaires qui limitent l’exploitation forestière, le défrichement ou la conversion des écosystèmes naturels restants, en assurant la protection à long terme des habitats essentiels et des fonctions écologiques.
C23: 17. Les restrictions s'appliquent à l'exploitation des écosystèmes naturels restants (par exemple, les forêts, les pâturages, les zones humides) | D23: =IF(ISBLANK('Étape 2. Évaluer les facteurs'!E30),"",'Étape 2. Évaluer les facteurs'!E30) | I23: • Mener des campagnes de communication pour sensibiliser les parties prenantes concernées à la loi. • Mettre en place un système de surveillance des changements de la couverture forestière afin d’identifier l’exploitation forestière illégale. • Adopter des mesures coercitives (par exemple, des amendes, le refus d’accès au crédit) contre les violations de la loi. • Veiller à ce que les ressources humaines et financières allouées aux forces de l’ordre soient adéquates.
B24: h. Conditions sociales et culturelles | C24: 18. Les femmes, les jeunes et les peuples autochtones participent à la prise de décision concernant la restauration | D24: =IF(ISBLANK('Étape 2. Évaluer les facteurs'!E31),"",'Étape 2. Évaluer les facteurs'!E31) | I24: • Veiller à ce que les flux financiers relatifs aux biens et/ou services générés par le paysage restauré (par exemple, les paiements pour services écosystémiques) parviennent aux populations vivant dans et autour de la zone restaurée. • Mettre en place des structures financières, telles que des obligations ou des programmes de financement axés sur les résultats, qui récompensent les communautés locales pour la restauration de leur environnement.
C25: 19. La population locale bénéficie de la restauration | D25: =IF(ISBLANK('Étape 2. Évaluer les facteurs'!E32),"",'Étape 2. Évaluer les facteurs'!E32) | I25: • Ensure that financial flows for the goods and/or services generated by the restored landscape (e.g., payments for ecosystem services) go to people living in and around the restored landscape. • Develop financial structures, such as bonds or outcome-based finance schemes, that reward local communities for restoring their environment. • Create participatory monitoring systems that enable local communities to report the benefits of restoration in the near- and long-term and inform future design changes or adjustments. • Allow local people to harvest some of the forest products from the restored landscape..
B26: i. Conditions institutionnelles | C26: 20. Les rôles et les responsabilités en matière de restauration sont clairement définis | D26: =IF(ISBLANK('Étape 2. Évaluer les facteurs'!E33),"",'Étape 2. Évaluer les facteurs'!E33) | I26: • Créer une plateforme ou un comité de restauration des écosystèmes à l’échelle nationale, étatique, locale ou de bassin versant, qui définisse les rôles et les responsabilités des entités gouvernementales, de la société civile, du secteur universitaire et du secteur privé, ainsi que des autres parties prenantes concernées.
C27: 21. Une coordination institutionnelle efficace est maintenue | D27: =IF(ISBLANK('Étape 2. Évaluer les facteurs'!E34),"",'Étape 2. Évaluer les facteurs'!E34) | I27: • Au sein du gouvernement, créer un groupe de travail interministériel sur la restauration des écosystèmes chargé de coordonner les activités gouvernementales (nationales, étatiques et municipales) en matière de restauration. • Créer une initiative de restauration multipartite qui définisse la vision et coordonne les activités de restauration à l’échelle du territoire (par exemple, le PACT de la forêt atlantique du Brésil).
B28: Condition habilitante | C28: Facteur clé | D28: Réponse | E28: Stratégies visant à combler les lacunes en matière de conditions habilitants | F28: National | G28: Régional | H28: Local | I28: Exemples de stratégies pour combler l'écart en matière de facteurs clés
A29: Mettre en œuvre | B29: j. Direction | C29: 22. Il existe des leaders nationaux et/ou locaux de la restauration | D29: =IF(ISBLANK('Étape 2. Évaluer les facteurs'!E36),"",'Étape 2. Évaluer les facteurs'!E36) | I29: • Encourager, soutenir et donner la parole aux futurs leaders locaux de la restauration (particuliers, organisations). • Organiser des réunions rassemblant des leaders locaux de la restauration issus de divers endroits (y compris en dehors de la zone candidate) afin qu'ils s'inspirent mutuellement et partagent leurs bonnes pratiques.
C30: 23. Il existe un engagement politique soutenu | D30: =IF(ISBLANK('Étape 2. Évaluer les facteurs'!E37),"",'Étape 2. Évaluer les facteurs'!E37) | I30: • Créer et mobiliser un large électorat (représentant de multiples secteurs, y compris l'agriculture) qui maintienne la restauration sur l'agenda politique national.
B31: k. Connaissance | C31: 24. Il existe une « expertise technique » pertinente en matière de restauration pour la zone candidate | D31: =IF(ISBLANK('Étape 2. Évaluer les facteurs'!E38),"",'Étape 2. Évaluer les facteurs'!E38) | I31: • Créer des programmes de restauration des écosystèmes dans les universités et les écoles d'agriculture. • Prioriser la restauration des écosystèmes dans les programmes de subventions de recherche publics et privés. • Créer des liens entre les chercheurs et les professionnels de la restauration afin que les premiers puissent mener des recherches pratiques applicables au paysage.
C32: 25. Le « savoir-faire » en matière de restauration est transféré par l'intermédiaire de partenaires ou de services de vulgarisation. | D32: =IF(ISBLANK('Étape 2. Évaluer les facteurs'!E39),"",'Étape 2. Évaluer les facteurs'!E39) | I32: • Faciliter les rencontres entre agriculteurs et les échanges sur les questions de restauration. • Établir des indicateurs clés de performance liés à la restauration des écosystèmes pour les agents de vulgarisation. • Accroître le financement de la formation à la restauration des écosystèmes au sein des services de vulgarisation. • Inclure l’assistance technique à la restauration dans les programmes de financement agricole destinés aux agriculteurs. • Utiliser les technologies modernes de l’information et de la communication pour mieux connecter les agents de vulgarisation et les gestionnaires fonciers, et pour fournir aux deux les recherches et les informations les plus récentes.
B33: l.Conception technique | C33: 26. Le projet de restauration repose sur des bases techniques et adaptées au changement climatique | D33: =IF(ISBLANK('Étape 2. Évaluer les facteurs'!E40),"",'Étape 2. Évaluer les facteurs'!E40) | I33: • Élaborer un plan de restauration fondé sur les meilleures données scientifiques et tenant compte des changements climatiques. • Examiner les plans de restauration issus d’expériences de restauration réussies ailleurs afin de tirer des enseignements sur les meilleures pratiques.
C34: 27. Les limites de restauration «fuites» | D34: =IF(ISBLANK('Étape 2. Évaluer les facteurs'!E41),"",'Étape 2. Évaluer les facteurs'!E41) | I34: • Mettre en place des mesures visant à accroître la productivité par hectare des cultures, de l’élevage ou du bois sur les terres agricoles et forestières existantes. • Mettre en place des mesures visant à réduire la demande de cultures, de bétail ou de bois.
B35: m. Financement et incitations | C35: 28. Les incitations positives et les fonds de restauration l'emportent sur les incitations négatives | D35: =IF(ISBLANK('Étape 2. Évaluer les facteurs'!E42),"",'Étape 2. Évaluer les facteurs'!E42) | I35: • Mettre en place des mécanismes de financement dédiés à la restauration des écosystèmes, tels que : - Subventions - Prêts à faible taux d'intérêt - Allègements fiscaux (sur les intrants, les produits ou le financement de la restauration) - Dépenses publiques directes - Politiques de marchés publics - Paiements pour les services écosystémiques (par exemple, l'eau, le carbone) - Supprimer ou réduire les incitations qui découragent la régénération forestière ou arboricole • Utiliser des évaluations des flux de financement public vers des secteurs clés, tels que l'agriculture ou la sylviculture, afin d'identifier les domaines où des impacts indésirables et néfastes pour l'environnement pourraient se produire. Les flux de financement peuvent inclure, entre autres, des subventions ou des incitations.
C36: 29. Les fonds sont disponibles pour les projets de restauration | D36: =IF(ISBLANK('Étape 2. Évaluer les facteurs'!E43),"",'Étape 2. Évaluer les facteurs'!E43) | I36: • Communiquer et faire connaître activement la disponibilité d’incitations financières et de possibilités de financement grâce à une diffusion accessible et ciblée. • Fournir une assistance technique et administrative aux parties prenantes et aux utilisateurs des terres afin de soutenir les processus de demande, de conformité et de rapport. • Simplifier les procédures de demande et réduire les exigences administratives et documentaires afin de faciliter l’accès aux incitations et aux fonds.
B37: n. Retour | C37: 30. Un système de suivi efficace est mis en place | D37: =IF(ISBLANK('Étape 2. Évaluer les facteurs'!E44),"",'Étape 2. Évaluer les facteurs'!E44) | I37: • Dans la mesure du possible, établir une base de référence (par exemple, des photographies, des images satellites, des données sur les hectares et d'autres mesures du paysage tel qu'il est) afin de permettre des comparaisons au fil du temps. • Développer et mettre en œuvre un système de suivi des performances (y compris la surveillance par télédétection et la surveillance participative sur le terrain).
C38: 31. Les succès précoces et continus sont signalés | D38: =IF(ISBLANK('Étape 2. Évaluer les facteurs'!E45),"",'Étape 2. Évaluer les facteurs'!E45) | I38: • Communiquer publiquement les progrès réalisés en matière de restauration, les réussites et les leçons apprises. Veillez à ce que les histoires trouvent un écho auprès du public cible (par exemple, des images de progrès, des témoignages de bénéfices pour les personnes).
B12562: X
B12563: N'applique pas

Sheet Tableau récapitulatif
A1: TABLEAU RÉCAPITULATIF DU DIAGNOSTIC DE RESTAURATION
A3: Vert = EN SERVICE | D3: Résumé : | F3: Auteur : Organisme coordinateur et année
A4: Jaune = PARTIELLEMENT EN SERVICE | D4: Texte provisoire permettant à l'utilisateur de décrire la portée de cette évaluation, notamment les limites géographiques, la période envisagée pour la restauration et les objectifs de la restauration sur ce site. Le champ d'application peut être défini au niveau national ou en fonction d'un paysage de référence, et peut inclure des processus de consultation pertinents pour les autorités compétentes impliquées dans la planification de la restauration.
A5: Rouge = HORS SERVICE
A7: Thème | B7: Condition habilitante | D7: Facteur clé | E7: Réponse | F7: Stratégies futures pour combler les écarts
A8: Motiver | B8: a. Avantages | D8: La restauration génère des avantages économiques | E8: =IF(ISBLANK('Étape 2. Évaluer les facteurs'!E13),"",'Étape 2. Évaluer les facteurs'!E13) | F8: ='Étape 3. Proposer des stratégie'!E6 -> 0
D9: La restauration génère des avantages sociaux | E9: =IF(ISBLANK('Étape 2. Évaluer les facteurs'!E14),"",'Étape 2. Évaluer les facteurs'!E14) | F9: ='Étape 3. Proposer des stratégie'!E7 -> 0
D10: La restauration génère des avantages environnementaux | E10: =IF(ISBLANK('Étape 2. Évaluer les facteurs'!E15),"",'Étape 2. Évaluer les facteurs'!E15) | F10: ='Étape 3. Proposer des stratégie'!E8 -> 0
B11: b. Conscience | D11: Les avantages de la restauration sont communiqués publiquement. | E11: =IF(ISBLANK('Étape 2. Évaluer les facteurs'!E16),"",'Étape 2. Évaluer les facteurs'!E16) | F11: ='Étape 3. Proposer des stratégie'!E9 -> 0
D12: Les possibilités de restauration sont identifiées | E12: =IF(ISBLANK('Étape 2. Évaluer les facteurs'!E17),"",'Étape 2. Évaluer les facteurs'!E17) | F12: ='Étape 3. Proposer des stratégie'!E10 -> 0
B13: c. Événements de crise | D13: Les événements de crise sont exploités | E13: =IF(ISBLANK('Étape 2. Évaluer les facteurs'!E18),"",'Étape 2. Évaluer les facteurs'!E18) | F13: ='Étape 3. Proposer des stratégie'!E11 -> 0
B14: d. Exigences légales | D14: Il existe des lois et des politiques qui exigent une restauration | E14: =IF(ISBLANK('Étape 2. Évaluer les facteurs'!E19),"",'Étape 2. Évaluer les facteurs'!E19) | F14: ='Étape 3. Proposer des stratégie'!E12 -> 0
D15: Les lois et les politiques sont comprises | E15: =IF(ISBLANK('Étape 2. Évaluer les facteurs'!E20),"",'Étape 2. Évaluer les facteurs'!E20) | F15: ='Étape 3. Proposer des stratégie'!E13 -> 0
A17: Activer | B17: e. Conditions écologiques | D17: Les conditions du sol, de l'eau, du climat et du feu sont adéquates pour la restauration | E17: =IF(ISBLANK('Étape 2. Évaluer les facteurs'!E22),"",'Étape 2. Évaluer les facteurs'!E22) | F17: ='Étape 3. Proposer des stratégie'!E15 -> 0
D18: Les plantes et les animaux susceptibles d'entraver la restauration sont réduits au minimum | E18: =IF(ISBLANK('Étape 2. Évaluer les facteurs'!E23),"",'Étape 2. Évaluer les facteurs'!E23) | F18: ='Étape 3. Proposer des stratégie'!E16 -> 0
D19: Les semences indigènes, des pantules ou des populations sources sont facilement disponibles | E19: =IF(ISBLANK('Étape 2. Évaluer les facteurs'!E24),"",'Étape 2. Évaluer les facteurs'!E24) | F19: ='Étape 3. Proposer des stratégie'!E17 -> 0
B20: f. Conditions économiques | D20: Gestion d'autres activités qui entrent en conflit avec la restauration | E20: =IF(ISBLANK('Étape 2. Évaluer les facteurs'!E25),"",'Étape 2. Évaluer les facteurs'!E25) | F20: ='Étape 3. Proposer des stratégie'!E18 -> 0
D21: Il existe des chaînes de valeur et/ou des marchés pour les produits de base (bois, produits agricoles) et les produits environnementaux (carbone, eau, biodiversité) issus des zones restaurées. | E21: =IF(ISBLANK('Étape 2. Évaluer les facteurs'!E26),"",'Étape 2. Évaluer les facteurs'!E26) | F21: ='Étape 3. Proposer des stratégie'!E19 -> 0
B22: g. Conditions de la politique | D22: Les usagers, les propriétaires ou les communautés foncières disposent de droits fonciers garantis sur la terre et ses ressources naturelles | E22: =IF(ISBLANK('Étape 2. Évaluer les facteurs'!E27),"",'Étape 2. Évaluer les facteurs'!E27) | F22: ='Étape 3. Proposer des stratégie'!E20 -> 0
D23: Les politiques relatives à la restauration sont harmonisées et rationalisées | E23: =IF(ISBLANK('Étape 2. Évaluer les facteurs'!E28),"",'Étape 2. Évaluer les facteurs'!E28) | F23: ='Étape 3. Proposer des stratégie'!E21 -> 0
D24: L’exploitation forestière est soumise à des restrictions dans les écosystèmes naturels restants (forêts, pâturages, zones humides, etc.) | E24: =IF(ISBLANK('Étape 2. Évaluer les facteurs'!E29),"",'Étape 2. Évaluer les facteurs'!E29) | F24: ='Étape 3. Proposer des stratégie'!E22 -> 0
D25: Les restrictions s'appliquent à l'exploitation des écosystèmes naturels restants (par exemple, les forêts, les pâturages, les zones humides) | E25: =IF(ISBLANK('Étape 2. Évaluer les facteurs'!E30),"",'Étape 2. Évaluer les facteurs'!E30) | F25: ='Étape 3. Proposer des stratégie'!E23 -> 0
B26: h. Conditions sociales et culturelles | D26: Les femmes, les jeunes et les peuples autochtones participent à la prise de décision concernant la restauration | E26: =IF(ISBLANK('Étape 2. Évaluer les facteurs'!E31),"",'Étape 2. Évaluer les facteurs'!E31) | F26: ='Étape 3. Proposer des stratégie'!E24 -> 0
D27: La population locale bénéficie de la restauration | E27: =IF(ISBLANK('Étape 2. Évaluer les facteurs'!E32),"",'Étape 2. Évaluer les facteurs'!E32) | F27: ='Étape 3. Proposer des stratégie'!E25 -> 0
B28: i. Conditions institutionnelles | D28: Les rôles et les responsabilités en matière de restauration sont clairement définis | E28: =IF(ISBLANK('Étape 2. Évaluer les facteurs'!E33),"",'Étape 2. Évaluer les facteurs'!E33) | F28: ='Étape 3. Proposer des stratégie'!E26 -> 0
D29: Une coordination institutionnelle efficace est maintenue | E29: =IF(ISBLANK('Étape 2. Évaluer les facteurs'!E34),"",'Étape 2. Évaluer les facteurs'!E34) | F29: ='Étape 3. Proposer des stratégie'!E27 -> 0
A31: Mettre en œuvre | B31: j. Direction | D31: Il existe des leaders nationaux et/ou locaux de la restauration | E31: =IF(ISBLANK('Étape 2. Évaluer les facteurs'!E36),"",'Étape 2. Évaluer les facteurs'!E36) | F31: ='Étape 3. Proposer des stratégie'!E29 -> 0
D32: Il existe un engagement politique soutenu | E32: =IF(ISBLANK('Étape 2. Évaluer les facteurs'!E37),"",'Étape 2. Évaluer les facteurs'!E37) | F32: ='Étape 3. Proposer des stratégie'!E30 -> 0
B33: k. Connaissance | D33: Il existe une « expertise technique » pertinente en matière de restauration pour la zone candidate | E33: =IF(ISBLANK('Étape 2. Évaluer les facteurs'!E38),"",'Étape 2. Évaluer les facteurs'!E38) | F33: ='Étape 3. Proposer des stratégie'!E31 -> 0
D34: Le « savoir-faire » en matière de restauration est transféré par l'intermédiaire de partenaires ou de services de vulgarisation. | E34: =IF(ISBLANK('Étape 2. Évaluer les facteurs'!E39),"",'Étape 2. Évaluer les facteurs'!E39) | F34: ='Étape 3. Proposer des stratégie'!E32 -> 0
B35: l. Conception technique | D35: Le projet de restauration repose sur des bases techniques et adaptées au changement climatique | E35: =IF(ISBLANK('Étape 2. Évaluer les facteurs'!E40),"",'Étape 2. Évaluer les facteurs'!E40) | F35: ='Étape 3. Proposer des stratégie'!E33 -> 0
D36: Les limites de restauration «fuites» | E36: =IF(ISBLANK('Étape 2. Évaluer les facteurs'!E41),"",'Étape 2. Évaluer les facteurs'!E41) | F36: ='Étape 3. Proposer des stratégie'!E34 -> 0
B37: m. Financement et incitations | D37: Les incitations positives et les fonds de restauration l'emportent sur les incitations négatives | E37: =IF(ISBLANK('Étape 2. Évaluer les facteurs'!E42),"",'Étape 2. Évaluer les facteurs'!E42) | F37: ='Étape 3. Proposer des stratégie'!E35 -> 0
D38: Les fonds sont disponibles pour les projets de restauration | E38: =IF(ISBLANK('Étape 2. Évaluer les facteurs'!E43),"",'Étape 2. Évaluer les facteurs'!E43)
B39: n. Retour | D39: Un système de suivi efficace est mis en place | E39: =IF(ISBLANK('Étape 2. Évaluer les facteurs'!E44),"",'Étape 2. Évaluer les facteurs'!E44) | F39: ='Étape 3. Proposer des stratégie'!E37 -> 0
D40: Les succès précoces et continus sont signalés | E40: =IF(ISBLANK('Étape 2. Évaluer les facteurs'!E45),"",'Étape 2. Évaluer les facteurs'!E45) | F40: ='Étape 3. Proposer des stratégie'!E38 -> 0
