Workbook

Sheet Instrucciones
A1: Diagnóstico de restauración
A2: Versión 2.0 - Actualizado en 2026
B4: Informacion general | H4: ¿Cómo funciona el diagnóstico? | N4: Otras consideraciones
B5: ¡Bienvenido al diagnóstico de restauración de WRI! Una herramienta de evaluación rápida para valorar la preparación de una zona geográfica o escala para la restauración y diseñar acciones estratégicas que garanticen el éxito a largo plazo. Una herramienta independiente desarrollada como parte de ROAM (Metodología de evaluación de oportunidades de restauración) https://iucn.org/resources/grey-literature/guide-restoration-opportunities-assessment-methodology-roam | H5: El diagnóstico sigue un proceso de tres pasos; se recomienda encarecidamente leer la sección anterior antes de empezar. Además, se sugiere un paso preparatorio. Consulte la pestaña "Antes de empezar". Cada paso corresponde a una sección de la herramienta, y cada uno de ellos se explica en una pestaña independiente de este documento: Paso 1. Definir el alcance; Paso 2. Evaluar los factores clave para la restauración; Paso 3. Proponer estrategias para subsanar las deficiencias La pestaña «Tabla resumen» genera una tabla resumen basada en los datos introducidos en los pasos 1, 2 y 3. | N5: Cronograma sugerido para la aplicación del diagnóstico Paso 1. Definir el alcance 2-3 días Paso 2. Evaluar los factores clave para la restauración 2-4 semanas Paso 3. Seleccionar acciones para abordar las deficiencias. 2-3 semanas El cronograma sugerido proporciona una estimación indicativa del tiempo necesario para aplicar el diagnóstico. La duración real puede variar en función del contexto, el alcance de la evaluación, la disponibilidad de información, los procesos de participación de las partes interesadas y el tiempo asignado por el equipo de ejecución. En algunos casos, las etapas pueden prolongarse si es necesario realizar consultas adicionales, recopilar datos o llevar a cabo procesos de validación. Por el contrario, el proceso puede avanzar más rápidamente cuando se dispone fácilmente de información y de las partes interesadas.
B10: ¿Qué es la herramienta de diagnóstico de restauración? El Diagnóstico de Restauración te ayuda a evaluar si se dan los factores clave culturales, financieros, políticos, institucionales y ecológicos necesarios para que la restauración de los ecosistemas prospere. Al identificar las carencias y los retos, podrás pasar de una planificación general a una actuación específica y eficaz.
B14: ¿Por qué es útil esta herramienta? Un diagnóstico ayuda a identificar los factores clave que influyen en el éxito de la restauración y permite planificar y actuar de forma más estratégica.
B17: ¿Soy la persona adecuada para utilizar esta herramienta? Deberías utilizar esta herramienta si te encargas de planificar o coordinar políticas, acciones y medidas de restauración a nivel nacional o regional y deseas conocer las condiciones actuales necesarias para llevar a cabo una restauración satisfactoria.
N19: ¿Cuál es el resultado final de este diagnóstico? El diagnóstico permite llegar a un consenso sobre los factores clave que influyen en el éxito de la restauración y establecer un conjunto de medidas priorizadas para reforzar dichos factores y hacer posible la restauración en la zona o a la escala previstas.
H21: La columna "Orientación adicional" ofrece más detalles sobre cada factor clave para orientar sus respuestas en el paso 2.
B22: Nota sobre la participación: Si bien una sola persona puede encargarse de la introducción de datos, la herramienta resulta más eficaz cuando se utiliza de forma participativa, recabando perspectivas de diversos interesados y expertos.
B27: ¿Cuáles son los factores clave? Los factores clave son las condiciones y los elementos que influyen en el éxito y la sostenibilidad a largo plazo de las iniciativas de restauración. Por ejemplo, entre estos factores se incluyen los beneficios que aporta la restauración, los conocimientos disponibles sobre la restauración, las condiciones del mercado y las políticas relacionadas con la restauración, entre otros. A modo de referencia, en el paso 2 se incluye una lista completa de las condiciones propicias y los factores clave.
N29: Documentos a recopilar con antelación (lista no exhaustiva) +Planes, estrategias o programas nacionales de restauración +Compromisos de restauración en el marco de la CDB y la CMNUCC +Leyes o políticas relacionadas con la restauración forestal, agrícola u otros ecosistemas pertinentes +Documentación subnacional de las acciones de restauración +Planes de desarrollo municipal en los paisajes objetivo
H30: Si necesita más información sobre cómo se ha elaborado esta herramienta, puede consultar una explicación detallada por escrito del diagnóstico en línea en: XXXX
B35: Uso de los datos: Sus datos se utilizarán de conformidad con la Política de Privacidad de WRI, que puede consultarse en el siguiente enlace: https://www.wri.org/about/privacy-policy. Nos gustaría destacar que puede interactuar con WRI en línea a través de diversos sitios web, aplicaciones, herramientas de diagnóstico, herramientas digitales, encuestas, correos electrónicos, páginas en redes sociales y otros servicios en línea mediante los cuales llevamos a cabo investigaciones, actividades programáticas, comunicaciones o iniciativas de participación (en conjunto, los "Servicios").

Sheet Antes de empezar
B1: Antes de empezar
B3: Antes de empezar
B4: ¿Por qué completar esta fase? Esta fase de preparación contribuye a garantizar que el diagnóstico se desarrolle sin contratiempos y arroje resultados en los que las partes interesadas confíen y sobre los que puedan actuar. Esto ayuda a garantizar: Alineación: Las funciones y responsabilidades están claras. Inclusión: Se cuenta con la participación de las partes interesadas pertinentes. Eficiencia: La información y los documentos esenciales ya están listos.
B6: Cómo completar esta fase
B7: 1. Nombrar a un responsable del proceso Designar a una persona encargada de coordinar el diagnóstico y de recopilar los resultados. 2. Definir la participación de las partes interesadas Elija cómo las partes interesadas contribuirán a: Talleres para debates grupales y puesta en común rápida Entrevistas sobre temas determinados Aportaciones a distancia de expertos técnicos que colaboran de forma remota 3. Recopilar materiales clave Recopilar documentos y datos relevantes que respalden la evaluación
B9: Diseño de la participación de las partes interesadas
B10: Empieza por analizar el panorama social en torno a la restauración: quiénes son los usuarios, quiénes se ven afectados y quiénes tienen influencia. Identifica las necesidades, las motivaciones y las relaciones de las partes interesadas para comprender dónde pueden surgir fricciones o puntos de coincidencia. Aprovecha esta información para diseñar puntos de contacto —talleres, entrevistas, procesos de retroalimentación— que sean inclusivos, iterativos y se adapten al contexto. Trata a las partes interesadas como co-diseñadores, y no solo como fuentes de datos, para mejorar la facilidad de uso, la relevancia y la aceptación de la herramienta. Herramienta recomendada para cartografiar los paisajes sociales: https://www.wri.org/research/mapping-social-landscapes-guide-identifying-networks-priorities-and-values-restoration
B17: Documentos que se recomienda reunir (lista no exhaustiva)
B18: □ A. Contexto normativo y jurídico [ ] Estrategias o programas nacionales de restauración. [ ] Leyes y reglamentos (silvicultura, agricultura, ordenación del territorio, recursos hídricos). [ ] Compromisos internacionales (CMNUCC, CDB, CNULD). [ ] Planes nacionales de desarrollo y contribuciones nacionalmente determinadas (NDC). □ B. Ejecución y planificación [ ] Planes de acción de restauración a nivel subnacional o regional. [ ] Planes de desarrollo municipal para los paisajes en cuestión. [ ] Documentación de programas financiados por donantes. [ ] Presupuestos institucionales y organigramas existentes. □ C. Datos biofísicos y socioeconómicos [ ] Evaluaciones de la cobertura del suelo y la degradación del suelo. [ ] Mapas de oportunidades de restauración (por ejemplo, resultados de ROAM). [ ] Datos socioeconómicos (situación de tenencia, dependencia de los medios de subsistencia, análisis de mercado). □ D. Seguimiento y valores de referencia [ ] Datos procedentes de sistemas de seguimiento del paisaje (por ejemplo, Global Forest Watch). [ ] Indicadores de restauración existentes e informes de progreso históricos.
B20: Garantizar la inclusión y la equidad
B21: Es posible que algunos participantes se muestren reacios a intervenir en los debates en grupo y las dinámicas sociales y de género locales pueden excluir a ciertos grupos. El equipo coordinador debería adaptar los métodos de participación para garantizar que se tengan en cuenta perspectivas diversas. Esto se puede hacer de la siguiente manera: • organizar grupos de discusión separados para mujeres y/o comunidades indígenas • utilizar las lenguas locales • contar con la participación de intermediarios de confianza • ofrecer ayuda para los desplazamientos o una compensación económica cuando sea necesario • establecer acuerdos para garantizar un espacio seguro • permitir la participación anónima por escrito en el caso de preguntas delicadas

Sheet Paso 1. Definir el alcance
B1: Paso 1. Definir el alcance
B3: ¿Por qué es importante este paso?
B4: En este paso, puedes dedicar un tiempo a definir claramente el alcance de la evaluación. Esto incluye decidir dónde se llevará a cabo el diagnóstico, el plazo previsto y los objetivos de la restauración del paisaje. Tomar estas decisiones desde el principio ayuda a garantizar que el diagnóstico se centre en los aspectos, las partes interesadas y las oportunidades de recuperación adecuados.
B7: Selecciona la zona geográfica y los tipos de ecosistema
B8: Defina el entorno geográfico, la escala o el paisaje en el que se llevará a cabo el diagnóstico. Es importante seleccionar el ámbito geográfico adecuado, ya que determina qué ecosistemas se evaluarán, qué partes interesadas deben participar y qué opciones de restauración son pertinentes. Esto puede incluir: Nacional Subnacional (es decir, municipio, provincia, distrito) Paisaje (o paisaje marino, si procede) Zona de restauración Transfronterizo (es decir, dos o más países)
B14: Captura los tipos de ecosistema
B15: La siguiente lista de ecosistemas es orientativa.
B16: Referencia: Tipología Global de Ecosistemas de la UICN 2.0
B17: https://portals.iucn.org/library/sites/library/files/documents/2020-037-En.pdf, https://global-ecosystems.org/
B18: Terrestre | F18: Agua dulce | I18: Marino
B19: Bosques tropicales y subtropicales | F19: Turberas | I19: Plataformas marinas
B20: Bosques y zonas boscosas templadas y boreales | F20: Humedales | I20: Manglares y sistemas costeros
B21: Matorrales y bosques arbustivos | F21: Ecosistemas ribereños | I21: Fondos marinos profundos
B22: Sabanas y praderas | F22: Cuencas hidrográficas
B23: Desiertos y semidesiertos | F23: Aguas dulces artificiales
B24: Polar-alpino
B25: Sistemas productivos y agrícolas
B26: Paisajes urbanos
B28: Establecer el horizonte temporal
B29: Decide hasta qué punto en el futuro se prevé que llegue el proyecto de restauración. La restauración es un proceso a largo plazo. Aunque algunos beneficios pueden aparecer pronto, muchos resultados ecológicos y sociales tardan años en materializarse. Establecer un plazo claro ayuda a fijar expectativas realistas y garantiza que las iniciativas de restauración se ajusten a las políticas y los ciclos de planificación existentes. Apuesta por una visión a largo plazo, aunque las medidas se pongan en marcha a corto plazo. Siempre que sea posible, hay que ajustar el cronograma a los marcos de planificación nacionales o regionales.
B31: Definir los objetivos de restauración
B32: Aclara qué es lo que quieres conseguir con la restauración del paisaje. Los objetivos de restauración pueden centrarse en un único ecosistema (como los bosques o los manglares) o en una combinación de ecosistemas y usos del suelo, incluidos los sistemas agrícolas o agroforestales. Los objetivos pueden describirse tanto antes como después de ejecutar el diagnóstico, dependiendo del contexto y de cómo se lleve a cabo dicho diagnóstico. Entre los objetivos habituales de la restauración se incluyen (lista no exhaustiva): - Conservación de la biodiversidad - Mitigación o adaptación al cambio climático - Mejora de los medios de vida - Seguridad hídrica - Producción alimentaria Unos objetivos claramente definidos ayudan a determinar qué opciones de restauración se tienen en cuenta y facilitan que las partes interesadas se pongan de acuerdo sobre cómo se definirá el éxito.
B34: Validar el alcance con las partes interesadas
B35: Antes de continuar, confirme el alcance con las partes interesadas pertinentes. Una validación temprana contribuye a generar confianza, un entendimiento común y un sentido de implicación en el proceso de diagnóstico. Además, contribuye a garantizar que la evaluación refleje las prioridades y realidades locales.

Sheet Paso 2. Evaluar los factores
A1: Paso 2. Evalúa los factores clave para la restauración seleccionando una respuesta para cada una de las preguntas siguientes. Se ofrece una definición y una serie de preguntas complementarias para recabar más información
B3: Objetivo En el paso 2 se evalúa si los factores clave para el éxito de la restauración de los ecosistemas están actualmente: • En funcionamiento • Parcialmente en funcionamiento • No en funcionamiento El objetivo no es realizar un análisis exhaustivo de cada aspecto del proceso de restauración, sino identificar rápidamente las fortalezas, las debilidades y los posibles obstáculos para una restauración exitosa. Estructura de la evaluación La evaluación se articula en torno a tres temas generales: 1. Motivar: factores que inspiran o motivan para impulsar procesos que conducen a la restauración 2. Habilitar: factores que crean un contexto favorable para la restauración 3. Implementar: factores relacionados con las capacidades y los recursos para movilizar la implementación de las medidas de restauración sobre el terreno | K3: El código de colores significa lo siguiente:
K4: Verde = EN FUNCIONAMIENTO
K5: Amarillo = PARCIALMENTE EN FUNCIONAMIENTO
K6: Rojo = NO EN FUNCIONAMIENTO
K7: Blanco: NO APLICABLE
B12: Condición habilitante | C12: Factor clave | D12: Pregunta | E12: Respuesta | F12: Nacional | G12: Regional | H12: Local | I12: Definición | J12: Orientación | K12: Pregunta(s) complementaria(s) | L12: Respuestas complementarias, justificación y documentos de soporte
A13: Motivar | B13: a. Beneficios | C13: 1. La restauración genera beneficios económicos | D13: • ¿Se espera que la restauración del área objetivo genere beneficios económicos que resulten en un impacto neto positivo financiero o económico a nivel de toda la economía en relación con el uso actual de la tierra? | I13: Se espera que la restauración del área objetivo produzca beneficios económicos (por ejemplo, diversificación económica, daños evitados, nuevos productos comercializables) que creen un impacto financiero neto positivo (beneficios privados) y/o un impacto neto positivo en toda la economía (beneficios públicos) en relación con el uso de la tierra actual. Nota al margen: “impactos económicos que se refieren a los beneficios ambientales que funcionan como bienes públicos, o a los impactos económicos en toda la economía que capturan los efectos indirectos relacionados con la restauración en las cadenas de valor y la economía en general, incluido el crecimiento del PIB y el empleo. Estos impactos suelen surgir de beneficios económicos como la diversificación, los daños evitados y los nuevos productos de mercado posibilitados por la restauración. | J13: • Los beneficios económicos de la restauración son los resultados positivos globales para los ingresos o las finanzas que se derivan de la aplicación de actividades de restauración frente a un escenario sin cambios. • Algunos ejemplos de beneficios económicos incluyen un mayor ingreso, mejores oportunidades empresariales, una mayor producción de productos básicos clave o nuevas oportunidades de empleo que resultan de los esfuerzos de restauración. Una lista más completa de posibles beneficios se incluye en esta herramienta en la tabla “Beneficios de la Restauración”. • El marco temporal de esta respuesta debe considerar el cronograma de las actividades de restauración previstas, reconociendo que los procesos de restauración y sus beneficios ocurren en el largo plazo. • Siempre que sea posible, distinga entre los beneficios a corto, mediano y largo plazo, incluidos los resultados esperados una vez que la restauración se haya implementado por completo. • Tome nota de qué personas o grupos probablemente recibirían estos beneficios. • Algunos propietarios de tierras pueden estar preocupados de que la “restauración” signifique que perderán sus tierras, sus derechos de uso o sus ingresos en relación con el statu quo. Por lo tanto, la respuesta a esta pregunta puede respaldarse con documentos que muestren cómo los beneficios netos superan los costos. Nota al margen: los derechos territoriales formalizados podrían surgir como un cobeneficio positivo del proyecto de restauración. En algunos casos, la implementación del proyecto y el desembolso de fondos para apoyar las actividades de restauración pueden requerir que se definan claramente derechos sobre la tierra. En consecuencia, esto podría acelerar los procesos de demarcación y permitir que las comunidades locales obtengan títulos legales sobre sus tierras. | K13: • Si la respuesta es “sí”, ¿cuáles son los beneficios económicos esperados? • Si la respuesta es “sí”, ¿quién se beneficia? • Si la respuesta es “no”, ¿cuál es la magnitud de la brecha financiera o económica prevista?
C14: 2. La restauración genera beneficios sociales | D14: • ¿Se espera que la restauración del área objetivo genere beneficios sociales, culturales o políticos para las personas que viven en esa área, incluidos los grupos de mujeres, los jóvenes y los pueblos indígenas? | I14: Se espera que la restauración del área objetivo mejore los medios de vida, eleve la posición social o política de las poblaciones salvaguarde o restaure sitios de patrimonio cultural natural o el uso de prácticas culturalmente significativas, o produzca otros beneficios sociales, culturales y/o políticos para la población local. | J14: • Revise la lista de posibles beneficios sociales en la La tabla "Beneficios de la restauración" se encuentra en los materiales de apoyo para esta herramienta. Por ejemplo, las actividades de restauración pueden reportar beneficios de índole social, cultural o política, como una mayor visibilidad de los valores culturales, el reconocimiento de los conocimientos ecológicos tradicionales, la consecución de logros políticos, el aumento de las oportunidades recreativas o la mejora de la equidad de género. La restauración también puede ser una forma de que los gobiernos sean vistos como líderes en la escena mundial y cumplan los compromisos de los acuerdos internacionales (por ejemplo, CMNUCC, CNULD, CNUDB, REDD+, ODS). Además, la restauración puede ser beneficiosa para países o comunidades con una conexión cultural histórica con los bosques u otros ecosistemas (por ejemplo, tradiciones y folclore basados en los bosques, medios de vida y empleo basados en los ecosistemas). • Considere si los beneficios enumerados en la tabla se reconocen o se consideran en los planes, programas o actividades de restauración en el paisaje objetivo. • Siempre que sea posible, distinga entre los beneficios sociales a corto, mediano y largo plazo, incluidos los resultados esperados una vez que la restauración se haya implementado por completo. • Tome nota de qué personas o grupos probablemente recibirían estos beneficios. | K14: • Si la respuesta es “sí”, ¿cuáles son los beneficios sociales esperados? | L14: ·
C15: 3. La restauración genera beneficios ambientales | D15: • ¿Se espera que la restauración del área objetivo genere beneficios ambientales? | I15: Se espera que la restauración del área objetivo genere beneficios ambientales sustanciales y a largo plazo, incluida la conservación y recuperación de la biodiversidad, una mayor mitigación y adaptación al cambio climático, una menor degradación de la tierra y la desertificación, y la restauración de servicios ecosistémicos vitales como la regulación del agua, la fertilidad del suelo y el secuestro de carbono. Estas mejoras contribuirán a aumentar la resiliencia ecológica y los medios de vida sostenibles a lo largo del tiempo. | J15: Algunos ejemplos de beneficios ambientales incluyen una mayor biodiversidad, una mayor seguridad de las cuencas hidrográficas, una mayor mitigación y adaptación al cambio climático y una mayor fertilidad del suelo, entre otros. En los materiales de apoyo para este diagnóstico se proporciona una descripción más completa de los beneficios ambientales previstos. Tabla “Beneficios de la Restauración”. • Siempre que sea posible, distinga entre los beneficios ambientales a corto, mediano y largo plazo, incluidos los resultados esperados una vez que la restauración se haya implementado por completo. | K15: • Si la respuesta es “sí”, ¿cuáles son los beneficios ambientales esperados? | L15: ·
B16: b. Conscientización | C16: 4. Los beneficios de la restauración se comunican públicamente | D16: • ¿Se comunican los beneficios de restaurar el área objetivo a todas las partes interesadas, incluidos todos grupos poblacionales, y se diseñan canales de comunicación para llegar a estas diversas partes interesadas? | I16: Los beneficios de la restauración del área objetivo se han comunicado claramente a los gestores del territorio, los grupos vulnerables y otras partes interesadas. | J16: • La comunicación puede realizarse a través de diversos canales, incluidos artículos, prensa, redes sociales, radio y televisión, visitas de demostración, obras de teatro callejeras u otras vías dirigidas a las partes interesadas y los responsables de la toma de decisiones pertinentes. • La comunicación entre pares sobre los beneficios de la restauración puede ser un medio eficaz para generar conciencia y motivar la acción. • Considere si esta comunicación está organizada como parte de una estrategia más amplia de participación de las partes interesadas. • Una lista más completa de beneficios se incluye en los materiales de apoyo al diagnóstico en la tabla “Beneficios de la Restauración”. | K16: • ¿Qué beneficios podrían surgir? • ¿Cómo se ha dirigido o incluido específicamente la comunicación a las partes interesadas clave? | L16: ·
C17: 5. Se identifican oportunidades de restauración | D17: • ¿Se han identificado y cuantificado áreas objetivo o prioritarias para la restauración? | I17: Se han identificado y cuantificado áreas candidatas para la restauración. | J17: • Las áreas objetivo para la restauración son los lugares donde deben realizarse esfuerzos de restauración basándose en una combinación de consideraciones ambientales, sociales y económicas, incluyendo su contribución al clima global, la biodiversidad y otros objetivos ambientales. • La información sobre estas oportunidades puede presentarse en mapas nacionales o subnacionales y/o estrategias de restauración, y debe ser coherente con las áreas que las agencias gubernamentales utilizan al asignar fondos, programas y recursos de planificación para la restauración. • Considerar si las partes interesadas reconocen y hacen referencia a los mismos niveles de prioridad. | K17: • Si la respuesta es “sí”, ¿cuáles son las áreas candidatas? • Si la respuesta es “sí”, ¿qué tan grande es la oportunidad de restauración? | L17: ·
B18: c. Eventos de crisis | C18: 6. Los eventos de crisis se aprovechan | D18: • ¿Está experimentando la área objetivo un acontecimiento de crisis, o el riesgo de que se produzca en el futuro, que motivaría la restauración en el paisaje objetivo, y cómo podrían afectar esos acontecimientos a los diferentes grupos de población (rural y campesina, urbana, indígena, mujeres, jóvenes, etc.) y anticiparse a ellos? | I18: El gobierno y/o la sociedad civil utilizan el riesgo o la ocasión de eventos de crisis, incluso considerando escenarios futuros (incluido el climático), para generar apoyo político y público para la restauración de los ecosistemas. | J18: • Los eventos de crisis pueden incluir inundaciones, deslizamientos de tierra, sequías, incendios, tormentas de arena, escasez de madera, disminución del rendimiento de los cultivos, desempleo u otras perturbaciones que afectan a los ecosistemas y los medios de subsistencia. • Las crisis pueden crear oportunidades para catalizar la restauración (por ejemplo, generar impulso político después de un desastre), pero también pueden interrumpir, retrasar o detener los esfuerzos de restauración (por ejemplo, daños a la infraestructura, desvío de fondos, inestabilidad social). • Considere ambas dimensiones: (i) la capacidad de aprovechar las crisis para impulsar la restauración, y (ii) la resiliencia de los esfuerzos de restauración para resistir y recuperarse de las crisis. • Evaluar cómo los distintos grupos pueden verse afectados por los eventos de crisis y las respuestas de recuperación, incluidos los posibles impactos desproporcionados en las poblaciones vulnerables. • Considere si las prioridades de restauración están alineadas con los riesgos climáticos actuales y futuros, y si las inversiones se evalúan en función de su viabilidad climática a largo plazo (más allá de las decisiones de diseño técnico). • En el contexto del cambio climático, considérense tanto los acontecimientos pasados como los escenarios futuros, incluyendo el aumento de la frecuencia e intensidad de los choques climáticos. Herramientas como SPARCLE pueden utilizarse para visualizar rápidamente los impactos del cambio climático. • Cuando sea pertinente, identifique medidas para mitigar los riesgos para la implementación de la restauración (por ejemplo, planificación adaptativa, financiación diversificada, preparación de la comunidad). Aunque las crisis no son deseables, cuando ocurren pueden brindar oportunidades para movilizar el apoyo político y comunitario para la recuperación. | K18: • ¿Qué tipos de crisis han ocurrido en el panorama objetivo en el pasado? • ¿Qué tipos de crisis podrían ocurrir en el futuro? | L18: ·
B19: d. Requisitos legales | C19: 7. Existen leyes y políticas que exigen la restauración | D19: • ¿Existen leyes o políticas que obliguen a los propietarios o administradores de tierras a replantar o restaurar ecosistemas en áreas que han sido taladas (por ejemplo, bosques, pastizales, humedales)? | I19: El gobierno tiene leyes y políticas que requieren que los administradores de tierras permitan la recuperación de la vegetación natural o replantar árboles en ecosistemas naturales que hayan sido talados en el área objetivo. | J19: • Considerar si la legislación exige específicamente la restauración, como requisitos de reforestación, obligaciones de rehabilitar tierras o regulaciones de restauración de actividades extractivas. ¿Estas leyes y políticas especifican quién está obligado a restaurar, en qué situaciones y durante qué plazos? ¿Este marco legal se aplica a todos los límites del área objetivo? (Es decir, ¿los requisitos son de alcance nacional?) • Los requisitos de restauración suelen dirigirse más a las entidades involucradas en la tala comercial, la minería u otras actividades extractivas que a las actividades de subsistencia. | K19: • En caso afirmativo, ¿qué términos y condiciones específicos establece la ley (por ejemplo, qué restaurar, cuándo y cómo)? | L19: ·
C20: 8. Las leyes y políticas que exigen la restauración se comprenden y aplican ampliamente | D20: • ¿La ley o política que exige la restauración o rehabilitación del ecosistema se aplica de manera visible, creíble y justa, y es ampliamente comprendida por todos los actores relevantes, incluyendo a todos los grupos? | I20: Las leyes y políticas que exigen la restauración o rehabilitación de los ecosistemas (incluidas las actividades para recuperar las funciones de los ecosistemas, reducir la degradación o apoyar la regeneración natural) en el paisaje objetivo son comprendidas por los actores pertinentes y se aplican de manera visible, creíble y justa. | J20: • No basta con que exista una ley o política que exija la restauración o rehabilitación; es necesario que se aplique de manera justa, que las entidades afectadas la comprendan y que las autoridades la implementen para que sirva de motivación para la acción. • Considere si los requisitos legales para la restauración o rehabilitación del paisaje se comunican a las partes interesadas clave y se complementan con acciones como campañas de comunicación, medidas coercitivas (por ejemplo, multas) por infracciones y la garantía de recursos humanos y financieros adecuados para su cumplimiento. • Los mandatos gubernamentales de restauración o rehabilitación pueden generar susceptibilidad en torno a la participación del gobierno en decisiones sobre el uso de la tierra que, de otro modo, estarían bajo la jurisdicción de las comunidades tradicionales o los propietarios privados. Por lo tanto, la forma en que se comunican los requisitos legales y se complementan con otras políticas, incentivos y prácticas puede ser fundamental para su eficacia. | K20: • No basta con que exista una ley que exija la restauración; es necesario que las entidades afectadas la comprendan y las autoridades la apliquen para motivar la restauración. | L20: ·
B21: Condición habilitante | C21: Factor clave | D21: Pregunta | E21: Respuesta | F21: Nacional | G21: Regional | H21: Local | I21: Definición | J21: Orientación | K21: Pregunta(s) complementaria(s) | L21: Respuestas complementarias, justificación y documentos de soporte
A22: Habilitar | B22: e. Condiciones ecológicas | C22: 9. Las condiciones del suelo, el agua, el clima y fuego son adecuadas para la restauración. | D22: • ¿Son las condiciones de suelo, precipitaciones, temperatura, fuego y gestión del paisaje objetivo adecuadas para habilitar el crecimiento y la supervivencia de la vegetación plantada o en regeneración natural? | I22: Las condiciones de suelo, pluviosidad y temperatura del área objetivo son adecuadas para el rebrote de la vegetación natural, y el régimen de incendios no dificulta la recuperación de los ecosistemas naturales. | J22: • Este factor clave combina múltiples condiciones ecológicas que afectan la restauración del ecosistema. Cada condición (suelo, precipitaciones, temperatura, incendios) debe evaluarse por separado, pero la respuesta puede reflejar la suma de las cuatro. | K22: • Si la respuesta es “no”, ¿cuáles son las deficiencias en la idoneidad física? ¿Son viables los esfuerzos para superar estas limitaciones? | L22: ·
C23: 10. Se reducen al mínimo las plantas y animales que pueden obstaculizar la restauración | D23: • ¿Es posible eliminar o controlar eficazmente las plantas y los animales invasores no deseados que obstaculizan la recuperación del ecosistema en los sitios de restauración objetivo? | I23: Las especies invasoras persistentes en el área objetivo se pueden gestionar o controlar para evitar que interfieran con la vegetación replantada o en regeneración natural. Los sitios de restauración pueden protegerse del pastoreo del ganado que impide la recuperación del ecosistema. | J23: • Considerar si existen medidas de monitoreo o control (cercas, manejo de malezas, eliminación) para gestionar especies problemáticas o invasoras que puedan competir con o excluir a las especies utilizadas para la restauración. • Los paisajes pueden estar libres de plantas y/o animales no deseados ya sea porque nunca existieron de forma natural en el ecosistema o porque se han minimizado con éxito mediante la gestión. • Algunos ejemplos de especies que pueden obstaculizar los esfuerzos de restauración son Brachiaria spp. en Brasil, Imperata cylindrica en Indonesia, Pueraria montana (kudzu) en el sur de los Estados Unidos y animales de pastoreo no controlados (ganado vacuno, ovejas, cabras) en múltiples lugares. | K23: • Si la respuesta es “no”, ¿cuáles son las especies vegetales y/o animales persistentes y cómo afectan la restauración del ecosistema? | L23: ·
C24: 11. Semillas nativas, plántulas o poblaciones de origen están fácilmente disponibles | D24: • ¿El área objetivo tiene poblaciones fuente, bancos de propágulos del suelo (como sistemas de raíces subterráneas y bancos de semillas) o fuentes de bajo costo de semillas y plántulas nativas que puedan ser la base para la recuperación del ecosistema? | I24: El paisaje objetivo tiene fuentes naturales que apoyan la regeneración, como áreas naturales cercanas, rebrote de raíces subterráneas, semillas dispersadas por animales y fácil acceso a semillas y plántulas nativas de bajo costo que apoyan la recuperación del ecosistema. | J24: • Las poblaciones fuente viables o los bancos de propágulos del suelo de plantas nativas son de vital importancia para la restauración pasiva. • Este factor clave de éxito se aplica a toda la cadena de suministro de semillas y plántulas nativas, incluida la producción de semillas, la recolección y el procesamiento de semillas y los viveros de plántulas. | K24: • Si la respuesta es “no”, ¿dónde está la brecha (por ejemplo, semillas, recolectores de semillas, viveros, poblaciones fuente, bancos de propágulos del suelo)? | L24: ·
B25: f. Condiciones económicas | C25: 12. Gestión de otras actividades que se contraponen a la restauración. | D25: • ¿Están disminuyendo las presiones económicas derivadas de la producción agrícola, ganadera, de leña y/o de biocombustibles sobre las tierras degradadas y los ecosistemas naturales en la zona objetivo, y/o existen mecanismos para gestionar las demandas económicas contrapuestas sobre la tierra que impulsan la degradación de la misma? | I25: Las presiones económicas derivadas de la producción agrícola, ganadera, de leña y/o de biocombustibles sobre las tierras degradadas y los ecosistemas naturales en la zona objetivo están disminuyendo y/o se están gestionando activamente mediante políticas, incentivos, planificación del uso de la tierra o mejoras de la productividad, reduciendo así las presiones que impulsan la degradación de la tierra y "liberando" oportunidades para la restauración. | J25: • Las presiones sobre el uso del suelo que se contraponen a la restauración pueden provenir de la expansión agrícola, el desarrollo de infraestructuras, el pastoreo de ganado, la extracción de leña y la urbanización. • Considere si existen mecanismos para gestionar estas demandas que se contraponen a la restauración, como la planificación del uso del suelo, la zonificación, la intensificación agrícola en tierras existentes, las intervenciones en la cadena de suministro, los incentivos para la producción sostenible o las restricciones a la expansión en ecosistemas naturales. • Este factor clave de éxito es posiblemente uno de los más importantes a la luz de la creciente demanda mundial de tierras para producir cultivos, ganado y biocombustibles (Searchinger et al. 2013) • Este factor clave no se aplicaría cuando la tierra se restaura a sistemas agroforestales o silvopastoriles, que continúan produciendo cosechas y ganado, respectivamente. | K25: • ¿Cuáles son los principales usos alternativos de la tierra en competencia para las áreas candidatas a ser restauradas? | L25: ·
C26: 13. Existen cadenas de valor y/o mercados para productos básicos (madera, productos agrícolas) y productos ambientales (carbono, agua, biodiversidad) de áreas restauradas. | D26: • ¿Existen cadenas de valor, derechos sobre la tierra y políticas que permitan que los productos o servicios procedentes de tierras restauradas lleguen a los consumidores finales? | I26: En la medida en que la restauración forestal en el paisaje objetivo genere productos y servicios comercializables, se establecerán cadenas de valor que permitirán que estos productos lleguen desde el bosque restaurado hasta el consumidor final. | J26: • Este factor clave de éxito se refiere tanto al acceso al mercado como a la demanda del mercado de productos y servicios derivados de paisajes forestales restaurados. Una “cadena de valor” describe los múltiples pasos involucrados en la oferta de un producto o servicio, como la cosecha, la recolección, el procesamiento, el transporte y la distribución. Una cadena de valor derivada de la restauración sugiere que los individuos o grupos en el área objetivo pueden obtener medios de vida y actividades económicas locales como parte de la restauración de los ecosistemas. Además, las cadenas de valor de los productos ambientales incluyen la generación/suministro del servicio, la emisión de créditos de carbono o de naturaleza, la compra de créditos, etc. • Considerar si existen iniciativas, cooperativas o empresas en las áreas objetivo que vendan productos o servicios como resultado de las actividades de restauración. ¿Pueden los productores de estos lugares diferenciar sus productos y servicios a través de etiquetas, certificaciones o acceso a mercados preferenciales? ¿Existe infraestructura para procesar y agregar los productos y servicios ofrecidos desde los ecosistemas? ¿Existen promotores o desarrolladores de proyectos que apoyen la generación de créditos de carbono o de naturaleza? ¿Qué políticas que faciliten los mercados de carbono y naturaleza están en vigor? • Los servicios de los ecosistemas restaurados podrían incluir la recreación, el turismo y el suministro de agua. | K26: • Si la respuesta es “no”, ¿dónde están las brechas en esa cadena de valor? • Si la respuesta es “si”,¿cuál es la cadena de valor, incluidos los productores, intermediarios, consumidores finales, etc.? | L26: ·
B27: g. Condiciones de las políticas | C27: 14. Los usuarios de tierras, los propietarios de tierras o las comunidades tienen derechos de tenencia seguros sobre la tierra y los recursos naturales de la tierra. | D27: • ¿Quienes gestionan el área objetivo tienen derechos claros y seguros para utilizar la tierra, cosechar productos de forma sostenible y recibir los beneficios financieros que se derivarían de la restauración? ¿Estos derechos son accesibles a todas las partes interesadas, incluidas las mujeres y los grupos vulnerables? | I27: Las personas y comunidades que gestionan el área objetivo tienen derechos claros y seguros (por ejemplo, en forma de propiedad de la tierra o derechos de gestión de recursos naturales) sobre los beneficios que se derivarían de la restauración. | J27: • La falta (o inseguridad) de tenencia de la tierra y de derechos sobre los recursos naturales en el área objetivo puede desalentar la restauración que implica intervención humana. La gente no invertirá en plantar árboles y vegetación autóctona ni permitirá la regeneración natural en las tierras que gestiona si no es probable que se beneficie del estado restaurado. • Los derechos de tenencia y sobre los recursos naturales pueden adoptar la forma de propiedad privada de la tierra, tierras comunales, acuerdos consuetudinarios, certificados de derechos de uso, etc. • Considere también si la tenencia vigente se superpone o entra en conflicto con los derechos consuetudinarios. | K27: • Si la respuesta es “no”, ¿qué derechos faltan y para quiénes? | L27: ·
C28: 15. Se armonizan y racionalizan las políticas que afectan a la restauración | D28: • ¿Las políticas que podrían tener un impacto en la restauración del área objetivo están alineadas y optimizadas en un contexto global, nacional, subnacional y local? | I28: Las políticas públicas pertinentes están alineadas, son coherentes y optimizadas para apoyar eficazmente los esfuerzos de restauración en el área objetivo. Estas políticas se refuerzan mutuamente, minimizan las barreras administrativas innecesarias y crean un entorno propicio para su aplicación. Las políticas que promueven la igualdad de género y la inclusión social también se consideran esenciales para apoyar unos resultados de restauración inclusivos y sostenibles. | J28: • Las políticas nacionales sobre clima, biodiversidad y degradación de la tierra probablemente tendrán puntos de superposición para la restauración que pueden considerarse a través de los comités nacionales existentes. • Otras políticas a considerar incluyen aquellas sobre agricultura, industrias extractivas, agua, planificación del uso de la tierra, infraestructura y recursos naturales. • En algunos casos, las políticas de conservación de la naturaleza u otros sectores pueden inhibir la restauración (por ejemplo, leyes que prohíben la extracción de semillas nativas de áreas protegidas, leyes que prohíben la cosecha de especies de árboles nativos, subsidios que incentivan los factores de degradación). | K28: • Si la respuesta es “no”, ¿cuáles políticas no están alineadas o simplificadas? | L28: ·
C29: 16. Existen restricciones a la tala, degradación o perturbación de los ecosistemas naturales restantes (bosques, pastizales, humedales). | D29: • ¿El área objetivo tiene leyes que restringen la tala o desmonte de los ecosistemas naturales restantes? | I29: El área objetivo tiene leyes que restringen la limpieza o tala de los ecosistemas naturales restantes. | J29: • Las restricciones a la tala de los bosques y ecosistemas naturales restantes pueden impedir una mayor expansión de áreas degradadas o taladas. Estas restricciones también crean un incentivo para restaurar la productividad de áreas ya taladas, ya que se reducen las oportunidades de utilizar la frontera forestal. • Las restricciones también pueden adoptar la forma de una extensa red de parques nacionales y bosques nacionales, una extensa red de territorios indígenas forestados, normas de protección de ecosistemas en tierras comunales, normas de “cero pérdidas netas”, porcentajes específicos de tierra que se requiere que permanezca como bosque (por ejemplo, el Código Forestal de Brasil) y más. • Un componente importante de este factor clave de éxito es que los “bosques y ecosistemas naturales” hayan sido claramente definidos por la jurisdicción que patrocina la restricción (por ejemplo, el gobierno nacional). Esta definición debe incluir los bosques primarios, los bosques secundarios y los bosques degradados y otros ecosistemas con potencial de restauración. Nota: Los posibles efectos de desplazamiento o fugas (por ejemplo, el desplazamiento de la limpieza a otras áreas) se abordan en una sección aparte de esta evaluación y deben considerarse junto con esta pregunta. | K29: • Si es así, ¿cuáles son esas leyes? | L29: ·
C30: 17. Se aplican restricciones a la tala de los ecosistemas naturales restantes (por ejemplo, bosques, pastizales, humedales). | D30: • ¿Se aplican adecuadamente estas restricciones de limpieza o tala? | I30: Las leyes que restringen la tala de los ecosistemas naturales restantes se aplican adecuadamente. | J30: • No basta con que existan regulaciones que restrinjan la tala de los ecosistemas naturales restantes; es necesario que las autoridades pertinentes hagan cumplir las restricciones. • Particularmente en áreas remotas, la aplicación de la ley depende de la capacidad de las organizaciones encargadas de hacer cumplir la ley y de los incentivos que tienen para ejercer actividades de aplicación de la ley. | K30: • Si la respuesta es "no", ¿por qué no? | L30: ·
B31: h. Condiciones sociales y culturales | C31: 18. Las mujeres, los jóvenes y los pueblos indígenas participan en la toma de decisiones sobre restauración | D31: • ¿Las mujeres, los jóvenes y los pueblos indígenas que viven en el área objetivo y sus alrededores, junto con los sistemas culturales, las estructuras de gobernanza tradicionales y los sistemas de conocimiento que representan, participan de manera significativa en la toma de decisiones sobre restauración (por ejemplo, diseño de programas, establecimiento de objetivos, gestión, seguimiento y selección de indicadores)? | I31: Se reconoce y apoya explícitamente a las mujeres, los jóvenes y los pueblos indígenas como participantes clave en la planificación y ejecución de la restauración a todas las escalas. Sus sistemas culturales, estructuras de gobernanza tradicionales y conocimientos se respetan e integran en los órganos decisorios, los acuerdos de gobernanza y los procesos de supervisión, garantizando resultados de restauración inclusivos, representativos y culturalmente apropiados. | J31: • La toma de decisiones relacionadas con áreas (incluida la planificación, el diseño, la gestión y el seguimiento) debe ser inclusiva y culturalmente apropiada. Cuando la participación es limitada o extractiva, los esfuerzos de restauración corren el riesgo de fragmentación, debilitamiento de la apropiación local y distribución desigual de los beneficios, especialmente para las mujeres, los jóvenes y los pueblos indígenas. • Aprovechar y fortalecer las instituciones locales existentes y los procesos culturalmente arraigados (por ejemplo, cooperativas forestales a nivel de aldeas, grupos de mujeres, organizaciones de pueblos indígenas, asociaciones de jóvenes y sistemas de gobernanza tradicional) pueden respaldar los acuerdos de cogestión, mejorar la participación local y aumentar la adopción a largo plazo de iniciativas de restauración. • La planificación e implementación de la restauración deben reconocer y respetar los sistemas culturales en general (incluidos los valores, conocimientos y prácticas de diversos grupos de partes interesadas) e integrar estas perspectivas en los procesos de toma de decisiones, gestión y monitoreo. • Una participación eficaz e inclusiva requiere transparencia y rendición de cuentas en la toma de decisiones, respeto por el consentimiento libre, previo e informado (CLPI) cuando corresponda, y mecanismos de quejas y retroalimentación accesibles y confiables que permitan a las partes interesadas plantear sus inquietudes y posibilitar la corrección del curso cuando los procesos o resultados fallan. | K31: • Si la respuesta es "no", ¿qué grupos no están bien representados? • Si la respuesta es "no", ¿de qué aspectos de la restauración quedan excluidos los grupos vulnerables? | L31: ·
C32: 19. La población local se beneficia de la restauración | D32: • ¿Las personas que viven en el área objetivo y sus alrededores pueden capturar o disfrutar los beneficios generados por la restauración, como mejores medios de vida o servicios ecosistémicos? | I32: Las comunidades que viven en las zonas objetivo o en sus alrededores ven atendidas sus necesidades gracias a los esfuerzos de restauración y reciben beneficios medioambientales (por ejemplo, mejora de la calidad del agua, aumento del suministro de productos forestales) o económicos (por ejemplo, fuentes de ingresos alternativas, mejora de los medios de subsistencia) gracias a la restauración. | J32: • La documentación de planificación y el diseño técnico de cualquier iniciativa de restauración deben incluir marcos y mecanismos para garantizar que las personas que viven en las áreas restauradas o adyacentes a ellas sean los principales beneficiarios de los resultados positivos de la restauración. Aquí encontrará ejemplos de los beneficios que puede reportar la restauración. • Los planificadores o implementadores de restauraciones deben preguntarse continuamente: Entre los beneficios sociales, culturales, políticos, medioambientales y económicos identificados, ¿especifican los planes de restauración qué personas o grupos locales se espera que se beneficien de las actividades de restauración? ¿Se corresponden estos beneficios con las necesidades locales? ¿Los beneficios que recibe la población local son razonables, equitativos y confiables? • Si la población local no percibe los beneficios, tendrá pocos incentivos para cambiar sus comportamientos a fin de posibilitar la restauración o sostener el paisaje restaurado a largo plazo. | K32: • Si la respuesta es “no”, ¿qué barreras o limitaciones impiden que las comunidades locales accedan a los beneficios de la restauración? | L32: ·
B33: i. Condiciones institucionales | C33: 20. Los roles y responsabilidades para la restauración están claramente definidos | D33: ¿Están claramente definidos los roles y responsabilidades para la restauración del ecosistema en el área objetivo, son comprendidos por los actores relevantes y acompañados por la autoridad y, cuando es necesario, existen mecanismos de resolución de conflictos? | I33: Los roles y responsabilidades para la restauración en el área objetivo están claramente definidos, son comprendidos entre los actores relevantes (por ejemplo, el gobierno, la sociedad civil, el sector privado y otras partes interesadas pertinentes) y están acompañados por la autoridad. Y existen y se aplican mecanismos de resolución de conflictos | J33: • Considere si existen agencias, instituciones o grupos designados con el poder de implementar la restauración del ecosistema. • En ausencia de claridad sobre los roles y responsabilidades, puede producirse inacción debido a que no se cubren roles importantes, a incertidumbre sobre quién hace qué o a que instituciones y grupos reclaman responsabilidades y derechos superpuestos. • Para responder adecuadamente a esta pregunta, los usuarios tal vez necesiten trazar un mapa de los mandatos existentes para la planificación, coordinación, implementación y monitoreo de la restauración entre entidades públicas, grupos y organizaciones privadas, propietarios de tierras, usuarios de tierras y otras partes interesadas clave. Los roles, responsabilidades y derechos también pueden definirse en leyes, políticas o prácticas consuetudinarias. • Los mecanismos de resolución de conflictos para la restauración de ecosistemas son sistemas estructurados y colaborativos diseñados para gestionar disputas entre las partes interesadas con respecto a la gestión, el acceso y el uso de los recursos naturales u otras actividades durante los proyectos de restauración. | K33: • Si la respuesta es “no”, ¿qué falta en términos de claridad de roles y responsabilidades? | L33: ·
C34: 21. Se mantiene una coordinación institucional eficaz | D34: ¿Se coordinan eficazmente las partes interesadas pertinentes del gobierno, la sociedad civil y el sector privado -por ejemplo, a través de un grupo de trabajo o un proceso multilateral- para diseñar, aplicar y supervisar la restauración del ecosistema en el área candidata, garantizando al mismo tiempo que estos esfuerzos incluyan a los grupos vulnerables? | I34: Los actores relevantes del gobierno, la sociedad civil y/o el sector privado están suficientemente coordinados para diseñar, implementar y supervisar la restauración en el área objetivo. | J34: • Considere si las instituciones públicas y privadas se han comprometido a establecer un liderazgo y mandatos claros para la restauración. ¿Existe una acción conjunta demostrada en forma de mecanismos de coordinación, comités, grupos de trabajo o alianzas que se reúnan periódicamente y tomen decisiones sobre la restauración? ¿Estos esfuerzos de coordinación incluyen planes, datos, aportes técnicos y seguimiento compartidos, especialmente entre los niveles de gobernanza local, regional y nacional? | K34: • Si la respuesta es “no”, ¿qué falta en términos de coordinación? | L34: ·
B35: Condición habilitante | C35: Factor clave | D35: Pregunta | E35: Respuesta | F35: Nacional | G35: Regional | H35: Local | I35: Definición | J35: Orientación | K35: Pregunta(s) complementaria(s) | L35: Respuestas complementarias, justificación y documentos de soporte
A36: Implementar | B36: j. Liderazgo | C36: 22. Existen lideres nacionales y/o locales de restauración | D36: • ¿Existe un defensor carismático y comprometido de la restauración para el área objetivo? ¿Representan a todas las partes interesadas de la sociedad, incluidas las mujeres, los jóvenes y los pueblos indígenas? | I36: Existen personas carismáticas (o instituciones poderosas) que pueden inspirar eficazmente a los responsables de la toma de decisiones para perseguir la restauración, movilizar apoyos y mantener el impulso a lo largo del tiempo en el área candidata | J36: • Los lideres locales de la restauración pueden ser personas o grupos comprometidos con la restauración del área y capaces de actuar en consecuencia. En algunos paisajes o ecosistemas, puede ser necesario resaltar a los lideres de restauracion y darles un perfil visible. • Históricamente, los ejemplos exitosos de restauración contaron con un promotor o un fuerte apoyo gubernamental. Pocos carecían de ambos. | K36: • ¿Quién es el lider local de la restauración(es)?
C37: 23. Existe un compromiso político sostenido | D37: • ¿Existe un compromiso claro y sostenido a largo plazo por parte de las instituciones gubernamentales y no gubernamentales para apoyar los esfuerzos de restauración en el área objetivo, incluidos los presupuestos asignados? | I37: El compromiso de las autoridades gubernamentales (en los niveles pertinentes, cuando corresponda) y de las instituciones no gubernamentales con la restauración en el área objetivo está claramente establecido y reconocido como un compromiso sostenido y de largo plazo y con un presupuesto asignado. | J37: • Puede ser difícil predecir el compromiso a largo plazo de un gobierno u organización. En tales situaciones, hay que considerar si el compromiso trasciende a los partidos políticos y si la restauración producirá beneficios recurrentes para las principales partes interesadas. • Los objetivos de restauración del gobierno podrían ser apoyados con fondos públicos específicos. A la hora de revisar, compruebe si los objetivos llevan aparejado un presupuesto o mecanismo de financiación claro, que indique una demanda real y sostenida, o si existe un plan de financiación. | K37: • En caso afirmativo, ¿cuál es la prueba del compromiso expreso y de quién?
B38: k. Conocimiento | C38: 24. Existen "conocimientos técnicos" de restauración pertinentes para el área candidata | D38: • ¿Existe conocimiento local diverso (incluido el conocimiento indígena, el conocimiento ecológico tradicional y el conocimiento con perspectiva de género) sobre cómo implementar la restauración a escala en el área objetivo? | I38: Los expertos locales conocen las técnicas de restauración (por ejemplo, regeneración natural y asistida, conocimientos tradicionales) adaptadas al área candidata, o generan investigaciones al respecto. | J38: • La experiencia local puede provenir del conocimiento tradicional de las comunidades que viven en el paisaje o sus alrededores, de expertos de universidades y servicios de extensión rural, y de organizaciones no gubernamentales activas en ese campo. • El conocimiento puede generarse localmente o importarse de otro lugar, pero debe ser comunicado o impartido por profesionales locales. Se puede obtener orientación sobre “mejores prácticas” en materia de restauración de parte de universidades, organizaciones no gubernamentales o agencias de extensión, así como también de individuos o grupos locales con experiencia en restauración a largo plazo. | K38: • Si la respuesta es “no”, ¿cuáles son las lagunas de conocimiento más importantes?
C39: 25. El "saber hacer" de la restauración se transfiere a través de homólogos o servicios de extensión | D39: • ¿Existen servicios de extensión, visitas de agricultor a agricultor, grupos de mujeres, redes locales y/u otros medios de concientización y desarrollo de capacidades para la restauración, y cuentan con los recursos adecuados en el área objetivo o a nivel nacional? | I39: Se cuenta con asistencia técnica y extensión rural (“servicios de extensión”), visitas de agricultor a agricultor, grupos de mujeres, redes locales y/u otros medios de concientización y desarrollo de capacidades para la restauración, y se cuenta con los recursos adecuados en el área candidata. | J39: • El intercambio de conocimientos puede documentarse en servicios de extensión formales, como visitas de campo, programas de capacitación, escuelas de campo, materiales impresos y sitios de demostración. • Considerar si los grupos de aprendizaje informales sobre restauración están compartiendo información o coordinando actividades, incluidos grupos de mujeres, asociaciones de productores o intercambio de conocimientos entre pueblos indígenas. Esta comunicación de "agricultor a agricultor" o de "gestor de tierras a gestor de tierras" puede ser uno de los medios más eficaces de educación y formación. • Las redes o asociaciones locales para el desarrollo de capacidades en materia de restauración de ecosistemas, agroforestería o reforestación pueden ser mencionadas en documentos o informes nacionales de organizaciones no gubernamentales. | K39: • Para el panorama candidato, ¿qué entidades están mejor posicionadas para prestar servicios de extensión?
B40: l. Diseño técnico | C40: 26. El diseño de la restauración tiene una base técnica y adaptada al cambio climático | D40: • ¿El plan de restauración del área objetivo se basa en las mejores prácticas, incorporando la mejor ciencia disponible, el conocimiento ecológico tradicional y enfoques resilientes al clima? | I40: El plan de restauración se basa en las mejores prácticas de diseño, ejecución y mantenimiento de las actividades de restauración. El plan de restauración del paisaje incorpora la mejor ciencia disponible y enfoques resilientes al clima que garantizan que la intervención, incluidos aspectos como la selección de especies y las técnicas de restauración, sea apropiada para el contexto local y los objetivos de la intervención, y reduzca la vulnerabilidad de la intervención de restauración a los impactos climáticos como sequías, inundaciones, incendios forestales y temperaturas extremas. | J40: • Considerar si los enfoques para la restauración de los ecosistemas están respaldados por la investigación científica, el conocimiento local o las prácticas indígenas para recuperar los ecosistemas naturales y reducir la vulnerabilidad a los impactos climáticos. • El diseño técnico debe abordar aspectos tales como la preparación del sitio, la pendiente, la selección de especies, el espaciamiento de los árboles y el mantenimiento, o cómo eliminar las presiones que impiden que la vegetación natural vuelva a crecer (por ejemplo, el ganado, los incendios). • Los planes de restauración deben tener en cuenta los impactos climáticos proyectados para ser resilientes al clima. | K40: • Si la respuesta es “no”, ¿qué falta en el plan?
C41: 27. La restauración limita las "fugas" | D41: • ¿El proceso de restauración cuenta con disposiciones establecidas (por ejemplo, políticas, prácticas, incentivos, mejoras de rendimiento) que limiten las fugas o se está desarrollando de una manera que las reduce? ¿Las actividades de restauración evitan el desplazamiento de los usuarios de la tierra a otras zonas en las que no tienen más opción que transformar/limpiar ecosistemas naturales para usos agrícolas de la tierra? | I41: La restauración de los ecosistemas en el área candidata evita la transferencia de las actividades de desmonte a otros lugares ("fugas"), lo que se traduce en un aumento neto de la superficie restaurada. | J41: • Existe el riesgo de que la restauración del ecosistema en el área objetivo pueda resultar en el desplazamiento de las actividades que estaban causando la degradación de la tierra a algún otro paisaje. • Si bien dicha “fuga” podría resultar en un aumento de la cantidad de área restaurada en el paisaje objetivo, también resultaría en un aumento de tierras degradadas o deforestadas en otros lugares. • Las formas de limitar las fugas de las actividades de restauración podrían incluir: Combinar la restauración con usos productivos (por ejemplo, agroforestería), brindar alternativas de sustento locales que no requieran convertir tierras en tierras agrícolas, aumentar la eficiencia agrícola para que la producción no se traslade a nuevas áreas, planificar la restauración a nivel del paisaje para gestionar dónde cambian las actividades y abordar los factores subyacentes de la degradación. • Para obtener más información sobre la reforestación en un país que desplaza la deforestación a otro país, consulte: Meyfroidt y Lambin (2011). | K41: • Si la respuesta es “no”, ¿qué medidas faltan en el proceso de restauración para evitar el desplazamiento de la degradación de la tierra a otras áreas?
B42: m. Financiamiento e incentivos | C42: 28. Los incentivos positivos y los fondos para la restauración superan a los incentivos negativos | D42: • Desde la perspectiva de las partes interesadas pertinentes, ¿los incentivos financieros y los mecanismos de financiación disponibles fomentan suficientemente la restauración en el área objetivo, en comparación con los incentivos que pueden desalentar o impedir la recuperación del ecosistema? | I42: Desde la perspectiva de las partes interesadas pertinentes, los incentivos financieros y los mecanismos de financiación para apoyar la restauración en la zona candidata están disponibles, son accesibles y suficientemente atractivos para fomentar la inversión en actividades de restauración. Estos incentivos están diseñados para compensar los costos de oportunidad y los riesgos financieros asociados con la restauración, y para compensar los incentivos competitivos que favorecen usos de la tierra o prácticas que obstaculizan o retrasan la recuperación del ecosistema. El marco general de incentivos apoya el compromiso sostenido con la restauración a largo plazo. | J42: • La restauración puede ocurrir cuando los incentivos generales superan tanto los costos de la restauración como los beneficios continuos que se obtienen en el paisaje degradado. • Los incentivos “positivos” (por ejemplo, subvenciones, préstamos, exenciones fiscales, subsidios, pagos por servicios ecosistémicos, bienes y servicios privados) fomentan la restauración, mientras que los incentivos “negativos” (por ejemplo, subsidios para la ganadería, la agricultura o las industrias extractivas) la desalientan. • Si los incentivos positivos se ven eclipsados por los negativos, es poco probable que haya una restauración a gran escala; y tanto la cantidad como el momento de los incentivos importan. • Los incentivos y la financiación son parte de la implementación porque afectan directamente las decisiones de los administradores de tierras para restaurar. • También se pueden analizar los compromisos corporativos para el área propuesta, los cuales se refieren a los compromisos de las empresas para restaurar ecosistemas o cumplir objetivos climáticos y de biodiversidad. Al revisar, compruebe si estos compromisos son específicos, mensurables y están vinculados a acciones concretas o a la financiación de la restauración. | K42: • ¿Cuáles son los principales incentivos positivos y negativos que influyen en las decisiones de restauración y uso de la tierra en el paisaje objetivo? • Desde la perspectiva de las partes interesadas pertinentes, ¿cuál es la magnitud o escala de estos incentivos (por ejemplo, valor financiero por hectárea o medidas comparables)?
C43: 29. Hay financiación disponible para acciones de restauración | D43: ¿Son los incentivos financieros y los mecanismos de financiación destinados a promover la restauración en el área objetivo accesibles, inclusivos y utilizables por una amplia gama de partes interesadas, incluidas las comunidades locales, garantizando al mismo tiempo la sostenibilidad a largo plazo? | I43: Los mecanismos e incentivos financieros han sido cuidadosamente diseñados, seleccionados y aplicados para apoyar eficazmente las políticas, acciones y medidas de restauración, tanto a escala del paisaje como de la comunidad. Estos mecanismos son accesibles a un amplio abanico de partes interesadas, promueven la participación equitativa y aprovechan la financiación del sector privado, cuando procede, para mejorar y mantener los resultados de la restauración. La financiación a largo plazo se refiere a los recursos financieros que se comprometen a apoyar actividades durante un largo periodo de tiempo, garantizando la continuidad y la estabilidad. | J43: • Los incentivos y fondos incluyen subvenciones, préstamos, exenciones fiscales sobre los insumos, productos o financiación de la restauración, gastos gubernamentales directos como subsidios o políticas de adquisiciones, pagos por servicios ecosistémicos o mercados privados de bienes y servicios que fomentan los esfuerzos de restauración de los ecosistemas. • Considere si las personas, comunidades o grupos en las áreas de restauración han solicitado y recibido apoyo financiero para actividades de restauración. Incluya comentarios de las personas o grupos que han intentado acceder a estos incentivos o fondos pero no lo han conseguido. • La financiación a largo plazo y los mecanismos de mercado se refieren al apoyo financiero sostenido para actividades a lo largo del tiempo, incluidas fuentes de financiación específicas o sistemas que generan una demanda continua, como los mercados de crédito ambiental. Al realizar la revisión, verifique si existen compromisos de financiación plurianuales o instrumentos basados en el mercado que puedan respaldar de manera confiable la implementación. | K43: • Si la respuesta es “no”, ¿cuáles son las barreras de acceso?
B44: n. Retroalimentación | C44: 30. Existe un sistema eficaz de monitoreo para el seguimiento | D44: ¿Existe un sistema de seguimiento para el seguimiento y evaluación del progreso de la restauración a nivel paisajístico o nacional pertinente, y está alineado con los sistemas de seguimiento nacionales y globales? | I44: Existe un sistema para supervisar los progresos y evaluar el impacto de la restauración en el área candidata. | J44: • La información para el seguimiento y la evaluación debe recopilarse de forma planificada y continua para proporcionar conocimiento y retroalimentación sobre la implementación de las actividades de restauración. Los aspectos a supervisar pueden incluir las hectáreas restauradas, las tasas de supervivencia de las especies plantadas, los beneficios económicos y sociales cuantificados y los flujos de servicios ecosistémicos. • Los sistemas de seguimiento y evaluación pueden emplear enfoques como la teledetección, el seguimiento a nivel del suelo con participación colectiva (por ejemplo, utilizando tecnologías de la comunidad, voluntarios y comunicaciones) y encuestas a los habitantes del área objetivo. | K44: • Si la respuesta es “si”, ¿ya se están recopilando datos de referencia? • Si la respuesta es “no”, ¿qué aspectos de un sistema de supervisión del desempeño faltan?
C45: 31. Se comunican los éxitos tempranos y continuos | D45: • ¿Se comunican los éxitos de la restauración y se identifica al público objetivo? | I45: Los éxitos clave en la restauración del área candidata se comparten rápidamente con las partes interesadas, lo que garantiza que estén informadas del progreso y fomenta un sentido de asociación y compromiso. | J45: • La comunicación puede adoptar la forma de documentación y cobertura de historias en campañas mediáticas y redes sociales, pero también puede incluir observación directa a través de visitas de agricultores, administradores de tierras y tomadores de decisiones a los sitios de restauración. • Lograr y comunicar públicamente el éxito, incluidos los “éxitos tempranos”, puede ayudar a mantener el impulso, atraer más participación, generar réplicas en otras partes del panorama, apuntalar el apoyo político y sostener el financiamiento externo. | K45: • Si la respuesta es “sí”, ¿cómo se comunican los éxitos (por ejemplo, a través de qué medios)? • Si la respuesta es “no”, ¿qué medios están disponibles y podrían utilizarse?
B12568: X
B12569: No aplicable
B12571: En funcionamiento
B12572: Parcialmente en funcionamiento
B12573: No en funcionamiento
B12574: No aplicable

Sheet Paso 3. Proponer estrategias
A1: Paso 3. Seleccionar medidas estratégicas para subsanar las deficiencias en factores clave
B3: Objetivo El paso 3 te ayudará a diseñar estrategias para abordar los factores clave que faltan o que solo se han implementado parcialmente. El objetivo es identificar medidas que aumenten las probabilidades de que la restauración tenga éxito en la zona en cuestión. Estrategias de identificación Los usuarios hacen una lluvia de ideas y anotan propuestas a partir de las categorías de ejemplo que se indican a continuación, que puedan servir para mejorar los factores de éxito que faltan o que son débiles: • Políticas • Incentivos • Reformas institucionales • Medidas de desarrollo de capacidades • Intervenciones intersectoriales (por ejemplo, agricultura, finanzas, tenencia de la tierra) Consideraciones clave: • Una estrategia puede abordar varias carencias • Las estrategias deben especificar claramente: • Quién actuará • Qué se hará • Por qué • Para cuándo • Cómo, incluyendo cómo se financiarán las acciones En la herramienta se ofrecen ejemplos de estrategias, pero estos son meramente ilustrativos, no prescriptivos. El contexto local y el criterio propio son fundamentales.
B5: Condición habilitante | C5: Factor clave | D5: Respuesta | E5: Estrategias para subsanar las deficiencias en las condiciones habilitantes | F5: Nacional | G5: Regional | H5: Local | I5: Ejemplos de estrategias para abordar las brechas en factores clave
A6: Motivar | B6: a. Beneficios | C6: 1. La restauración genera beneficios económicos | D6: =IF(ISBLANK('Paso 2. Evaluar los factores'!E13),"",'Paso 2. Evaluar los factores'!E13) | I6: • Realizar un análisis costo-beneficio comparando (a) los probables beneficios generados por el área restaurada, (b) los probables costos de restaurar el paisaje objetivo, y (c) los probables costos y beneficios del uso actual del ecosistema. • Explore metodologías de contabilidad de ecosistemas para evaluar los beneficios económicos de los servicios ecosistémicos (por ejemplo, UNSEEA) y la capacidad de las oficinas nacionales de estadística para llevar a cabo dichas evaluaciones.
C7: 2. La restauración genera beneficios sociales | D7: =IF(ISBLANK('Paso 2. Evaluar los factores'!E14),"",'Paso 2. Evaluar los factores'!E14) | I7: • Involucrar a las comunidades que viven en el área objetivo y sus alrededores para identificar sus objetivos y prioridades sociales, políticas o culturales. Esto podría hacerse mediante encuestas o talleres presenciales. Con base en este ejercicio, co-creen un mapa de intervenciones de restauración que podrían ayudar a lograr estos objetivos. • Validar los planes de restauración existentes, los instrumentos de financiamiento, los sistemas de monitoreo y los indicadores con las comunidades locales, incluidos representantes de poblaciones vulnerables, para garantizar que los planes satisfagan las necesidades de la comunidad.
C8: 3. La restauración genera beneficios ambientales | D8: =IF(ISBLANK('Paso 2. Evaluar los factores'!E15),"",'Paso 2. Evaluar los factores'!E15) | I8: • Involucrar a científicos (por ejemplo, biólogos, ecólogos, hidrólogos, científicos del suelo) para identificar qué beneficios ambientales podrían generarse a partir de los esfuerzos de restauración.
B9: b. Conscientización | C9: 4. Los beneficios de la restauración se comunican públicamente | D9: =IF(ISBLANK('Paso 2. Evaluar los factores'!E16),"",'Paso 2. Evaluar los factores'!E16) | I9: • Elaborar materiales y campañas de concienciación a través de periódicos, radio, televisión, internet o visitas a sitios, según el público objetivo. • Introducir o aprovechar las actividades nacionales de restauración existentes, como programas públicos o escolares de plantación de árboles.
C10: 5. Se identifican oportunidades de restauración | D10: =IF(ISBLANK('Paso 2. Evaluar los factores'!E17),"",'Paso 2. Evaluar los factores'!E17) | I10: • Realizar una actividad de planificación de “Metodología de evaluación de oportunidades de restauración”. Se trata de un completo recurso de planificación de la restauración disponible en línea https://iucn.org/resources/grey-literature/guide-restoration-opportunities-assessment-methodology-roam
B11: c. Eventos de crisis | C11: 6. Los eventos de crisis se aprovechan | D11: =IF(ISBLANK('Paso 2. Evaluar los factores'!E18),"",'Paso 2. Evaluar los factores'!E18) | I11: • Realizar y comunicar investigaciones que cuantifiquen y visualicen hasta qué punto los ecosistemas restaurados pueden prevenir o mitigar desastres humanitarios naturales y ahorrar dinero en esfuerzos de mitigación cuando se implementan una planificación y una prevención adecuadas. • Cuando ocurran desastres, comunicar públicamente de inmediato los beneficios de la restauración.
B12: d. Requisitos legales | C12: 7. Existen leyes y políticas que exigen la restauración | D12: =IF(ISBLANK('Paso 2. Evaluar los factores'!E19),"",'Paso 2. Evaluar los factores'!E19) | I12: • Establecer una ley gubernamental (o una política industrial) que requiera que los administradores de tierras permitan la recuperación de la vegetación o la replanten en áreas que hayan sido taladas debido a su propia actividad comercial (por ejemplo, tala, minería, etc.).
C13: 8. Las leyes y políticas que exigen la restauración se comprenden y aplican ampliamente | D13: =IF(ISBLANK('Paso 2. Evaluar los factores'!E20),"",'Paso 2. Evaluar los factores'!E20) | I13: • Realizar una campaña de comunicación para concientizar a los actores relevantes sobre los requerimientos de restauración. • Adoptar medidas coercitivas (por ejemplo, multas, denegación de acceso al crédito, cárcel) contra las violaciones de los requisitos de restauración. • Garantizar que los recursos humanos y financieros para la aplicación de la ley sean adecuados.
B14: Condición habilitante | C14: Factor clave | D14: Respuesta | E14: Estrategias para subsanar las deficiencias en las condiciones habilitantes | F14: Nacional | G14: Regional | H14: Local | I14: Ejemplos de estrategias para abordar las brechas en factores clave
A15: Habilitar | B15: e. Condiciones ecológicas | C15: 9. Las condiciones del suelo, el agua, el clima y fuego son adecuadas para la restauración. | D15: =IF(ISBLANK('Paso 2. Evaluar los factores'!E22),"",'Paso 2. Evaluar los factores'!E22) | I15: • Gestionar o ajustar de forma adaptativa el plan de restauración (por ejemplo, la combinación de especies) para que coincida con el régimen hídrico y climático del paisaje. • Implementar un programa para prevenir incendios no deseados o introducir quemas prescritas. • Implementar un programa para mejorar la calidad del suelo (por ejemplo, plantando especies fijadoras de nitrógeno). • Crear diques o medialunas para almacenar agua después de las lluvias.
C16: 10. Se reducen al mínimo las plantas y animales que pueden obstaculizar la restauración | D16: =IF(ISBLANK('Paso 2. Evaluar los factores'!E23),"",'Paso 2. Evaluar los factores'!E23) | I16: • Implementar un programa para eliminar plantas invasoras (por ejemplo, utilizando árboles nativos de rápido crecimiento para dar sombra a las invasoras, utilizando cabras, uso apropiado del fuego). • Implementar un programa para excluir al ganado errante no deseado (por ejemplo, incentivos y capacitación sobre cercas).
C17: 11. Semillas nativas, plántulas o poblaciones de origen están fácilmente disponibles | D17: =IF(ISBLANK('Paso 2. Evaluar los factores'!E24),"",'Paso 2. Evaluar los factores'!E24) | I17: • Establecer leyes que protejan las áreas restantes de vegetación nativa en el área candidato. • Crear incentivos financieros y programas de desarrollo de capacidades destinados a fortalecer y aumentar el número y la calidad de los viveros de plántulas y las redes de recolectores de semillas.
B18: f. Condiciones económicas | C18: 12. Gestión de otras actividades que se contraponen a la restauración. | D18: =IF(ISBLANK('Paso 2. Evaluar los factores'!E25),"",'Paso 2. Evaluar los factores'!E25) | I18: • Aplicar medidas técnicas y financieras para aumentar la productividad (rendimientos por hectárea) de los cultivos y el ganado en las tierras agrícolas no marginales existentes. • Implementar medidas técnicas y financieras para aumentar el suministro de madera y productos agrícolas y de energía renovable no derivada de biomasa procedente de paisajes restaurados. • Evitar establecer objetivos de bioenergía que puedan dar lugar a que tierras degradadas o antiguas tierras forestales se conviertan en plantaciones de biomasa. • ¿Las medidas financieras incluyen incentivos políticos? Una estrategia clave para abordar esta presión económica es redirigir los incentivos hacia actividades de uso de la tierra nocivas y hacia prácticas agrícolas regenerativas. • Utilise evaluaciones de los flujos de financiación pública hacia sectores clave, como la agricultura o la silvicultura, para identificar dónde pueden estar produciéndose impactos no deseados y perjudiciales para el medio ambiente. Los flujos de financiación pueden incluir subvenciones o incentivos, entre otros.
C19: 13. Existen cadenas de valor y/o mercados para productos básicos (madera, productos agrícolas) y productos ambientales (carbono, agua, biodiversidad) de áreas restauradas. | D19: =IF(ISBLANK('Paso 2. Evaluar los factores'!E26),"",'Paso 2. Evaluar los factores'!E26) | I19: • Fomentar el crecimiento de los mercados (tanto de oferta como de demanda) de productos básicos (madera, productos agrícolas) y productos ambientales (carbono, agua, biodiversidad) derivados de paisajes restaurados. • Proporcionar financiamiento a bajo interés para las empresas directamente involucradas en la “cadena de valor de la restauración”.
B20: g. Condiciones de las políticas | C20: 14. Los usuarios de tierras, los propietarios de tierras o las comunidades tienen derechos de tenencia seguros sobre la tierra y los recursos naturales de la tierra. | D20: =IF(ISBLANK('Paso 2. Evaluar los factores'!E27),"",'Paso 2. Evaluar los factores'!E27) | I20: • Reformar las políticas para garantizar que los administradores de tierras tengan derechos claros y seguros sobre la tierra y los recursos naturales (por ejemplo, los árboles) en sus tierras.
C21: 15. Se armonizan y racionalizan las políticas que afectan a la restauración | D21: =IF(ISBLANK('Paso 2. Evaluar los factores'!E28),"",'Paso 2. Evaluar los factores'!E28) | I21: • Realizar una evaluación para identificar las políticas existentes que podrían incidir en la eficacia y eficiencia de la restauración del ecosistema, determinar si cada una de ellas se apoya mutuamente y recomendar reformas de políticas para lograr una mayor alineación.
C22: 16. Existen restricciones a la tala, degradación o perturbación de los ecosistemas naturales restantes (bosques, pastizales, humedales). | D22: =IF(ISBLANK('Paso 2. Evaluar los factores'!E29),"",'Paso 2. Evaluar los factores'!E29) | I22: • Establecer leyes que restrinjan la tala o el desmonte de los ecosistemas naturales restantes. Establecer, fortalecer y hacer cumplir marcos legales y regulatorios que restrinjan la tala, el desmonte o la conversión de los ecosistemas naturales restantes, asegurando la protección a largo plazo de los hábitats críticos y las funciones ecológicas.
C23: 17. Se aplican restricciones a la tala de los ecosistemas naturales restantes (por ejemplo, bosques, pastizales, humedales). | D23: =IF(ISBLANK('Paso 2. Evaluar los factores'!E30),"",'Paso 2. Evaluar los factores'!E30) | I23: • Realizar campañas de comunicación para concientizar a los actores relevantes sobre la ley. • Establecer un sistema de monitoreo del cambio de cobertura forestal para identificar la tala ilegal. • Adoptar medidas coercitivas (por ejemplo, multas, denegación de acceso al crédito) contra las infracciones de la ley. • Garantizar que los recursos humanos y financieros para la aplicación de la ley sean adecuados.
B24: h. Condiciones sociales y culturales | C24: 18. Las mujeres, los jóvenes y los pueblos indígenas participan en la toma de decisiones sobre restauración | D24: =IF(ISBLANK('Paso 2. Evaluar los factores'!E31),"",'Paso 2. Evaluar los factores'!E31) | I24: • Involucrar a representantes de las personas que viven en el área objetivo y sus alrededores en el proceso de restauración (por ejemplo, establecimiento de objetivos, diseño, implementación, monitoreo y selección de indicadores) y en los mecanismos de gobernanza (por ejemplo, grupos de múltiples partes interesadas). • Cultivar defensores de la restauración en las comunidades locales realizando esfuerzos de desarrollo de capacidades o desarrollando estructuras financieras que prioricen proyectos de restauración liderados por la comunidad. • Adoptar medidas inclusivas (por ejemplo, métodos de facilitación interculturales o adaptables, convocatorias abiertas, talleres en idiomas locales) para convocar y reflejar las diversas perspectivas de todas las personas en el paisaje. • Utilizar datos desglosados por sexo al medir la participación, los beneficios y otros resultados de la restauración.
C25: 19. La población local se beneficia de la restauración | D25: =IF(ISBLANK('Paso 2. Evaluar los factores'!E32),"",'Paso 2. Evaluar los factores'!E32) | I25: • Garantizar que los flujos financieros para los bienes y/o servicios generados por el paisaje restaurado (por ejemplo, pagos por servicios ecosistémicos) lleguen a las personas que viven en el área restaurado y sus alrededores. • Desarrollar estructuras financieras, como bonos o esquemas de financiación basados en resultados, que recompensen a las comunidades locales por restaurar su medio ambiente. • Crear sistemas de monitoreo participativo que permitan a las comunidades locales informar sobre los beneficios de la restauración en el corto y largo plazo e informar sobre futuros cambios o ajustes de diseño. • Permitir que la gente local coseche algunos de los productos forestales del ecosistema restaurado.
B26: i. Condiciones institucionales | C26: 20. Los roles y responsabilidades para la restauración están claramente definidos | D26: =IF(ISBLANK('Paso 2. Evaluar los factores'!E33),"",'Paso 2. Evaluar los factores'!E33) | I26: • Crear una plataforma o comité de restauración de ecosistemas a nivel nacional, estatal, local o de cuenca hidrográfica que articule los roles y responsabilidades entre las entidades gubernamentales, de la sociedad civil, académicas y del sector privado y otras partes interesadas relevantes.
C27: 21. Se mantiene una coordinación institucional eficaz | D27: =IF(ISBLANK('Paso 2. Evaluar los factores'!E34),"",'Paso 2. Evaluar los factores'!E34) | I27: • Dentro del gobierno, crear un Grupo de Trabajo interministerial sobre Restauración de Ecosistemas encargado de coordinar las actividades gubernamentales (nacional, estatal y municipal) en materia de restauración. • Crear una iniciativa de restauración con múltiples partes interesadas que establezca la visión y coordine las actividades de restauración en todo el paisaje (por ejemplo, el PACT del Bosque Atlántico de Brasil).
B28: Condición habilitante | C28: Factor clave | D28: Respuesta | E28: Estrategias para subsanar las deficiencias en las condiciones habilitantes | F28: Nacional | G28: Regional | H28: Local | I28: Ejemplos de estrategias para abordar las brechas en factores clave
A29: Implementar | B29: j. Liderazgo | C29: 22. Existen lideres nacionales y/o locales de restauración | D29: =IF(ISBLANK('Paso 2. Evaluar los factores'!E36),"",'Paso 2. Evaluar los factores'!E36) | I29: • Cultivar, apoyar y dar voz a los posibles lideres locales de la restauración (individuos, organizaciones). • Convocar reuniones de lideres locales de la restauración de múltiples ubicaciones (incluso afuera del área candidata) para que se inspiren mutuamente y compartan las mejores prácticas.
C30: 23. Existe un compromiso político sostenido | D30: =IF(ISBLANK('Paso 2. Evaluar los factores'!E37),"",'Paso 2. Evaluar los factores'!E37) | I30: • Crear y movilizar un electorado amplio (que represente a múltiples sectores, incluida la agricultura) que mantenga la restauración en la agenda política nacional.
B31: k. Conocimiento | C31: 24. Existen "conocimientos técnicos" de restauración pertinentes para el área candidata | D31: =IF(ISBLANK('Paso 2. Evaluar los factores'!E38),"",'Paso 2. Evaluar los factores'!E38) | I31: • Crear programas de restauración de ecosistemas en universidades y escuelas de agricultura. • Priorizar la restauración de ecosistemas en los programas públicos y privados de subvenciones para investigación. • Construir puentes entre investigadores y profesionales de la restauración para que los primeros generen investigaciones prácticas que se apliquen en el paisaje.
C32: 25. El "saber hacer" de la restauración se transfiere a través de homólogos o servicios de extensión | D32: =IF(ISBLANK('Paso 2. Evaluar los factores'!E39),"",'Paso 2. Evaluar los factores'!E39) | I32: • Facilitar reuniones entre agricultores y la interacción en materia de restauración. • Establecer indicadores clave de desempeño relacionados con la restauración de ecosistemas para los agentes de extensión. • Aumentar la financiación para la capacitación en restauración de ecosistemas dentro de los servicios de extensión. • Incluir asistencia técnica para la restauración como parte de los paquetes de financiamiento agrícola para los agricultores. • Utilizar tecnologías modernas de información y comunicación para conectar mejor a los agentes de extensión y a los administradores de tierras, y para proporcionar a ambos la investigación y la información más actualizadas.
B33: l. Diseño técnico | C33: 26. El diseño de la restauración tiene una base técnica y adaptada al cambio climático | D33: =IF(ISBLANK('Paso 2. Evaluar los factores'!E40),"",'Paso 2. Evaluar los factores'!E40) | I33: • Desarrollar un plan de restauración basado en la mejor ciencia y teniendo en cuenta el cambio climático. • Revisar los planes de restauración de experiencias de restauración exitosas en otros lugares para obtener conocimientos sobre las mejores prácticas.
C34: 27. La restauración limita las "fugas" | D34: =IF(ISBLANK('Paso 2. Evaluar los factores'!E41),"",'Paso 2. Evaluar los factores'!E41) | I34: • Introducir medidas que aumenten la productividad por hectárea de cultivos, ganado o madera de las tierras agrícolas y forestales existentes. • Introducir medidas que reduzcan la demanda de cultivos, ganado o madera.
B35: m. Financiamiento e incentivos | C35: 28. Los incentivos positivos y los fondos para la restauración superan a los incentivos negativos | D35: =IF(ISBLANK('Paso 2. Evaluar los factores'!E42),"",'Paso 2. Evaluar los factores'!E42) | I35: • Introducir mecanismos de financiación dedicados a la restauración de ecosistemas, como: - Subvenciones - Préstamos a bajo interés - Exenciones fiscales (sobre los insumos, los productos o la financiación de la restauración) - Gasto público directo - Políticas de contratación pública - Pagos por servicios ecosistémicos (por ejemplo, agua, carbono) - Eliminar o reducir los incentivos que desincentivan la regeneración forestal o arbórea • Utilizar evaluaciones de los flujos de financiamiento público a sectores clave, como la agricultura o la silvicultura, para identificar dónde pueden estar ocurriendo impactos no deseados y perjudiciales para el medio ambiente. Los flujos de financiación pueden incluir subvenciones o incentivos, entre otros.
C36: 29. Hay financiación disponible para acciones de restauración | D36: =IF(ISBLANK('Paso 2. Evaluar los factores'!E43),"",'Paso 2. Evaluar los factores'!E43) | I36: • Comunicar y publicitar activamente la disponibilidad de incentivos financieros y oportunidades de financiación mediante una difusión accesible y específica. • Brindar asistencia técnica y administrativa a las partes interesadas y a los usuarios de la tierra para apoyar los procesos de solicitud, cumplimiento y presentación de informes. • Simplificar los procedimientos de solicitud y reducir los requisitos administrativos y de documentación para disminuir las barreras de acceso a incentivos y fondos.
B37: n. Retroalimentación | C37: 30. Existe un sistema eficaz de monitoreo para el seguimiento | D37: =IF(ISBLANK('Paso 2. Evaluar los factores'!E44),"",'Paso 2. Evaluar los factores'!E44) | I37: • Siempre que sea posible, establecer una línea de base (por ejemplo, fotografías, imágenes satelitales, datos sobre hectáreas y otras mediciones del paisaje tal como es) para permitir comparaciones a lo largo del tiempo. • Desarrollar e implementar un sistema de monitoreo del desempeño (incluyendo monitoreo por teledetección y monitoreo participativo a nivel del terreno).
C38: 31. Se comunican los éxitos tempranos y continuos | D38: =IF(ISBLANK('Paso 2. Evaluar los factores'!E45),"",'Paso 2. Evaluar los factores'!E45) | I38: • Comunicar públicamente el progreso de la restauración, las historias de éxito y las lecciones aprendidas. Asegúrese de que las historias conectan con el público destinatario (por ejemplo, imágenes de progreso, historias de beneficios para las personas).
B12562: X
B12563: No aplicable

Sheet Tabla resumen
A1: TABLA RESUMEN DEL DIAGNÓSTICO DE RESTAURACIÓN
A3: Verde = EN FUNCIONAMIENTO | D3: Resumen: | F3: Autor: Entidad coordinadora y año
A4: Amarillo = PARCIALMENTE EN FUNCIONAMIENTO | D4: Texto provisional para que el usuario describa el alcance de esta evaluación, incluyendo los límites geográficos, el periodo de tiempo considerado para la restauración y los objetivos de la restauración en esta ubicación. El alcance puede establecerse a nivel nacional o definirse en función de un paisaje de referencia, y puede incluir procesos de consulta pertinentes para las jurisdicciones implicadas en la planificación de la restauración.
A5: Rojo = NO EN FUNCIONAMIENTO
A7: Tema | B7: Condición habilitante | D7: Factor clave | E7: Respuesta | F7: Estrategias futuras para abordar las brechas
A8: Motivar | B8: a. Beneficios | D8: La restauración genera beneficios económicos | E8: =IF(ISBLANK('Paso 2. Evaluar los factores'!E13),"",'Paso 2. Evaluar los factores'!E13) | F8: ='Paso 3. Proponer estrategias'!E6 -> 0
D9: La restauración genera beneficios sociales | E9: =IF(ISBLANK('Paso 2. Evaluar los factores'!E14),"",'Paso 2. Evaluar los factores'!E14) | F9: ='Paso 3. Proponer estrategias'!E7 -> 0
D10: La restauración genera beneficios ambientales | E10: =IF(ISBLANK('Paso 2. Evaluar los factores'!E15),"",'Paso 2. Evaluar los factores'!E15) | F10: ='Paso 3. Proponer estrategias'!E8 -> 0
B11: b. Conscientización | D11: Los beneficios de la restauración se comunican públicamente | E11: =IF(ISBLANK('Paso 2. Evaluar los factores'!E16),"",'Paso 2. Evaluar los factores'!E16) | F11: ='Paso 3. Proponer estrategias'!E9 -> 0
D12: Se identifican oportunidades de restauración | E12: =IF(ISBLANK('Paso 2. Evaluar los factores'!E17),"",'Paso 2. Evaluar los factores'!E17) | F12: ='Paso 3. Proponer estrategias'!E10 -> 0
B13: c. Eventos de crisis | D13: Los eventos de crisis se aprovechan | E13: =IF(ISBLANK('Paso 2. Evaluar los factores'!E18),"",'Paso 2. Evaluar los factores'!E18) | F13: ='Paso 3. Proponer estrategias'!E11 -> 0
B14: d. Requisitos legales | D14: Existen leyes y políticas que exigen la restauración | E14: =IF(ISBLANK('Paso 2. Evaluar los factores'!E19),"",'Paso 2. Evaluar los factores'!E19) | F14: ='Paso 3. Proponer estrategias'!E12 -> 0
D15: Las leyes y políticas que exigen la restauración se comprenden y aplican ampliamente | E15: =IF(ISBLANK('Paso 2. Evaluar los factores'!E20),"",'Paso 2. Evaluar los factores'!E20) | F15: ='Paso 3. Proponer estrategias'!E13 -> 0
A17: Habilitar | B17: e. Condiciones ecológicas | D17: Las condiciones del suelo, el agua, el clima y fuego son adecuadas para la restauración. | E17: =IF(ISBLANK('Paso 2. Evaluar los factores'!E22),"",'Paso 2. Evaluar los factores'!E22) | F17: ='Paso 3. Proponer estrategias'!E15 -> 0
D18: Se reducen al mínimo las plantas y animales que pueden obstaculizar la restauración | E18: =IF(ISBLANK('Paso 2. Evaluar los factores'!E23),"",'Paso 2. Evaluar los factores'!E23) | F18: ='Paso 3. Proponer estrategias'!E16 -> 0
D19: Semillas nativas, plántulas o poblaciones de origen están fácilmente disponibles | E19: =IF(ISBLANK('Paso 2. Evaluar los factores'!E24),"",'Paso 2. Evaluar los factores'!E24) | F19: ='Paso 3. Proponer estrategias'!E17 -> 0
B20: f. Condiciones económicas | D20: Gestión de otras actividades que se contraponen a la restauración. | E20: =IF(ISBLANK('Paso 2. Evaluar los factores'!E25),"",'Paso 2. Evaluar los factores'!E25) | F20: ='Paso 3. Proponer estrategias'!E18 -> 0
D21: Existen cadenas de valor y/o mercados para productos básicos (madera, productos agrícolas) y productos ambientales (carbono, agua, biodiversidad) de áreas restauradas. | E21: =IF(ISBLANK('Paso 2. Evaluar los factores'!E26),"",'Paso 2. Evaluar los factores'!E26) | F21: ='Paso 3. Proponer estrategias'!E19 -> 0
B22: g. Condiciones de las políticas | D22: Los usuarios de tierras, los propietarios de tierras o las comunidades tienen derechos de tenencia seguros sobre la tierra y los recursos naturales de la tierra. | E22: =IF(ISBLANK('Paso 2. Evaluar los factores'!E27),"",'Paso 2. Evaluar los factores'!E27) | F22: ='Paso 3. Proponer estrategias'!E20 -> 0
D23: Se armonizan y racionalizan las políticas que afectan a la restauración | E23: =IF(ISBLANK('Paso 2. Evaluar los factores'!E28),"",'Paso 2. Evaluar los factores'!E28) | F23: ='Paso 3. Proponer estrategias'!E21 -> 0
D24: Existen restricciones a la tala, degradación o perturbación de los ecosistemas naturales restantes (bosques, pastizales, humedales). | E24: =IF(ISBLANK('Paso 2. Evaluar los factores'!E29),"",'Paso 2. Evaluar los factores'!E29) | F24: ='Paso 3. Proponer estrategias'!E22 -> 0
D25: Se aplican restricciones a la tala de los ecosistemas naturales restantes (por ejemplo, bosques, pastizales, humedales). | E25: =IF(ISBLANK('Paso 2. Evaluar los factores'!E30),"",'Paso 2. Evaluar los factores'!E30) | F25: ='Paso 3. Proponer estrategias'!E23 -> 0
B26: h. Condiciones sociales y culturales | D26: Las mujeres, los jóvenes y los pueblos indígenas participan en la toma de decisiones sobre restauración | E26: =IF(ISBLANK('Paso 2. Evaluar los factores'!E31),"",'Paso 2. Evaluar los factores'!E31) | F26: ='Paso 3. Proponer estrategias'!E24 -> 0
D27: La población local se beneficia de la restauración | E27: =IF(ISBLANK('Paso 2. Evaluar los factores'!E32),"",'Paso 2. Evaluar los factores'!E32) | F27: ='Paso 3. Proponer estrategias'!E25 -> 0
B28: i. Condiciones institucionales | D28: Los roles y responsabilidades para la restauración están claramente definidos | E28: =IF(ISBLANK('Paso 2. Evaluar los factores'!E33),"",'Paso 2. Evaluar los factores'!E33) | F28: ='Paso 3. Proponer estrategias'!E26 -> 0
D29: Se mantiene una coordinación institucional eficaz | E29: =IF(ISBLANK('Paso 2. Evaluar los factores'!E34),"",'Paso 2. Evaluar los factores'!E34) | F29: ='Paso 3. Proponer estrategias'!E27 -> 0
A31: Implementar | B31: j. Liderazgo | D31: Existen lideres nacionales y/o locales de restauración | E31: =IF(ISBLANK('Paso 2. Evaluar los factores'!E36),"",'Paso 2. Evaluar los factores'!E36) | F31: ='Paso 3. Proponer estrategias'!E29 -> 0
D32: Existe un compromiso político sostenido | E32: =IF(ISBLANK('Paso 2. Evaluar los factores'!E37),"",'Paso 2. Evaluar los factores'!E37) | F32: ='Paso 3. Proponer estrategias'!E30 -> 0
B33: k. Conocimiento | D33: Existen "conocimientos técnicos" de restauración pertinentes para el área candidata | E33: =IF(ISBLANK('Paso 2. Evaluar los factores'!E38),"",'Paso 2. Evaluar los factores'!E38) | F33: ='Paso 3. Proponer estrategias'!E31 -> 0
D34: El "saber hacer" de la restauración se transfiere a través de homólogos o servicios de extensión | E34: =IF(ISBLANK('Paso 2. Evaluar los factores'!E39),"",'Paso 2. Evaluar los factores'!E39) | F34: ='Paso 3. Proponer estrategias'!E32 -> 0
B35: l. Diseño técnico | D35: El diseño de la restauración tiene una base técnica y adaptada al cambio climático | E35: =IF(ISBLANK('Paso 2. Evaluar los factores'!E40),"",'Paso 2. Evaluar los factores'!E40) | F35: ='Paso 3. Proponer estrategias'!E33 -> 0
D36: La restauración limita las "fugas" | E36: =IF(ISBLANK('Paso 2. Evaluar los factores'!E41),"",'Paso 2. Evaluar los factores'!E41) | F36: ='Paso 3. Proponer estrategias'!E34 -> 0
B37: m. Financiamiento e incentivos | D37: Los incentivos positivos y los fondos para la restauración superan a los incentivos negativos | E37: =IF(ISBLANK('Paso 2. Evaluar los factores'!E42),"",'Paso 2. Evaluar los factores'!E42) | F37: ='Paso 3. Proponer estrategias'!E35 -> 0
D38: Hay financiación disponible para acciones de restauración | E38: =IF(ISBLANK('Paso 2. Evaluar los factores'!E43),"",'Paso 2. Evaluar los factores'!E43)
B39: n. Retroalimentación | D39: Existe un sistema eficaz de monitoreo para el seguimiento | E39: =IF(ISBLANK('Paso 2. Evaluar los factores'!E44),"",'Paso 2. Evaluar los factores'!E44) | F39: ='Paso 3. Proponer estrategias'!E37 -> 0
D40: Se comunican los éxitos tempranos y continuos | E40: =IF(ISBLANK('Paso 2. Evaluar los factores'!E45),"",'Paso 2. Evaluar los factores'!E45) | F40: ='Paso 3. Proponer estrategias'!E38 -> 0
