Workbook

Sheet Instructions
A1: INSTRUCTIONS
A3: Welcome to The Restoration Diagnostic Assessment Tool. This Excel-based tool is designed to help decision makers, managers and analysts identify which key success factors for forest landscape restoration are already in place, which are partially in place, and which are missing within a country or landscape being considered for restoration. The tool accompanies The Restoration Diagnostic, which can be found at www.wri.org/restorationdiagnostic.
A5: The tool consists of three questionnaire tabs (Diagnostic - Motivate, Diagnostic - Enable, Diagnostic - Implement) and a summary table. The three questionnaire tabs help decision makers and restoration supporters analyze the existence of key success factors within a current or future restoration project. In particular, it helps them focus their efforts on the most important factors to get in place before large amounts of human, financial, or political capital are invested. When applied periodically every few years once a restoration effort is underway, this tool can help implementers adjust and refine their policies and practices as a means of adaptive management.
A7: To complete the questionnaire tabs:
B8: ● | C8: Select the each questionnaire tab and complete individually
B9: ● | C9: Answer the "key success factors" questions for each category (motivate, enable, implement) by selecting from the dropdown menu. There are 31 questions in total, with the answer options being "yes," "partly," and "no." These answers will correspond to colors on the summary table on the final tab.
B10: ● | C10: Record any clarifying comments, information, or data that support your answers in column H. This information will help justify responses, serve as a reminder of underlying rationale, or highlight where significant data gaps exist.
A12: As the questionnaire tabs are completed, responses automatically appear on the Summary Table
A14: See The Restoration Diagnostic: A method for developing forest landscape restoration strategies by rapidly assessing the status of key success factors to find suggested sources of information for answering these questions.
C19: Prepared by

Sheet Diagnostic - Motivation
A1: Motivate: Decision makers, landowners, and/or citizens are inspired or motivated to catalyze processes that lead to forest landscape restoration
B3: Feature | C3: Key Success Factor | D3: Definition | E3: Comment | F3: Diagnostic question | G3: Response | H3: Notes on Response | I3: Follow up question(s) | J3: Follow up response(s) | K3: Examples of strategies to address gap in key success factor
B4: a. Benefits | C4: Restoration generates economic benefits | D4: Restoring the candidate landscape is expected to yield economic benefits (e.g., economic diversification, avoided damages, new marketable products) that create a net positive financial impact (private benefits) and/or net positive economic impact (public benefits) relative to the status quo land use. | E4: • Review Table 4 (in the Restoration Diagnostic) to identify possible economic benefits. • The financial case for restoration is made when restoration increases the land manager’s discounted net cash flows relative to the status quo, or where restoration would help achieve a public goal at less cost than the best alternative approach. • The economic case for restoration is made when the full suite of market and nonmarket benefits of restoration would outweigh the costs of undertaking the restoration. • Some landowners may be concerned that “restoration” means they will lose their land outright, lose user rights to the land, and/or lose money relative to the status quo. Therefore, one needs to articulate why this would not the case or how the net benefits outweigh the costs. • Be sure to understand and articulate (in “notes” column) who the economic beneficiaries would be. | F4: • Is restoring the candidate landscape expected to generate economic benefits that result in a net positive financial or economic impact relative to the status quo land use? | H4: • If “yes”, then what are the expected economic benefits? • If “yes”, then who benefits? • If “no”, then how big is the expected financial or economic gap? | I4: • If “yes”, then what are the expected economic benefits? • If “yes”, then who benefits? • If “no”, then how big is the expected financial or economic gap? | J4: · | K4: • Conduct a benefit-cost analysis comparing (a) likely benefits generated from the restored landscape, (b) likely costs of restoring the candidate landscape, and (c) likely costs and benefits of the status quo use of the landscape.
C5: Restoration generates social benefits | D5: Restoring the candidate landscape is expected to yield social, cultural, and/or political benefits. | E5: • Review Table 4 (in the Restoration Diagnostic) to identify possible social benefits. • Restoration can be beneficial to countries or communities with a historical cultural connection to forests (e.g., forest-based traditions and folklore, forest-based livelihoods and employment). • Restoration can be a way for governments to be seen as leaders on the global stage. • Restoration can be a way for governments to meet commitments to international agreements (e.g., UNFCCC and REDD+, UNCCD, CBD, Bonn Challenge). • Be sure to understand and articulate (in “notes” column) who the social beneficiaries would be. | F5: • Is restoring the candidate landscape expected to generate social benefits? | H5: • If “yes”, then what are the expected social benefits? | I5: • If “yes”, then what are the expected social benefits? | J5: · | K5: • Engage communities living in and around the candidate landscape to identify which social benefits could be generated if the landscape were restored in a certain manner.
C6: Restoration generates environmental benefits | D6: Restoring the candidate landscape is expected to yield environmental benefits. | E6: • Review Table 4 (in the Restoration Diagnostic) to identify possible environmental benefits. • In most conceivable situations, this key success factor will be met. | F6: • Is restoring the candidate landscape expected to generate any environmental benefits? | H6: • If “yes”, then what are the expected environmental benefits? | I6: • If “yes”, then what are the expected environmental benefits? | J6: · | K6: • Engage scientists (e.g., biologists, ecologists, hydrologists, soil scientists) to identify which environmental benefits could be generated if the landscape were restored in a certain manner.
B7: b. Awareness | C7: Benefits of restoration are publicly communicated | D7: Benefits that would arise from the candidate landscape being restored have been clearly identified and communicated to land managers, the public, and other relevant stakeholders. | E7: • Review Table 4 (in the Restoration Diagnostic) to identify possible benefits. • Peer-to-peer (e.g., farmer-to-farmer) communication of the benefits of restoration can be an effective means of raising awareness and motivating action. People tend to trust those most like themselves. • Communication efforts that are targeted toward specific audiences may be more effective than those targeted at general audiences. | F7: • Are the benefits that would arise from the candidate landscape being restored clearly identified and communicated to stakeholders and the public? | H7: • What benefits might arise? • Which stakeholders would benefit? | I7: • What benefits might arise? • Which stakeholders would benefit? | J7: · | K7: • Conduct awareness-raising campaigns via newspapers, radio, television, internet, and/or site visits. • Introduce and/or leverage existing national tree planting days as well as school tree planting programs.
C8: Opportunities for restoration are identified | D8: Candidate areas for restoration have been identified and quantified. | E8: • Maps generated via both remote sensing (e.g., aerial photos, satellite imagery) and ground-based observations can identify, record, and communicate candidate areas of restoration. • One common way to quantify candidate areas is in terms of hectares. | F8: • Have candidate areas for restoration been identified and quantified? | H8: • If “yes”, then where are the candidate areas? • If “yes”, then how big is the restoration opportunity? | I8: • If “yes”, then where are the candidate areas? • If “yes”, then how big is the restoration opportunity? | J8: · | K8: • Conduct a “Restoration Opportunities Assessment Method” (see Box 2 in the Restoration Diagnostic).
B9: c. Crisis events | C9: Crisis events are leveraged | D9: The government and/or civil society use the risk or occasion of crisis events to build political and public support for forest landscape restoration. | E9: • Crisis events can include floods, landslides, droughts, sandstorms, wood shortages, declining crop yields, and unemployment. They include humanitarian catastrophes where damage could have been avoided if forest landscapes had been healthy (e.g., landslide), where the act of restoration mitigates the crisis (e.g., unemployment), or where restoration prevents future crises (e.g., floods). • One does not desire these events to occur. But when they do, restoration supporters should act quickly to mobilize political and community support for restoration. | F9: • Is the region experiencing a crisis event, or the risk of one, that would motivate restoration in the candidate landscape? | H9: • What types of crises have occurred in the candidate landscape in the past? • What types of crises could occur in the future? | I9: • What types of crises have occurred in the candidate landscape in the past? • What types of crises could occur in the future? | J9: · | K9: • Conduct and communicate research that quantifies and visualizes the degree to which restored forest landscapes can prevent or mitigate natural humanitarian disasters. • When disasters occur, immediately publicly communicate the benefits of restoration.
B10: d. Legal requirements | C10: Law requiring restoration exists | D10: The government has legislation that requires land managers to allow tree recovery or to replant trees in forest areas that have been cleared in the candidate landscape. | E10: • Restoration requirements are more likely to be directed at entities involved with commercial logging, mining, or other extractive activities than for subsistence activities. • Although some stakeholders might perceive a “legal requirement” to restore trees as an enabling condition for forest landscape restoration, by definition a “requirement” is designed to motivate action. • Government mandates for restoration can trigger sensitivities about government incursion into land-use decisions that otherwise would be the purview of traditional communities or private landowners. Therefore, how legal requirements are communicated and complemented by other policies, incentives, and practices can be important to the success of the requirement. | F10: • Does the government have a law requiring land owners or managers to replant or restore trees in forest areas that have been cleared? | H10: • If “yes”, what specific terms and conditions does the law have (e.g., what to restore, by when, how)? | I10: • If “yes”, what specific terms and conditions does the law have (e.g., what to restore, by when, how)? | J10: · | K10: • Establish government law (or industry policy) that requires land managers to allow tree recovery or to replant trees in areas that have been cleared due to their own commercial activity (e.g., logging).
C11: Law requiring restoration is broadly understood and enforced | D11: The law requiring tree recovery or replanting in the candidate landscape is understood by relevant actors and is enforced in a visible, credible, and fair manner. | E11: • It is not sufficient that a law requiring restoration merely exists; the law needs to be understood by affected entities and enforced by authorities if it is to motivate restoration. | F11: • Is the law requiring tree or forest restoration broadly understood by relevant actors and enforced in a visible, credible, and fair manner? | H11: • If “no”, then what is the nature of the shortcoming? | I11: • If “no”, then what is the nature of the shortcoming? | J11: · | K11: • Conduct communication campaign to make relevant actors aware of restoration requirements. • Take enforcement action (e.g., fines, denial of credit access, jail) against violations of restoration requirements. • Ensure human and financial resources for enforcement are adequate.

Sheet Diagnostic - Enable
A1: Enable: Enabling conditions are in place that create a favorable context for forest landscape restoration
B3: Feature | C3: Key Success Factor | D3: Definition | E3: Comment | F3: Diagnostic question | G3: Response | H3: Notes on response | I3: Follow up question(s) | J3: Follow up response(s) | K3: Examples of strategies to address gap in key success factor
B4: e. Ecological conditions | C4: Soil, water, climate, and fire conditions are suitable for restoration | D4: The candidate landscape’s soil, rainfall, and temperature conditions are suitable for forest regrowth, and the fire regime does not hinder forest regrowth. | E4: • This key success factor combines multiple physical conditions affecting forest regrowth. Each condition (soil, rainfall, temperature, fire) should be evaluated on its own, yet the response can reflect the aggregate of the four. | F4: • Are the candidate landscape’s soil, rainfall, temperature, and fire conditions suitable for enabling trees to regrow? | H4: · | I4: • If “no”, then what are the gaps in physical suitability? | J4: · | K4: • Adaptively manage or adjust restoration plan (e.g., species mix) to match water and climate regime of landscape. • Launch program to reduce unwanted fires. • Launch program to improve soil quality (e.g., plant nitrogen-fixing trees and bushes).
C5: Plants and animals that can impede restoration are absent | D5: The candidate landscape is free of unwanted plants (e.g., persistent invasive species) and unwanted animals (e.g., uncontrolled grazing livestock) that can hinder tree growth or recovery. | E5: • Examples include Brachiaria spp. in Brazil, Imperata cylindrica in Indonesia, kudzu in southern United States, and uncontrolled ruminants (cattle, sheep, goats) in multiple locations. • Landscapes can be free of unwanted plants and/or unwanted animals either because none ever existed naturally in the landscape or because they have been successfully removed through human intervention. | F5: • Is the candidate landscape free of unwanted plants and unwanted animals that could hinder tree recovery? | H5: · | I5: • If “no”, then what are the problematic plant and/or animal species? | J5: · | K5: • Implement program to remove invasive plants (e.g., using fast-growing native trees to create shade, using goats, appropriately applying herbicides). • Implement program to remove unwanted roaming livestock (e.g., incentives and training for fences).
C6: Native seeds, seedlings, or sources populations are readily available | D6: The candidate landscape has source populations (e.g., sizable patches of remnant native trees), underground root systems, animal dispersal agents, or low-cost sources of native tree seeds and seedlings that can be the foundation for forest regrowth. | E6: • Viable source populations or underground root systems of native trees are critically important for passive restoration. • This key success factor applies to the entire supply chain for native seeds and seedling, including seed production, seed collection, and seedling nurseries. | F6: • Does the candidate landscape have source populations, underground root systems, or low-cost sources of native tree seeds and seedlings that can be the foundation for forest regrowth? | H6: · | I6: • If “no”, then where is the gap (e.g., seeds, seed collectors, nurseries, source populations, underground root systems)? | J6: · | K6: • Establish laws protecting remaining tracts of native trees in candidate landscape. • Create financial incentives and training programs aimed at increasing the number and quality of seedling nurseries.
B7: f. Market conditions | C7: Competing demands (e.g., food, fuel) for degraded forestlands are declining | D7: Demand for crop, livestock, fuel wood, and/or biofuel production on degraded or former forestlands in the candidate landscape is declining (e.g., due to productivity improvements elsewhere), thereby “freeing up” land for forest restoration. | E7: • This key success factor is arguably one of the most important of them all in light of increasing global demand for land to generate crops, livestock, and biofuel (Searchinger et al. 2013). • This key success factor does not apply in cases where lands are restored into agroforestry or silvopastoral systems. In those systems, the restored lands also supply crops and livestock, respectively. | F7: • Is demand for crop, livestock, fuel wood, and/or biofuel production on degraded or former forestlands in the candidate landscape declining? | H7: · | I7: • What are the main alternative competing land uses for the candidate areas to be restored? | J7: · | K7: • Pursue technical and financial measures to increase the productivity (yields per hectare) of crops and livestock on existing nonmarginal agricultural land. • Pursue technical and financial measures to increase the supply of timber from sustainably managed plantations and of nonbiomass renewable energy. • Avoid establishing bioenergy targets that could lead to degraded or former forestlands being converted to biomass plantations.
C8: Value chains for products from restored areas exists | D8: To the degree that forest restoration in the candidate landscape generates marketable products and services, value chains are in place allowing these products to get from the restored forest to the end consumer. | E8: • This key success factor does not apply in cases where there is no intention to harvest or collect any marketable forest products. • This key success factor refers to both market access and market demand for products and services derived from restored forest landscapes. • “Value chain” includes steps such as harvesting, collecting, processing, transporting, and distributing forest products. • Markets include those for nonconsumptive forest benefits, too, such as recreation, tourism, and watershed protection. | F8: • Are value chains in place allowing products from restored forests to reach end consumers? | H8: · | I8: • If “no”, then where is the value chain gap? | J8: · | K8: • Encourage growth of markets (both supply and demand) for timber and nontimber forest products sustainably derived from restored forest landscapes. • Provide low-interest financing for businesses directly involved in the “restoration value chain.”
B9: g. Policy conditions | C9: Land and natural resource tenure are secure | D9: Those who manage the candidate landscape have clear and secure rights (e.g., in the form of land ownership or natural resource management rights) to the benefits that would accrue from restoring trees. | E9: • Lack of (or insecure) land tenure and natural resource rights can discourage restoration that involves human intervention. People will not invest in planting trees or allow trees to return to lands they manage if it is not clear that they have secure rights to the benefit from the restored trees. • Tenure and natural resource rights can be in the form of private land ownership, communal lands, user-right certificates, etc. • Be sure that the tenure that is in place does not infringe on customary rights. | F9: • Do those who manage the candidate landscape have clear and secure rights to the benefits that would accrue from restoring trees? | H9: · | I9: • If “no”, then what rights are missing, and for whom? | J9: · | K9: • Reform policies to ensure that land managers have clear and secure rights to land and the natural resources (e.g., trees) on their land.
C10: Policies affecting restoration are aligned and streamlined | D10: Relevant public policies are aligned, streamlined (e.g., not too bureaucratic), and mutually reinforcing to support forest restoration in the candidate landscape. | E10: • Policies to consider include those on agriculture, extractive industries, water, and natural resources. • In some cases nature conservation policies might inhibit restoration (e.g., laws forbidding extraction of native seeds from protected areas, laws forbidding harvesting native tree species). • In some cases regulations and paperwork might make implementation of restoration too cumbersome, time consuming, or difficult, especially for small land managers or owners. | F10: • Are policies that may affect forest restoration in the candidate landscape aligned and streamlined? | H10: · | I10: • If “no”, then which policies are not aligned or streamlined? | J10: · | K10: • Conduct an assessment to identify existing policies that might affect the efficacy and efficiency of forest landscape restoration, determine whether or not each is mutually supportive, and recommend policy reforms to achieve greater alignment.
C11: Restrictions on clearing remaining natural forests exist | D11: The candidate landscape has laws restricting clearing or cutting of remaining natural forests. | E11: • Restrictions on clearing remaining natural forests can prevent further expansion of degraded or cleared forest areas, thereby enabling net forest gain. These restrictions also create an incentive to restore the productivity of already cleared areas since access to the forest frontier is reduced. • These restrictions can take the form of a specific share of land that must remain under forest cover (e.g., Brazil’s Forest Code), an extensive network of national parks and national forests, an extensive network of forested indigenous territories, communal lands having forest protection rules, “no net forest loss” rules, and more. • An important component of this key success factor is that “natural forests” have been clearly defined by the jurisdiction sponsoring the restriction (e.g., national government). This definition should include primary forests, secondary forests, and degraded forests with potential for restoration. | F11: • Does the candidate landscape have laws restricting the clearing or cutting of remaining natural forests? | H11: · | I11: • If “yes”, then what are those laws? | J11: · | K11: • Establish laws that restrict cutting or clearing of remaining natural forests.
C12: Forest clearing restrictions are enforced | D12: Laws that restrict clearing of remaining natural forests are adequately enforced. | E12: • It is not sufficient that regulations restricting clearing of remaining natural forests merely exist; the restrictions need to be enforced by relevant authorities. • Particularly in remote areas, enforcement is in part a function of the capacity of law enforcement organizations and incentives for them to do their jobs. | F12: • Are these clearing or cutting restrictions adequately enforced? | H12: · | I12: • If “no”, then why not? | J12: · | K12: • Conduct communication campaign to make relevant actors aware of law. • Establish a forest cover change monitoring system to identify illegal clearing. • Take enforcement action (e.g., fines, denial of credit access) against violations of law. • Ensure human and financial resources for enforcement are adequate.
B13: h. Social conditions | C13: Local people are empowered to make decisions about restoration | D13: People living in and around the candidate landscape are empowered to become involved in the design of the forest restoration program, help define restoration goals, and play a role in management. | E13: • Unless local people are empowered, the ones whose land management practices need to change will have little stake in the success of restoration. • Leveraging existing local institutions and processes (e.g., forestry cooperatives via villages with customary tenure) can facilitate local participation and uptake. • Empowerment requires effective participation, as well as accountability regarding decisions that are taken and grievance mechanisms when these processes break down. | F13: • Are people living in and around the candidate landscape empowered to become involved in making decisions about restoration (e.g., program design, goal-setting, management)? | H13: · | I13: • If “no”, then what aspects are people not empowered to do? | J13: · | K13: • Involve representatives from people living in and around the candidate landscape in the restoration process (goal-setting, design, implementation, progress updates). • Cultivate restoration champion from local communities.
C14: Local people are able to benefit from restoration | D14: People who live in or around the candidate landscape can capture or enjoy the benefits from restoration (e.g., improved water quality, increased supply of forest products) or have alternative means of livelihood. | E14: • This key success factor is about who enjoys or captures the benefits―local people. The key success factors within the “benefits” in Table 2 (in the Restoration Diagnostic), on the other hand, are about the existence and types of benefits, regardless of who enjoys or captures them. • This key success factor is arguably one of the most important for any type of assisted regeneration. If local people do not benefit, then they will have little incentive to change behaviors to enable forest landscape restoration or sustain the restored landscape over the long term. | F14: • Are people living in and around the candidate landscape able to capture or enjoy the benefits generated by restoration? | H14: · | I14: • If “no”, then why not? | J14: · | K14: • Allow local people to harvest some of the forest products from the restored landscape. • Ensure that financial flows for the goods and/or services generated by the restored landscape (e.g., payments for ecosystem services) go to people living in and around the restored landscape.
B15: i. Institutional conditions | C15: Roles and responsibilities for restoration are clearly defined | D15: Roles and responsibilities for forest restoration in the candidate landscape are clearly defined, understood among relevant actors (e.g., government, civil society, private sector), and coupled with authority. | E15: • In the absence of such clarity and coordination, inaction may occur due to important roles not being filled or due to institutions claiming overlapping responsibility. • To adequately answer this question, users may need to map out the roles and responsibilities of actors. Be sure to recognize both vertical and horizontal relationships between entities. | F15: • Are the roles and responsibilities for forest restoration in the candidate landscape clearly defined, understood among relevant actors, and coupled with authority? | H15: · | I15: • If “no”, then what is missing in terms of clarity of roles and responsibilities? | J15: · | K15: • Create a national, state, or watershed Forest Landscape Restoration Plan that articulates roles and responsibilities among government, civil society, academic, and private sector entities.
C16: Effective institutional coordination is in place | D16: Relevant actors from government, civil society, and/or the private sector are sufficiently coordinated to design, implement, and monitor forest restoration in the candidate landscape. | E16: • Coordination might need to be between government agencies (e.g., ministries such as agriculture, environment, forestry, and development); between national, state, and municipal governments; or between government, nongovernmental organizations, and companies, to name a few. | F16: • Are relevant actors from government, civil society, and/or the private sector sufficiently coordinated to design, implement, and monitor forest restoration in the candidate landscape? | H16: · | I16: • If “no”, then what is missing in terms of coordination? | J16: · | K16: • Within government, create an interministerial Forest Landscape Restoration Task Force charged with coordinating government (national, state, municipal) activities on restoration. • Create a multisector stakeholder restoration initiative that sets the vision and coordinates restoration activities across the landscape (e.g., the Brazilian Atlantic Forest PACT).

Sheet Diagnostic - Implement
A1: Implement: Capacity and resources exist and are effectively mobilized to implement on-the-ground forest landscape restoration
B3: Feature | C3: Key Success Factor | D3: Definition | E3: Comment | F3: Diagnostic question | G3: Response | H3: Notes on response | I3: Follow up question(s) | J3: Follow up response(s) | K3: Examples of strategies to address gap in key success factor | L3: Notes on response | M3: Follow up question(s) | N3: Follow up response(s) | O3: Examples of strategies to address gap in key success factor
B4: j. Leadership | C4: National and/or local restoration champions exist | D4: Charismatic people (or powerful institutions) exist who can effectively inspire decision makers to pursue restoration, mobilize support, and maintain momentum over time in the candidate landscape. | E4: • Champions can be individuals or organizations. • Champions can play a role in both the “motivate” and “implement” theme. • Some landscapes may already have one or more champions. For others, champions may need to be cultivated and given a visible profile. • Most successful case examples (see case examples) had either a champion or strong government support. Few lacked both. | F4: • Is there a charismatic, committed champion(s) of restoration for the candidate landscape? | H4: · | I4: • Who is the champion(s)? | J4: · | K4: • Cultivate, support, and give a voice to prospective restoration champions (individuals, organizations). • Convene meetings of champions and prospective champions from multiple locations (even outside the candidate landscape) so they inspire each other and share best practices. | L4: · | M4: • Who is the champion(s)? | N4: · | O4: • Cultivate, support, and give a voice to prospective restoration champions (individuals, organizations). • Convene meetings of champions and prospective champions from multiple locations (even outside the candidate landscape) so they inspire each other and share best practices.
C5: Sustained political commitment exists | D5: Commitment from government (at multiple levels if relevant) and nongovernmental institutions to restoration in the candidate landscape exists and is sustained. | E5: • It may be difficult to assess the long-term commitment of an institution a priori. In such situations, consider factors such as whether or not the commitment transcends political parties and whether or not the benefits of restoration would be enjoyed by common citizens and powerful interests (if so, government commitment is likely to be more long term). | F5: • Is there expressed, long-term commitment from government and nongovernmental institutions to restoration in the candidate landscape? | H5: · | I5: • If “yes”, what is the proof of the expressed commitment, and from whom? | J5: · | K5: • Create and mobilize a broad constituency (representing multiple sectors including agriculture) that keeps restoration on the national political agenda. | L5: · | M5: • If “yes”, what is the proof of the expressed commitment, and from whom? | N5: · | O5: • Create and mobilize a broad constituency (representing multiple sectors including agriculture) that keeps restoration on the national political agenda.
B6: k. Knowledge | C6: Restoration "know how" relevant to candidate landscapes exist | D6: Local experts know of or generate research into restoration techniques (e.g., natural and assisted regeneration, traditional knowledge) tailored to the candidate landscape. | E6: • Local expertise can come from traditional knowledge from communities living in or around the landscape, experts from universities and rural extension services, and nongovernmental organizations active in the field. • The know-how may be generated locally or might be imported from elsewhere but communicated or delivered by local practitioners. | F6: • Does local knowledge on how to implement restoration at scale in the candidate landscape exist? | H6: · | I6: • If “no”, then what are the most important knowledge gaps? | J6: · | K6: • Create programs on forest landscape restoration in universities and agriculture schools. • Prioritize forest landscape restoration in public and private research grant-making programs. • Build bridges between researchers and restoration practitioners so the former generate actionable research that is applied in the landscape. | L6: · | M6: • If “no”, then what are the most important knowledge gaps? | N6: · | O6: • Create programs on forest landscape restoration in universities and agriculture schools. • Prioritize forest landscape restoration in public and private research grant-making programs. • Build bridges between researchers and restoration practitioners so the former generate actionable research that is applied in the landscape.
C7: Restoration "know how" transferred via peers or extension services | D7: Technical assistance and rural extension (“extension services”), farmer-to-farmer visits, and/or other means of awareness raising and capacity building for restoration are in place and adequately resourced in the candidate landscape. | E7: • Land managers may need training and other forms of capacity building on the “why” and “how” of restoration. • Training can occur via participatory workshops, person-to-person meetings, newsletters, videos, and other means. • “Farmer-to-farmer” or “land-manager-to-land-manager” communication can be one of the most effective means of education and training. People tend to trust those who are most like themselves. | F7: • Are extension services, farmer-to-farmer visits, and/or other means of awareness raising and capacity building for restoration in place and adequately resourced in the candidate landscape? | H7: · | I7: • For the candidate landscape, which entities are best positioned to deliver extension services? | J7: · | K7: • Facilitate farmer-to-farmer meetings and interaction regarding restoration. • Set key performance indicators related to forest landscape restoration for extension agents. • Increase funding for forest landscape restoration training within extension services. • Include restoration technical assistance as part of agriculture financing packages to farmers. • Utilize modern information and communication technologies to better connect extension agents and land managers, and to provide both with the most up-to-date research and information. | L7: · | M7: • For the candidate landscape, which entities are best positioned to deliver extension services? | N7: · | O7: • Facilitate farmer-to-farmer meetings and interaction regarding restoration. • Set key performance indicators related to forest landscape restoration for extension agents. • Increase funding for forest landscape restoration training within extension services. • Include restoration technical assistance as part of agriculture financing packages to farmers. • Utilize modern information and communication technologies to better connect extension agents and land managers, and to provide both with the most up-to-date research and information.
B8: l.Technical design | C8: Restoration design is technically grounded and climate resilient | D8: The forest landscape restoration plan for the candidate landscape is based on best practices, incorporating the best available science and climate-smart approaches. | E8: • “Best practices” in this context refers to the approaches for forest landscape restoration that are informed by scientific research and/or local experience and that have demonstrated success at facilitating restoration. In some regions, written “best practice” guidance may be available from universities, NGOs, or extension agencies, but in others it will not. • For active restoration, the technical design needs to address aspects such as site preparation, species selection, tree spacing, and maintenance factors. • For passive restoration, the technical design needs to address aspects such as how to remove pressures preventing trees from naturally regrowing (e.g., livestock, fire). • Restoration plans should factor in projected climate change in order to be climate resilient. | F8: • Is the forest restoration plan for the candidate landscape based on best practices, incorporating the best available science and climate-smart approaches? | H8: · | I8: • If “no”, then what is missing from the plan? | J8: · | K8: • Develop a forest landscape restoration plan informed by the best science and factoring in climate change. • Review restoration plans of successful restoration experiences elsewhere to gain insights on best practice. | L8: · | M8: • If “no”, then what is missing from the plan? | N8: · | O8: • Develop a forest landscape restoration plan informed by the best science and factoring in climate change. • Review restoration plans of successful restoration experiences elsewhere to gain insights on best practice.
C9: Restoration limits "leakage" | D9: Forest landscape restoration in the candidate landscape avoids transferring forest clearing activities to other locations (“leakage”), resulting in net increase in forest landscape area. | E9: • There is a risk that forest landscape restoration in the candidate landscape could result in transferring, “exporting,” or “outsourcing” to other areas or countries those activities that were causing deforestation, forest degradation, or otherwise keeping trees off the candidate landscape. • While such “leakage” might result in an increase in the amount of forest area in the candidate landscape, it would result in a loss of forest area elsewhere. From a global perspective, this loss could negate in part or in whole the gross forest gain from the candidate landscape. For example, Meyfroidt and Lambin (2011) recount an analysis of land use displacement triggered by forest restoration in seven countries experiencing a forest transition in recent decades (i.e., Bhutan, Chile, China, Costa Rica, El Salvador, India, and Vietnam). Since the advent of net forest regrowth in these seven nations, an area equivalent to 22 percent of their restored forest area underwent land use displacement in other countries. This displaced area increased to 52 percent between 2003 and 2007. A portion (not specified) of this displacement triggered deforestation. • The historic forest landscape restoration case examples assessed during the development of this Diagnostic did not have in place measures to limit leakage. Going forward, however, limiting leakage will be an important key success factor if forest landscape restoration is to lead to a net global increase in forest area and quality. | F9: Does the forest landscape restoration process have in place measures (e.g., policies, practices, incentives, yield improvements) that limit leakage or is unfolding in a manner that leakage is limited? | H9: · | I9: • If “no”, then what measures are missing from the restoration process? | J9: · | K9: • Introduce measures that increase the productivity per hectare of crops, livestock, or timber from existing agricultural and forestry lands • Introduce measures that decrease demand for crops, livestock, or timber | L9: · | M9: • If “no”, then what measures are missing from the restoration process? | N9: · | O9: • Introduce measures that increase the productivity per hectare of crops, livestock, or timber from existing agricultural and forestry lands • Introduce measures that decrease demand for crops, livestock, or timber
B10: m. Finance and incentives | C10: Positive incentives and funds for restoration outweigh negative incentives | D10: From the perspective of the land manager, financial incentives and funds for restoration of the candidate landscape exist and are sufficient to outweigh the financial incentives for activities that prevent trees from regrowing. | E10: • “Positive” incentives are those that can encourage forest landscape restoration. They can include (but are not limited to): grants, loans, tax breaks (on the inputs, outputs, or financing of restoration), direct government expenditures (e.g., subsidies, procurement policies), payments for ecosystem services, or private markets for goods and services. • “Negative” incentives are those that prevent forests or trees from regrowing on a landscape. They can include (but are not limited to): grants, loans, tax breaks, and direct government expenditures supporting livestock, agriculture, and extractive industries. • In some circumstances, both positive and negative financial incentives may exist but if the latter outweigh the former, restoration will not likely occur at scale. • Consider not only the amount but also the timing of the finance and incentives. • Incentives and finance fall under the “implementation” theme (and not the “enable” theme) because they refer to cash flows going to land managers in a manner that influences whether or not they implement measures to restore trees. | F10: • Do the incentives and funds that promote restoration outweigh those that prevent forest or tree regrowth from the land manager’s perspective in the candidate landscape? | H10: · | I10: • What are the relevant positive and negative incentives? • What is the scale of these incentives from a land manager’s perspective (e.g., $/hectare)? | J10: · | K10: • Introduce forest landscape restoration-dedicated financing mechanisms, such as: - Grants - Low-interest loans - Tax breaks (on the inputs, outputs, or financing of restoration) - Direct government expenditures - Government procurement policies - Payments for ecosystem services (e.g., water, carbon) • Remove or reduce incentives that discourage forest or tree regrowth | L10: · | M10: • What are the relevant positive and negative incentives? • What is the scale of these incentives from a land manager’s perspective (e.g., $/hectare)? | N10: · | O10: • Introduce forest landscape restoration-dedicated financing mechanisms, such as: - Grants - Low-interest loans - Tax breaks (on the inputs, outputs, or financing of restoration) - Direct government expenditures - Government procurement policies - Payments for ecosystem services (e.g., water, carbon) • Remove or reduce incentives that discourage forest or tree regrowth
C11: Incentives and funds are readily accessible | D11: Financial incentives and funds for restoration in the candidate landscape are available without excessive hurdles or bureaucracy for the relevant land managers or communities. | E11: • In some situations, financial incentives and funds for restoration may be available but accessing them can be difficult. For instance, funding availability may not be sufficiently advertised, the application process may be too technical for small landowners, the amount of paperwork may be too bureaucratic, and the eligibility criteria may preclude a large share of land managers most needed for large-scale restoration. | F11: • Are the financial incentives and funds designed to promote restoration in the candidate landscape readily accessible to the relevant land managers or communities? | H11: · | I11: • If “no”, then what are the barriers to access? | J11: · | K11: • Advertise the availability of incentives and funds. • Provide administrative support to land managers to apply for incentives and funds. • Reduce amount of paperwork for applying for incentives. | L11: · | M11: • If “no”, then what are the barriers to access? | N11: · | O11: • Advertise the availability of incentives and funds. • Provide administrative support to land managers to apply for incentives and funds. • Reduce amount of paperwork for applying for incentives.
B12: n. Feedback | C12: Effective performance monitoring and evaluation system is in place | D12: A system for monitoring progress and evaluating impact of restoration in the candidate landscape exists. | E12: • Performance monitoring systems were absent from most historic case examples. Nonetheless, since decision makers today are increasingly attuned to performance monitoring, having such systems in the future is an important key success factor. • Aspects to monitor could include (but are not limited to) hectares undergoing restoration, tree survival rates, and quantified benefits to people and wildlife. • Monitoring and evaluation systems can use remote sensing, crowd-sourced ground-level monitoring (using community and NGO volunteers and modern information communication technologies), and surveys of inhabitants of the candidate landscape. | F12: • Does the candidate landscape have a performance monitoring system in place for tracking and evaluating restoration progress? | H12: · | I12: • If “yes”, is baseline data already being gathered? • If “no”, what aspects of a performance monitoring system are missing? | J12: · | K12: • Whenever possible, establish a baseline (e.g., photos, satellite imagery, data on hectares and other measurements from the landscape as it is) to enable comparisons over time. • Develop and implement a performance monitoring system (including remote sensing monitoring and ground-level participatory monitoring). | L12: · | M12: • If “yes”, is baseline data already being gathered? • If “no”, what aspects of a performance monitoring system are missing? | N12: · | O12: • Whenever possible, establish a baseline (e.g., photos, satellite imagery, data on hectares and other measurements from the landscape as it is) to enable comparisons over time. • Develop and implement a performance monitoring system (including remote sensing monitoring and ground-level participatory monitoring).
C13: Early wins are communicated | D13: Early restoration successes in the candidate landscape are communicated to stakeholders. | E13: • Achieving and publicly communicating early success or “early wins” can help maintain momentum, recruit more engagement, trigger replication elsewhere in the landscape, shore up political support, and sustain external financing. • Visits between farmers or land managers are one approach that seems to work for communicating successes. If one’s neighbor has a positive experience with restoration, then one is more likely to adopt the same practices. • Showing “before” and “after” images and leveraging demonstration sites can be effective ways to showcase progress. | F13: • Are early restoration successes being communicated in the candidate landscape? | H13: · | I13: • If “yes”, how are the successes communicated (e.g., through what media)? • If “no”, what media are available that could be utilized? | J13: · | K13: • Publicly communicate restoration progress, success stories, and lessons learned. Ensure the stories connect with the target audiences (e.g., images of progress, stories of benefits to people). | L13: · | M13: • If “yes”, how are the successes communicated (e.g., through what media)? • If “no”, what media are available that could be utilized? | N13: · | O13: • Publicly communicate restoration progress, success stories, and lessons learned. Ensure the stories connect with the target audiences (e.g., images of progress, stories of benefits to people).

Sheet Summary
A1: RESTORATION DIAGNOSTIC SUMMARY TABLE
A3: GREEN= IN PLACE
A4: YELLOW= PARTLY IN PLACE
A5: RED= NOT IN PLACE
A7: Theme | B7: Feature | D7: Key success factor | E7: Response
A8: Motivate | B8: a. Benefits | D8: Restoration generates economic benefits | E8: ='Diagnostic - Motivation'!G4 -> 0
D9: Restoration generates social benefits | E9: ='Diagnostic - Motivation'!G5 -> 0
D10: Restoration generates environmental benefits | E10: ='Diagnostic - Motivation'!G6 -> 0
B11: b. Awareness | D11: Benefits of restoration are publicly communicated | E11: ='Diagnostic - Motivation'!G7 -> 0
D12: Opportunities for restoration are identified | E12: ='Diagnostic - Motivation'!G8 -> 0
B13: c. Crisis events | D13: Crisis events are leveraged | E13: ='Diagnostic - Motivation'!G9 -> 0
B14: d. Legal requirements | D14: Law requiring restoration exists | E14: ='Diagnostic - Motivation'!G10 -> 0
D15: Law requiring restoration is broadly understood and enforced | E15: ='Diagnostic - Motivation'!G11 -> 0
A17: Enable | B17: e. Ecological conditions | D17: Soil, water, climate, and fire conditions are suitable for restoration | E17: ='Diagnostic - Enable'!G4 -> 0
D18: Plants and animals that can impede restoration are absent | E18: ='Diagnostic - Enable'!G5 -> 0
D19: Native seeds, seedlings, or sources populations are readily available | E19: ='Diagnostic - Enable'!G6 -> 0
B20: f. Market conditions | D20: Competing demands (e.g., food, fuel) for degraded forestlands are declining | E20: ='Diagnostic - Enable'!G7 -> 0
D21: Value chains for products from restored areas exists | E21: ='Diagnostic - Enable'!G8 -> 0
B22: g. Policy conditions | D22: Land and natural resource tenure are secure | E22: ='Diagnostic - Enable'!G9 -> 0
D23: Policies affecting restoration are aligned and streamlined | E23: ='Diagnostic - Enable'!G10 -> 0
D24: Restrictions on clearing remaining natural forests exist | E24: ='Diagnostic - Enable'!G11 -> 0
D25: Forest clearing restrictions are enforced | E25: ='Diagnostic - Enable'!G12 -> 0
B26: h. Social conditions | D26: Local people are empowered to make decisions about restoration | E26: ='Diagnostic - Enable'!G13 -> 0
D27: Local people are able to benefit from restoration | E27: ='Diagnostic - Enable'!G14 -> 0
B28: i. Institutional conditions | D28: Roles and responsibilities for restoration are clearly defined | E28: ='Diagnostic - Enable'!G15 -> 0
D29: Effective institutional coordination is in place | E29: ='Diagnostic - Enable'!G16 -> 0
A31: Implement | B31: j. Leadership | D31: National and/or local restoration champions exist | E31: ='Diagnostic - Implement'!G4 -> 0
D32: Sustained political commitment exists | E32: ='Diagnostic - Implement'!G5 -> 0
B33: k. Knowledge | D33: Restoration "know how" relevant to candidate landscapes exist | E33: ='Diagnostic - Implement'!G6 -> 0
D34: Restoration "know how" transferred via peers or extension services | E34: ='Diagnostic - Implement'!G7 -> 0
B35: l. Technical design | D35: Restoration design is technically grounded and climate resilient | E35: ='Diagnostic - Implement'!G8 -> 0
D36: Restoration limits "leakage" | E36: ='Diagnostic - Implement'!G9 -> 0
B37: m. Finance and incentives | D37: Positive incentives and funds for restoration outweigh negative incentives | E37: ='Diagnostic - Implement'!G10 -> 0
D38: Incentives and funds are readily accessible | E38: ='Diagnostic - Implement'!G11 -> 0
B39: n. Feedback | D39: Effective performance monitoring and evaluation system is in place | E39: ='Diagnostic - Implement'!G12 -> 0
D40: Early wins are communicated | E40: ='Diagnostic - Implement'!G13 -> 0
